Workbook

Sheet EVIDENCE_ENTRY
A1: OPENINTEL EVIDENCE ENTRY TEMPLATE | H1: Tag each claim · Score auto-calculates | O1: Schema.org Convergence Fields
A2: CLAIM_ID | B2: CLAIM_TEXT | C2: CASE_REF | D2: SOURCE | E2: DB_TAG | F2: TIER | G2: URL | H2: DATE_ACCESSED | I2: VERIFICATION | J2: CORROBORATION | K2: NOTES | L2: AUTHOR_NAME | M2: AUTHOR_ORG | N2: ITEM_REVIEWED | O2: REVIEW_RATING | P2: DATE_PUBLISHED | Q2: DATE_REVIEWED | R2: POSITIVE_NOTES | S2: NEGATIVE_NOTES | U2: COMPLETE | V2: QUALITY | W2: CONSIST | X2: COMPOSITE | Y2: PROMO GATE
A3: CLAIM-001 | U3: =IF(COUNTA(A3:S3)=0,"",ROUND((COUNTA(B3:S3)/18)*100,0)) -> 0 | V3: =IF(F3="","",IF(F3="T1",100,IF(F3="T2",80,IF(F3="T3",60,IF(F3="T4",35,IF(F3="T5",15,IF(F3="N",50,0))))))) | W3: =IF(OR(A3="",E3=""),"",_xlfn.LET(_xlpm.tag_valid,COUNTIF(EVIDENCE_TAXONOMY!F4:F46,E3)>0,_xlpm.tier_filled,F3<>"",_xlpm.status_valid,OR(I3="verified",I3="pending",I3="disputed",I3="unverifiable",I3=""),_xlpm.corr_ok,IF(OR(F3="T4",F3="T5"),J3>0,TRUE),_xlpm.checks,_xlpm.tag_valid+_xlpm.tier_filled+_xlpm.status_valid+_xlpm.corr_ok,ROUND((_xlpm.checks/4)*100,0))) | X3: =IF(AND(U3<>"",V3<>"",W3<>""),ROUND((U3*0.3+V3*0.4+W3*0.3),0),IF(U3<>"",U3,"")) -> 0 | Y3: =IF(B3="","",_xlfn.LET(_xlpm.core_filled,AND(B3<>"",E3<>"",F3<>"",G3<>"",I3<>""),_xlpm.author_ok,OR(L3<>"",M3<>""),_xlpm.rating_ok,O3<>"",_xlpm.corr_ok,IF(OR(F3="T4",F3="T5"),J3>=2,TRUE),_xlpm.quality_ok,V3>=60,_xlpm.composite_ok,X3>=65,_xlpm.gates_pass,AND(_xlpm.core_filled,_xlpm.author_ok,_xlpm.rating_ok,_xlpm.corr_ok,_xlpm.quality_ok,_xlpm.composite_ok),IF(_xlpm.gates_pass,"✅ READY","❌ BLOCKED")))
A4: CLAIM-002 | U4: =IF(COUNTA(A4:S4)=0,"",ROUND((COUNTA(B4:S4)/18)*100,0)) -> 0 | V4: =IF(F4="","",IF(F4="T1",100,IF(F4="T2",80,IF(F4="T3",60,IF(F4="T4",35,IF(F4="T5",15,IF(F4="N",50,0))))))) | W4: =IF(OR(A4="",E4=""),"",_xlfn.LET(_xlpm.tag_valid,COUNTIF(EVIDENCE_TAXONOMY!F4:F46,E4)>0,_xlpm.tier_filled,F4<>"",_xlpm.status_valid,OR(I4="verified",I4="pending",I4="disputed",I4="unverifiable",I4=""),_xlpm.corr_ok,IF(OR(F4="T4",F4="T5"),J4>0,TRUE),_xlpm.checks,_xlpm.tag_valid+_xlpm.tier_filled+_xlpm.status_valid+_xlpm.corr_ok,ROUND((_xlpm.checks/4)*100,0))) | X4: =IF(AND(U4<>"",V4<>"",W4<>""),ROUND((U4*0.3+V4*0.4+W4*0.3),0),IF(U4<>"",U4,"")) -> 0 | Y4: =IF(B4="","",_xlfn.LET(_xlpm.core_filled,AND(B4<>"",E4<>"",F4<>"",G4<>"",I4<>""),_xlpm.author_ok,OR(L4<>"",M4<>""),_xlpm.rating_ok,O4<>"",_xlpm.corr_ok,IF(OR(F4="T4",F4="T5"),J4>=2,TRUE),_xlpm.quality_ok,V4>=60,_xlpm.composite_ok,X4>=65,_xlpm.gates_pass,AND(_xlpm.core_filled,_xlpm.author_ok,_xlpm.rating_ok,_xlpm.corr_ok,_xlpm.quality_ok,_xlpm.composite_ok),IF(_xlpm.gates_pass,"✅ READY","❌ BLOCKED")))
A5: CLAIM-003 | U5: =IF(COUNTA(A5:S5)=0,"",ROUND((COUNTA(B5:S5)/18)*100,0)) -> 0 | V5: =IF(F5="","",IF(F5="T1",100,IF(F5="T2",80,IF(F5="T3",60,IF(F5="T4",35,IF(F5="T5",15,IF(F5="N",50,0))))))) | W5: =IF(OR(A5="",E5=""),"",_xlfn.LET(_xlpm.tag_valid,COUNTIF(EVIDENCE_TAXONOMY!F5:F47,E5)>0,_xlpm.tier_filled,F5<>"",_xlpm.status_valid,OR(I5="verified",I5="pending",I5="disputed",I5="unverifiable",I5=""),_xlpm.corr_ok,IF(OR(F5="T4",F5="T5"),J5>0,TRUE),_xlpm.checks,_xlpm.tag_valid+_xlpm.tier_filled+_xlpm.status_valid+_xlpm.corr_ok,ROUND((_xlpm.checks/4)*100,0))) | X5: =IF(AND(U5<>"",V5<>"",W5<>""),ROUND((U5*0.3+V5*0.4+W5*0.3),0),IF(U5<>"",U5,"")) -> 0 | Y5: =IF(B5="","",_xlfn.LET(_xlpm.core_filled,AND(B5<>"",E5<>"",F5<>"",G5<>"",I5<>""),_xlpm.author_ok,OR(L5<>"",M5<>""),_xlpm.rating_ok,O5<>"",_xlpm.corr_ok,IF(OR(F5="T4",F5="T5"),J5>=2,TRUE),_xlpm.quality_ok,V5>=60,_xlpm.composite_ok,X5>=65,_xlpm.gates_pass,AND(_xlpm.core_filled,_xlpm.author_ok,_xlpm.rating_ok,_xlpm.corr_ok,_xlpm.quality_ok,_xlpm.composite_ok),IF(_xlpm.gates_pass,"✅ READY","❌ BLOCKED")))
A6: CLAIM-004 | U6: =IF(COUNTA(A6:S6)=0,"",ROUND((COUNTA(B6:S6)/18)*100,0)) -> 0 | V6: =IF(F6="","",IF(F6="T1",100,IF(F6="T2",80,IF(F6="T3",60,IF(F6="T4",35,IF(F6="T5",15,IF(F6="N",50,0))))))) | W6: =IF(OR(A6="",E6=""),"",_xlfn.LET(_xlpm.tag_valid,COUNTIF(EVIDENCE_TAXONOMY!F6:F48,E6)>0,_xlpm.tier_filled,F6<>"",_xlpm.status_valid,OR(I6="verified",I6="pending",I6="disputed",I6="unverifiable",I6=""),_xlpm.corr_ok,IF(OR(F6="T4",F6="T5"),J6>0,TRUE),_xlpm.checks,_xlpm.tag_valid+_xlpm.tier_filled+_xlpm.status_valid+_xlpm.corr_ok,ROUND((_xlpm.checks/4)*100,0))) | X6: =IF(AND(U6<>"",V6<>"",W6<>""),ROUND((U6*0.3+V6*0.4+W6*0.3),0),IF(U6<>"",U6,"")) -> 0 | Y6: =IF(B6="","",_xlfn.LET(_xlpm.core_filled,AND(B6<>"",E6<>"",F6<>"",G6<>"",I6<>""),_xlpm.author_ok,OR(L6<>"",M6<>""),_xlpm.rating_ok,O6<>"",_xlpm.corr_ok,IF(OR(F6="T4",F6="T5"),J6>=2,TRUE),_xlpm.quality_ok,V6>=60,_xlpm.composite_ok,X6>=65,_xlpm.gates_pass,AND(_xlpm.core_filled,_xlpm.author_ok,_xlpm.rating_ok,_xlpm.corr_ok,_xlpm.quality_ok,_xlpm.composite_ok),IF(_xlpm.gates_pass,"✅ READY","❌ BLOCKED")))
A7: CLAIM-005 | U7: =IF(COUNTA(A7:S7)=0,"",ROUND((COUNTA(B7:S7)/18)*100,0)) -> 0 | V7: =IF(F7="","",IF(F7="T1",100,IF(F7="T2",80,IF(F7="T3",60,IF(F7="T4",35,IF(F7="T5",15,IF(F7="N",50,0))))))) | W7: =IF(OR(A7="",E7=""),"",_xlfn.LET(_xlpm.tag_valid,COUNTIF(EVIDENCE_TAXONOMY!F7:F49,E7)>0,_xlpm.tier_filled,F7<>"",_xlpm.status_valid,OR(I7="verified",I7="pending",I7="disputed",I7="unverifiable",I7=""),_xlpm.corr_ok,IF(OR(F7="T4",F7="T5"),J7>0,TRUE),_xlpm.checks,_xlpm.tag_valid+_xlpm.tier_filled+_xlpm.status_valid+_xlpm.corr_ok,ROUND((_xlpm.checks/4)*100,0))) | X7: =IF(AND(U7<>"",V7<>"",W7<>""),ROUND((U7*0.3+V7*0.4+W7*0.3),0),IF(U7<>"",U7,"")) -> 0 | Y7: =IF(B7="","",_xlfn.LET(_xlpm.core_filled,AND(B7<>"",E7<>"",F7<>"",G7<>"",I7<>""),_xlpm.author_ok,OR(L7<>"",M7<>""),_xlpm.rating_ok,O7<>"",_xlpm.corr_ok,IF(OR(F7="T4",F7="T5"),J7>=2,TRUE),_xlpm.quality_ok,V7>=60,_xlpm.composite_ok,X7>=65,_xlpm.gates_pass,AND(_xlpm.core_filled,_xlpm.author_ok,_xlpm.rating_ok,_xlpm.corr_ok,_xlpm.quality_ok,_xlpm.composite_ok),IF(_xlpm.gates_pass,"✅ READY","❌ BLOCKED")))
A8: CLAIM-006 | U8: =IF(COUNTA(A8:S8)=0,"",ROUND((COUNTA(B8:S8)/18)*100,0)) -> 0 | V8: =IF(F8="","",IF(F8="T1",100,IF(F8="T2",80,IF(F8="T3",60,IF(F8="T4",35,IF(F8="T5",15,IF(F8="N",50,0))))))) | W8: =IF(OR(A8="",E8=""),"",_xlfn.LET(_xlpm.tag_valid,COUNTIF(EVIDENCE_TAXONOMY!F8:F50,E8)>0,_xlpm.tier_filled,F8<>"",_xlpm.status_valid,OR(I8="verified",I8="pending",I8="disputed",I8="unverifiable",I8=""),_xlpm.corr_ok,IF(OR(F8="T4",F8="T5"),J8>0,TRUE),_xlpm.checks,_xlpm.tag_valid+_xlpm.tier_filled+_xlpm.status_valid+_xlpm.corr_ok,ROUND((_xlpm.checks/4)*100,0))) | X8: =IF(AND(U8<>"",V8<>"",W8<>""),ROUND((U8*0.3+V8*0.4+W8*0.3),0),IF(U8<>"",U8,"")) -> 0 | Y8: =IF(B8="","",_xlfn.LET(_xlpm.core_filled,AND(B8<>"",E8<>"",F8<>"",G8<>"",I8<>""),_xlpm.author_ok,OR(L8<>"",M8<>""),_xlpm.rating_ok,O8<>"",_xlpm.corr_ok,IF(OR(F8="T4",F8="T5"),J8>=2,TRUE),_xlpm.quality_ok,V8>=60,_xlpm.composite_ok,X8>=65,_xlpm.gates_pass,AND(_xlpm.core_filled,_xlpm.author_ok,_xlpm.rating_ok,_xlpm.corr_ok,_xlpm.quality_ok,_xlpm.composite_ok),IF(_xlpm.gates_pass,"✅ READY","❌ BLOCKED")))
A9: CLAIM-007 | U9: =IF(COUNTA(A9:S9)=0,"",ROUND((COUNTA(B9:S9)/18)*100,0)) -> 0 | V9: =IF(F9="","",IF(F9="T1",100,IF(F9="T2",80,IF(F9="T3",60,IF(F9="T4",35,IF(F9="T5",15,IF(F9="N",50,0))))))) | W9: =IF(OR(A9="",E9=""),"",_xlfn.LET(_xlpm.tag_valid,COUNTIF(EVIDENCE_TAXONOMY!F9:F51,E9)>0,_xlpm.tier_filled,F9<>"",_xlpm.status_valid,OR(I9="verified",I9="pending",I9="disputed",I9="unverifiable",I9=""),_xlpm.corr_ok,IF(OR(F9="T4",F9="T5"),J9>0,TRUE),_xlpm.checks,_xlpm.tag_valid+_xlpm.tier_filled+_xlpm.status_valid+_xlpm.corr_ok,ROUND((_xlpm.checks/4)*100,0))) | X9: =IF(AND(U9<>"",V9<>"",W9<>""),ROUND((U9*0.3+V9*0.4+W9*0.3),0),IF(U9<>"",U9,"")) -> 0 | Y9: =IF(B9="","",_xlfn.LET(_xlpm.core_filled,AND(B9<>"",E9<>"",F9<>"",G9<>"",I9<>""),_xlpm.author_ok,OR(L9<>"",M9<>""),_xlpm.rating_ok,O9<>"",_xlpm.corr_ok,IF(OR(F9="T4",F9="T5"),J9>=2,TRUE),_xlpm.quality_ok,V9>=60,_xlpm.composite_ok,X9>=65,_xlpm.gates_pass,AND(_xlpm.core_filled,_xlpm.author_ok,_xlpm.rating_ok,_xlpm.corr_ok,_xlpm.quality_ok,_xlpm.composite_ok),IF(_xlpm.gates_pass,"✅ READY","❌ BLOCKED")))
A10: CLAIM-008 | U10: =IF(COUNTA(A10:S10)=0,"",ROUND((COUNTA(B10:S10)/18)*100,0)) -> 0 | V10: =IF(F10="","",IF(F10="T1",100,IF(F10="T2",80,IF(F10="T3",60,IF(F10="T4",35,IF(F10="T5",15,IF(F10="N",50,0))))))) | W10: =IF(OR(A10="",E10=""),"",_xlfn.LET(_xlpm.tag_valid,COUNTIF(EVIDENCE_TAXONOMY!F10:F52,E10)>0,_xlpm.tier_filled,F10<>"",_xlpm.status_valid,OR(I10="verified",I10="pending",I10="disputed",I10="unverifiable",I10=""),_xlpm.corr_ok,IF(OR(F10="T4",F10="T5"),J10>0,TRUE),_xlpm.checks,_xlpm.tag_valid+_xlpm.tier_filled+_xlpm.status_valid+_xlpm.corr_ok,ROUND((_xlpm.checks/4)*100,0))) | X10: =IF(AND(U10<>"",V10<>"",W10<>""),ROUND((U10*0.3+V10*0.4+W10*0.3),0),IF(U10<>"",U10,"")) -> 0 | Y10: =IF(B10="","",_xlfn.LET(_xlpm.core_filled,AND(B10<>"",E10<>"",F10<>"",G10<>"",I10<>""),_xlpm.author_ok,OR(L10<>"",M10<>""),_xlpm.rating_ok,O10<>"",_xlpm.corr_ok,IF(OR(F10="T4",F10="T5"),J10>=2,TRUE),_xlpm.quality_ok,V10>=60,_xlpm.composite_ok,X10>=65,_xlpm.gates_pass,AND(_xlpm.core_filled,_xlpm.author_ok,_xlpm.rating_ok,_xlpm.corr_ok,_xlpm.quality_ok,_xlpm.composite_ok),IF(_xlpm.gates_pass,"✅ READY","❌ BLOCKED")))
A11: CLAIM-009 | U11: =IF(COUNTA(A11:S11)=0,"",ROUND((COUNTA(B11:S11)/18)*100,0)) -> 0 | V11: =IF(F11="","",IF(F11="T1",100,IF(F11="T2",80,IF(F11="T3",60,IF(F11="T4",35,IF(F11="T5",15,IF(F11="N",50,0))))))) | W11: =IF(OR(A11="",E11=""),"",_xlfn.LET(_xlpm.tag_valid,COUNTIF(EVIDENCE_TAXONOMY!F11:F53,E11)>0,_xlpm.tier_filled,F11<>"",_xlpm.status_valid,OR(I11="verified",I11="pending",I11="disputed",I11="unverifiable",I11=""),_xlpm.corr_ok,IF(OR(F11="T4",F11="T5"),J11>0,TRUE),_xlpm.checks,_xlpm.tag_valid+_xlpm.tier_filled+_xlpm.status_valid+_xlpm.corr_ok,ROUND((_xlpm.checks/4)*100,0))) | X11: =IF(AND(U11<>"",V11<>"",W11<>""),ROUND((U11*0.3+V11*0.4+W11*0.3),0),IF(U11<>"",U11,"")) -> 0 | Y11: =IF(B11="","",_xlfn.LET(_xlpm.core_filled,AND(B11<>"",E11<>"",F11<>"",G11<>"",I11<>""),_xlpm.author_ok,OR(L11<>"",M11<>""),_xlpm.rating_ok,O11<>"",_xlpm.corr_ok,IF(OR(F11="T4",F11="T5"),J11>=2,TRUE),_xlpm.quality_ok,V11>=60,_xlpm.composite_ok,X11>=65,_xlpm.gates_pass,AND(_xlpm.core_filled,_xlpm.author_ok,_xlpm.rating_ok,_xlpm.corr_ok,_xlpm.quality_ok,_xlpm.composite_ok),IF(_xlpm.gates_pass,"✅ READY","❌ BLOCKED")))
A12: CLAIM-010 | U12: =IF(COUNTA(A12:S12)=0,"",ROUND((COUNTA(B12:S12)/18)*100,0)) -> 0 | V12: =IF(F12="","",IF(F12="T1",100,IF(F12="T2",80,IF(F12="T3",60,IF(F12="T4",35,IF(F12="T5",15,IF(F12="N",50,0))))))) | W12: =IF(OR(A12="",E12=""),"",_xlfn.LET(_xlpm.tag_valid,COUNTIF(EVIDENCE_TAXONOMY!F12:F54,E12)>0,_xlpm.tier_filled,F12<>"",_xlpm.status_valid,OR(I12="verified",I12="pending",I12="disputed",I12="unverifiable",I12=""),_xlpm.corr_ok,IF(OR(F12="T4",F12="T5"),J12>0,TRUE),_xlpm.checks,_xlpm.tag_valid+_xlpm.tier_filled+_xlpm.status_valid+_xlpm.corr_ok,ROUND((_xlpm.checks/4)*100,0))) | X12: =IF(AND(U12<>"",V12<>"",W12<>""),ROUND((U12*0.3+V12*0.4+W12*0.3),0),IF(U12<>"",U12,"")) -> 0 | Y12: =IF(B12="","",_xlfn.LET(_xlpm.core_filled,AND(B12<>"",E12<>"",F12<>"",G12<>"",I12<>""),_xlpm.author_ok,OR(L12<>"",M12<>""),_xlpm.rating_ok,O12<>"",_xlpm.corr_ok,IF(OR(F12="T4",F12="T5"),J12>=2,TRUE),_xlpm.quality_ok,V12>=60,_xlpm.composite_ok,X12>=65,_xlpm.gates_pass,AND(_xlpm.core_filled,_xlpm.author_ok,_xlpm.rating_ok,_xlpm.corr_ok,_xlpm.quality_ok,_xlpm.composite_ok),IF(_xlpm.gates_pass,"✅ READY","❌ BLOCKED")))
A13: CLAIM-011 | U13: =IF(COUNTA(A13:S13)=0,"",ROUND((COUNTA(B13:S13)/18)*100,0)) -> 0 | V13: =IF(F13="","",IF(F13="T1",100,IF(F13="T2",80,IF(F13="T3",60,IF(F13="T4",35,IF(F13="T5",15,IF(F13="N",50,0))))))) | W13: =IF(OR(A13="",E13=""),"",_xlfn.LET(_xlpm.tag_valid,COUNTIF(EVIDENCE_TAXONOMY!F13:F55,E13)>0,_xlpm.tier_filled,F13<>"",_xlpm.status_valid,OR(I13="verified",I13="pending",I13="disputed",I13="unverifiable",I13=""),_xlpm.corr_ok,IF(OR(F13="T4",F13="T5"),J13>0,TRUE),_xlpm.checks,_xlpm.tag_valid+_xlpm.tier_filled+_xlpm.status_valid+_xlpm.corr_ok,ROUND((_xlpm.checks/4)*100,0))) | X13: =IF(AND(U13<>"",V13<>"",W13<>""),ROUND((U13*0.3+V13*0.4+W13*0.3),0),IF(U13<>"",U13,"")) -> 0 | Y13: =IF(B13="","",_xlfn.LET(_xlpm.core_filled,AND(B13<>"",E13<>"",F13<>"",G13<>"",I13<>""),_xlpm.author_ok,OR(L13<>"",M13<>""),_xlpm.rating_ok,O13<>"",_xlpm.corr_ok,IF(OR(F13="T4",F13="T5"),J13>=2,TRUE),_xlpm.quality_ok,V13>=60,_xlpm.composite_ok,X13>=65,_xlpm.gates_pass,AND(_xlpm.core_filled,_xlpm.author_ok,_xlpm.rating_ok,_xlpm.corr_ok,_xlpm.quality_ok,_xlpm.composite_ok),IF(_xlpm.gates_pass,"✅ READY","❌ BLOCKED")))
A14: CLAIM-012 | U14: =IF(COUNTA(A14:S14)=0,"",ROUND((COUNTA(B14:S14)/18)*100,0)) -> 0 | V14: =IF(F14="","",IF(F14="T1",100,IF(F14="T2",80,IF(F14="T3",60,IF(F14="T4",35,IF(F14="T5",15,IF(F14="N",50,0))))))) | W14: =IF(OR(A14="",E14=""),"",_xlfn.LET(_xlpm.tag_valid,COUNTIF(EVIDENCE_TAXONOMY!F14:F56,E14)>0,_xlpm.tier_filled,F14<>"",_xlpm.status_valid,OR(I14="verified",I14="pending",I14="disputed",I14="unverifiable",I14=""),_xlpm.corr_ok,IF(OR(F14="T4",F14="T5"),J14>0,TRUE),_xlpm.checks,_xlpm.tag_valid+_xlpm.tier_filled+_xlpm.status_valid+_xlpm.corr_ok,ROUND((_xlpm.checks/4)*100,0))) | X14: =IF(AND(U14<>"",V14<>"",W14<>""),ROUND((U14*0.3+V14*0.4+W14*0.3),0),IF(U14<>"",U14,"")) -> 0 | Y14: =IF(B14="","",_xlfn.LET(_xlpm.core_filled,AND(B14<>"",E14<>"",F14<>"",G14<>"",I14<>""),_xlpm.author_ok,OR(L14<>"",M14<>""),_xlpm.rating_ok,O14<>"",_xlpm.corr_ok,IF(OR(F14="T4",F14="T5"),J14>=2,TRUE),_xlpm.quality_ok,V14>=60,_xlpm.composite_ok,X14>=65,_xlpm.gates_pass,AND(_xlpm.core_filled,_xlpm.author_ok,_xlpm.rating_ok,_xlpm.corr_ok,_xlpm.quality_ok,_xlpm.composite_ok),IF(_xlpm.gates_pass,"✅ READY","❌ BLOCKED")))
A15: CLAIM-013 | U15: =IF(COUNTA(A15:S15)=0,"",ROUND((COUNTA(B15:S15)/18)*100,0)) -> 0 | V15: =IF(F15="","",IF(F15="T1",100,IF(F15="T2",80,IF(F15="T3",60,IF(F15="T4",35,IF(F15="T5",15,IF(F15="N",50,0))))))) | W15: =IF(OR(A15="",E15=""),"",_xlfn.LET(_xlpm.tag_valid,COUNTIF(EVIDENCE_TAXONOMY!F15:F57,E15)>0,_xlpm.tier_filled,F15<>"",_xlpm.status_valid,OR(I15="verified",I15="pending",I15="disputed",I15="unverifiable",I15=""),_xlpm.corr_ok,IF(OR(F15="T4",F15="T5"),J15>0,TRUE),_xlpm.checks,_xlpm.tag_valid+_xlpm.tier_filled+_xlpm.status_valid+_xlpm.corr_ok,ROUND((_xlpm.checks/4)*100,0))) | X15: =IF(AND(U15<>"",V15<>"",W15<>""),ROUND((U15*0.3+V15*0.4+W15*0.3),0),IF(U15<>"",U15,"")) -> 0 | Y15: =IF(B15="","",_xlfn.LET(_xlpm.core_filled,AND(B15<>"",E15<>"",F15<>"",G15<>"",I15<>""),_xlpm.author_ok,OR(L15<>"",M15<>""),_xlpm.rating_ok,O15<>"",_xlpm.corr_ok,IF(OR(F15="T4",F15="T5"),J15>=2,TRUE),_xlpm.quality_ok,V15>=60,_xlpm.composite_ok,X15>=65,_xlpm.gates_pass,AND(_xlpm.core_filled,_xlpm.author_ok,_xlpm.rating_ok,_xlpm.corr_ok,_xlpm.quality_ok,_xlpm.composite_ok),IF(_xlpm.gates_pass,"✅ READY","❌ BLOCKED")))
... A22: CLAIM-020 | U22: =IF(COUNTA(A22:S22)=0,"",ROUND((COUNTA(B22:S22)/18)*100,0)) -> 0 | V22: =IF(F22="","",IF(F22="T1",100,IF(F22="T2",80,IF(F22="T3",60,IF(F22="T4",35,IF(F22="T5",15,IF(F22="N",50,0))))))) | W22: =IF(OR(A22="",E22=""),"",_xlfn.LET(_xlpm.tag_valid,COUNTIF(EVIDENCE_TAXONOMY!F22:F64,E22)>0,_xlpm.tier_filled,F22<>"",_xlpm.status_valid,OR(I22="verified",I22="pending",I22="disputed",I22="unverifiable",I22=""),_xlpm.corr_ok,IF(OR(F22="T4",F22="T5"),J22>0,TRUE),_xlpm.checks,_xlpm.tag_valid+_xlpm.tier_filled+_xlpm.status_valid+_xlpm.corr_ok,ROUND((_xlpm.checks/4)*100,0))) | X22: =IF(AND(U22<>"",V22<>"",W22<>""),ROUND((U22*0.3+V22*0.4+W22*0.3),0),IF(U22<>"",U22,"")) -> 0 | Y22: =IF(B22="","",_xlfn.LET(_xlpm.core_filled,AND(B22<>"",E22<>"",F22<>"",G22<>"",I22<>""),_xlpm.author_ok,OR(L22<>"",M22<>""),_xlpm.rating_ok,O22<>"",_xlpm.corr_ok,IF(OR(F22="T4",F22="T5"),J22>=2,TRUE),_xlpm.quality_ok,V22>=60,_xlpm.composite_ok,X22>=65,_xlpm.gates_pass,AND(_xlpm.core_filled,_xlpm.author_ok,_xlpm.rating_ok,_xlpm.corr_ok,_xlpm.quality_ok,_xlpm.composite_ok),IF(_xlpm.gates_pass,"✅ READY","❌ BLOCKED")))
A24: ── SUMMARY METRICS ──
A25: Total Entries | B25: =COUNTA(B3:B22) -> 0 | C25: Avg Completeness | D25: =IF(COUNTA(U3:U22)=0,"-",ROUND(AVERAGE(U3:U22),0)) -> 0 | E25: Avg Quality | F25: =IFERROR(IF(COUNTA(V3:V22)=0,"-",ROUND(AVERAGE(V3:V22),0)),"-") -> - | G25: Avg Consistency | H25: =IFERROR(IF(COUNTA(W3:W22)=0,"-",ROUND(AVERAGE(W3:W22),0)),"-") -> - | I25: Composite Score | J25: =IF(COUNTA(X3:X22)=0,"-",ROUND(AVERAGE(X3:X22),0)) -> 0 | L25: Promo Ready | M25: =COUNTIF(Y3:Y22,"✅ READY") -> 0 | N25: Blocked | O25: =COUNTIF(Y3:Y22,"❌ BLOCKED") -> 0 | P25: Promo Rate | Q25: =IFERROR(ROUND(M25/(M25+O25)*100,0),"-") -> -
A26: Tier Distribution | B26: ="T1: "&COUNTIF(F3:F22,"T1")&" T2: "&COUNTIF(F3:F22,"T2")&" T3: "&COUNTIF(F3:F22,"T3")&" T4: "&COUNTIF(F3:F22,"T4")&" T5: "&COUNTIF(F3:F22,"T5")&" N: "&COUNTIF(F3:F22,"N") -> T1: 0 T2: 0 T3: 0 T4: 0 T5: 0 N: 0 | E26: Verified | F26: =COUNTIF(I3:I22,"verified") -> 0 | G26: Pending | H26: =COUNTIF(I3:I22,"pending") -> 0 | I26: Disputed | J26: =COUNTIF(I3:I22,"disputed") -> 0

Sheet SCHEMA_MAP
A1: OPENINTEL ↔ SCHEMA.ORG CONVERGENCE MAP | E1: ClaimReview · ItemList · Person · Boolean
A2: OPENINTEL FIELD | B2: SCHEMA.ORG PROPERTY | C2: SCHEMA TYPE | D2: STATUS | E2: CONVERGENCE NOTES | F2: REQUIRED?
A3: ── EXISTING FIELDS (mapped) ──
A4: CLAIM_ID | B4: identifier (Thing) | C4: Text | URL | D4: ✅ MAPPED | E4: Direct match. Our CLAIM-### format is a valid identifier. | F4: YES
A5: CLAIM_TEXT | B5: claimReviewed (ClaimReview) | C5: Text | D5: ✅ MAPPED | E5: Exact match. The specific claim being fact-checked. | F5: YES
A6: CASE_REF | B6: isPartOf (CreativeWork) | C6: CreativeWork | D6: ✅ MAPPED | E6: Links to parent case/investigation. Use case ID from CASE_TYPES sheet. | F6: NO
A7: SOURCE | B7: author (CreativeWork) | C7: Person | Org | D7: ✅ MAPPED | E7: Maps to author. For promotion, should split into AUTHOR_NAME + AUTHOR_ORG (Person schema). | F7: YES
A8: DB_TAG | B8: additionalType (Thing) | C8: Text | URL | D8: ⚡ EXTENDED | E8: Our 38-type taxonomy extends Schema.org. No equivalent in ClaimReview — we're better here. | F8: YES
A9: TIER | B9: reviewRating.ratingValue | C9: Number | D9: ⚡ EXTENDED | E9: Map T1→5, T2→4, T3→3, T4→2, T5→1, N→0 for Schema.org numeric rating. Our tiered system is richer. | F9: YES
A10: URL | B10: url (Thing) | C10: URL | D10: ✅ MAPPED | E10: Direct match. Link to source material. | F10: YES
A11: DATE_ACCESSED | B11: sdDatePublished (CreativeWork) | C11: Date | D11: ⚠️ PARTIAL | E11: Schema.org has datePublished but no dateAccessed. Keep both — add DATE_PUBLISHED for convergence. | F11: NO
A12: VERIFICATION | B12: creativeWorkStatus (CreativeWork) | C12: Text | D12: ⚡ EXTENDED | E12: Our verified/pending/disputed/unverifiable is more specific than Schema.org's generic status field. | F12: YES
A13: CORROBORATION | B13: aggregateRating.ratingCount | C13: Integer | D13: ⚡ EXTENDED | E13: Number of independent sources confirming. Schema.org tracks rating count; we track source corroboration. | F13: NO
A14: NOTES | B14: reviewBody (Review) | C14: Text | D14: ✅ MAPPED | E14: Direct match. Free-text review body / annotation. | F14: NO
A16: ── NEW FIELDS (from Schema.org convergence) ──
A17: AUTHOR_NAME | B17: author.name (Person) | C17: Text | D17: ➕ NEW | E17: Named person who authored the evidence. Required for promotion — anonymous claims flagged. | F17: PROMO
A18: AUTHOR_ORG | B18: author.affiliation (Person) | C18: Text | D18: ➕ NEW | E18: Organization of the author/source. From Person schema affiliation property. | F18: PROMO
A19: ITEM_REVIEWED | B19: itemReviewed (Review) | C19: Thing | D19: ➕ NEW | E19: The specific thing being reviewed (event, document, statement). Google uses this for rich results. | F19: PROMO
A20: REVIEW_RATING | B20: reviewRating.alternateName | C20: Text | D20: ➕ NEW | E20: Human-readable verdict: True / Mostly True / Mixed / Mostly False / False / Unproven. Google ClaimReview label. | F20: PROMO
A21: DATE_PUBLISHED | B21: datePublished (CreativeWork) | C21: Date | D21: ➕ NEW | E21: When the original claim/source was published. Distinct from DATE_ACCESSED (when you retrieved it). | F21: PROMO
A22: DATE_REVIEWED | B22: dateModified (CreativeWork) | C22: Date | D22: ➕ NEW | E22: When this evidence review was last updated. Signals freshness to search engines. | F22: NO
A23: POSITIVE_NOTES | B23: positiveNotes (Review) | C23: ItemList | Text | D23: ➕ NEW | E23: Strengths of this evidence (structured pro list). Uses ItemList schema for ordered items. | F23: NO
A24: NEGATIVE_NOTES | B24: negativeNotes (Review) | C24: ItemList | Text | D24: ➕ NEW | E24: Weaknesses of this evidence (structured con list). Uses ItemList schema for ordered items. | F24: NO
A26: ── PROMOTION GATE (required for main web page) ──
A27: Rule | B27: Check | D27: Weight | E27: Rationale
A28: 1. Schema.org Required Fields | B28: CLAIM_TEXT + DB_TAG + TIER + URL + VERIFICATION all filled | D28: PASS/FAIL | E28: Hard gate — must pass. These are the minimum for a valid ClaimReview structured data entry.
A29: 2. Author Attribution | B29: AUTHOR_NAME or AUTHOR_ORG is non-empty | D29: PASS/FAIL | E29: Google requires author for ClaimReview rich results. Anonymous claims cannot be promoted.
A30: 3. Review Rating Present | B30: REVIEW_RATING is one of: True/Mostly True/Mixed/Mostly False/False/Unproven | D30: PASS/FAIL | E30: Google ClaimReview requires a textual rating. This is the human-readable verdict.
A31: 4. Evidence Quality Threshold | B31: Quality score (TIER weight) ≥ 60% | D31: 0.2 | E31: T1–T3 evidence passes automatically. T4–T5 need corroboration to qualify.
A32: 5. Consistency Check | B32: Consistency score ≥ 75% | D32: 0.2 | E32: DB_TAG must exist in taxonomy, tier within range, verification status valid.
A33: 6. Corroboration for Weak Sources | B33: If TIER = T4 or T5, CORROBORATION must be ≥ 2 | D33: PASS/FAIL | E33: Weak sources cannot be promoted without independent corroboration. Prevents single-source claims on main page.
A34: 7. Composite Score | B34: Overall composite ≥ 65% | D34: 0.6 | E34: Final quality gate. Weighted composite of completeness, quality, and consistency must hit threshold.

Sheet JSONLD_TEMPLATES
A1: JSON-LD STRUCTURED DATA TEMPLATES | D1: ClaimReview + Dataset · Inject into <head> of SPA case pages
A2: TEMPLATE | B2: JSON-LD CODE | D2: NOTES / FIELD MAPPING
A3: ── 1. ClaimReview (per evidence entry) ──
A4: ClaimReview (one per evidence entry) | B4: <script type="application/ld+json"> { "@context": "https://schema.org", "@type": "ClaimReview", "url": "https://openintel.org/cases/{{slug}}", "claimReviewed": "{{claim_text}}", "author": { "@type": "Organization", "name": "OpenIntel", "url": "https://openintel.org" }, "reviewRating": { "@type": "Rating", "ratingValue": {{tier_numeric}}, "bestRating": 5, "worstRating": 0, "alternateName": "{{review_rating}}" }, "itemReviewed": { "@type": "CreativeWork", "name": "{{item_reviewed}}", "author": { "@type": "Person", "name": "{{author_name}}", "affiliation": { "@type": "Organization", "name": "{{author_org}}" } }, "datePublished": "{{date_published}}", "appearance": [ { "@type": "WebPage", "url": "{{evidence_url}}" } ] }, "datePublished": "{{date_reviewed}}", "reviewBody": "Evidence type: {{db_tag}} (Tier {{tier}}). {{notes}}", "positiveNotes": { "@type": "ItemList", "itemListElement": [ { "@type": "ListItem", "position": 1, "name": "{{positive_notes}}" } ] }, "negativeNotes": { "@type": "ItemList", "itemListElement": [ { "@type": "ListItem", "position": 1, "name": "{{negative_notes}}" } ] }, "additionalType": "https://openintel.org/taxonomy/{{db_tag}}" } </script> | D4: FIELD MAP: {{slug}} ← case slug from API {{claim_text}} ← CLAIM_TEXT (col B) {{tier_numeric}} ← TIER mapped: T1=5, T2=4, T3=3, T4=2, T5=1, N=0 {{review_rating}} ← REVIEW_RATING (col O) {{item_reviewed}} ← ITEM_REVIEWED (col N) {{author_name}} ← AUTHOR_NAME (col L) {{author_org}} ← AUTHOR_ORG (col M) {{date_published}} ← DATE_PUBLISHED (col P) ISO 8601 {{evidence_url}} ← URL (col G) {{date_reviewed}} ← DATE_REVIEWED (col Q) ISO 8601 {{db_tag}} ← DB_TAG (col E) {{tier}} ← TIER (col F) {{notes}} ← NOTES (col K) {{positive_notes}} ← POSITIVE_NOTES (col R) {{negative_notes}} ← NEGATIVE_NOTES (col S) NOTE: Only inject for rows where PROMO GATE = ✅ READY Omit positiveNotes/negativeNotes blocks if empty. For multiple evidence items per case, emit multiple ClaimReview blocks.
A6: ── 2. Dataset (per API endpoint) ──
A7: Dataset (site-wide, on /api or /research index) | B7: <script type="application/ld+json"> { "@context": "https://schema.org", "@type": "Dataset", "name": "OpenIntel Evidence Taxonomy Dataset", "description": "Structured evidence grading database using a 38-type, 6-tier taxonomy for evaluating claims. Each entry is typed, tiered, and scored using the OpenIntel Evidence Classification System.", "url": "https://openintel.org/api/evidence", "license": "https://creativecommons.org/licenses/by-sa/4.0/", "creator": { "@type": "Organization", "name": "OpenIntel", "url": "https://openintel.org" }, "datePublished": "{{dataset_publish_date}}", "dateModified": "{{dataset_modified_date}}", "keywords": [ "evidence taxonomy", "fact-checking", "claim review", "structured evidence", "OSINT", "evidence grading" ], "measurementTechnique": "6-tier evidence classification (T1-T5 + Negative)", "variableMeasured": [ { "@type": "PropertyValue", "name": "Evidence Tier", "description": "Source strength rating from T1 (Primary/Strongest) to T5 (Weakest), plus N (Negative Evidence)", "minValue": 0, "maxValue": 5 }, { "@type": "PropertyValue", "name": "Evidence Type", "description": "One of 38 classified evidence types (e.g., declass_gov, court_record, peer_reviewed)" }, { "@type": "PropertyValue", "name": "Verification Status", "description": "One of: verified, pending, disputed, unverifiable" }, { "@type": "PropertyValue", "name": "Corroboration Count", "description": "Number of independent sources confirming this evidence" } ], "distribution": [ { "@type": "DataDownload", "encodingFormat": "application/json", "contentUrl": "https://openintel.org/api/evidence.json" }, { "@type": "DataDownload", "encodingFormat": "text/yaml", "contentUrl": "https://openintel.org/api/evidence.yaml" } ] } </script> | D7: DATASET SCHEMA NOTES: This goes on the /api index page or /research page. Signals to Google that this is structured research data, not editorial content. variableMeasured maps your 4 scoring dimensions: • Evidence Tier (T1-T5+N) → ratingValue 0-5 • Evidence Type (38 db_tags) → additionalType • Verification Status (4 states) → creativeWorkStatus • Corroboration Count → aggregateRating.ratingCount distribution offers both JSON and YAML downloads. Update encodingFormat if you add CSV export. {{dataset_publish_date}} ← first publish date {{dataset_modified_date}} ← last API data change License: CC BY-SA 4.0 recommended for open research. Change to appropriate license for your use case.
A9: ── 3. SPA Injection Code ──
A10: injectClaimReviewLD() (call in case detail component) | B10: // SPA helper: serialize API response → JSON-LD and inject into <head> // Call this in your case detail page component (onMount / useEffect) const TIER_MAP = { T1: 5, T2: 4, T3: 3, T4: 2, T5: 1, N: 0 }; function injectClaimReviewLD(caseData) { // caseData = API response for a single case // { slug, title, status, evidence: [{ claim_text, db_tag, tier, url, ... }] } const claimReviews = caseData.evidence .filter(e => e.promo_gate === 'READY') // Only promoted entries .map(e => ({ '@context': 'https://schema.org', '@type': 'ClaimReview', url: `https://openintel.org/cases/${caseData.slug}`, claimReviewed: e.claim_text, author: { '@type': 'Organization', name: 'OpenIntel', url: 'https://openintel.org' }, reviewRating: { '@type': 'Rating', ratingValue: TIER_MAP[e.tier] || 0, bestRating: 5, worstRating: 0, alternateName: e.review_rating }, itemReviewed: { '@type': 'CreativeWork', name: e.item_reviewed, author: { '@type': 'Person', name: e.author_name, ...(e.author_org && { affiliation: { '@type': 'Organization', name: e.author_org } }) }, datePublished: e.date_published, appearance: [{ '@type': 'WebPage', url: e.url }] }, datePublished: e.date_reviewed || new Date().toISOString().split('T')[0], reviewBody: `Evidence type: ${e.db_tag} (Tier ${e.tier}). ${e.notes || ''}`.trim(), additionalType: `https://openintel.org/taxonomy/${e.db_tag}`, ...(e.positive_notes && { positiveNotes: { '@type': 'ItemList', itemListElement: [{ '@type': 'ListItem', position: 1, name: e.positive_notes }] } }), ...(e.negative_notes && { negativeNotes: { '@type': 'ItemList', itemListElement: [{ '@type': 'ListItem', position: 1, name: e.negative_notes }] } }) })); // Remove existing LD+JSON scripts (avoid duplicates on SPA nav) document.querySelectorAll('script[data-openintel-ld]') .forEach(el => el.remove()); // Inject each ClaimReview as a separate script tag claimReviews.forEach((review, i) => { const script = document.createElement('script'); script.type = 'application/ld+json'; script.setAttribute('data-openintel-ld', `claim-${i}`); script.textContent = JSON.stringify(review, null, 2); document.head.appendChild(script); }); return claimReviews.length; } | D10: IMPLEMENTATION NOTES: 1. This function takes your existing API response object. The data is already there — status, slug, title, evidence array. No new API work needed. 2. Only entries where promo_gate === 'READY' get serialized into JSON-LD. The rest are filtered out. This is your quality gate in action. 3. Call in your case detail component: • React: useEffect(() => { injectClaimReviewLD(data); }, [data]) • Vue: onMounted(() => injectClaimReviewLD(data)) • Svelte: onMount(() => injectClaimReviewLD(data)) 4. The data-openintel-ld attribute lets us clean up on SPA navigation (no stale LD+JSON from previous page). 5. additionalType links to your taxonomy namespace: https://openintel.org/taxonomy/{{db_tag}} This is where you're better than ClaimReview — your 38-type system gives granularity they can't match. 6. appearance[] in itemReviewed links to the actual evidence source URL. Google uses this for the 'Claim appears in:' display in search results. 7. For SSR (Next.js/Nuxt): render the script tags server-side instead of DOM injection. Same JSON, just in the template <head> block. API FIELDS NEEDED (add to response if missing): • promo_gate: string ('READY' | 'BLOCKED') • review_rating: string • author_name: string • author_org: string • item_reviewed: string • date_published: string (ISO 8601) • date_reviewed: string (ISO 8601) • positive_notes: string | null • negative_notes: string | null
A12: ── 4. API Response → JSON-LD Field Map ──
A13: API Field | B13: JSON-LD Path | C13: Required | D13: Transform
A14: slug | B14: url (appended to base URL) | C14: ✅ | D14: `https://openintel.org/cases/${slug}`
A15: evidence[].claim_text | B15: claimReviewed | C15: ✅ | D15: Direct passthrough. Already in API response.
A16: evidence[].tier | B16: reviewRating.ratingValue | C16: ✅ | D16: TIER_MAP lookup: { T1:5, T2:4, T3:3, T4:2, T5:1, N:0 }
A17: evidence[].review_rating | B17: reviewRating.alternateName | C17: ✅ | D17: Direct passthrough. True/Mostly True/Mixed/Mostly False/False/Unproven
A18: evidence[].db_tag | B18: additionalType + reviewBody | C18: ✅ | D18: Prefix with namespace: `https://openintel.org/taxonomy/${db_tag}`
A19: evidence[].url | B19: itemReviewed.appearance[].url | C19: ✅ | D19: Direct passthrough. Links to the actual source material.
A20: evidence[].author_name | B20: itemReviewed.author.name | C20: PROMO | D20: NEW FIELD — add to API response. Required for promotion.
A21: evidence[].author_org | B21: itemReviewed.author.affiliation.name | C21: PROMO | D21: NEW FIELD — add to API response. Optional if author_name present.
A22: evidence[].item_reviewed | B22: itemReviewed.name | C22: PROMO | D22: NEW FIELD — add to API response. The thing being fact-checked.
A23: evidence[].promo_gate | B23: (filter gate — not in JSON-LD) | C23: GATE | D23: NEW FIELD — computed server-side from scoring formulas. 'READY' entries get LD, others don't.

Sheet PIPELINE_SPEC
A1: OPENINTEL FULL PIPELINE SPEC | B1: Postgres → Cloudflare Workers → Web Form → Auto-Promote → JSON-LD
A2: SECTION | B2: SPEC | C2: NOTES
A3: ── 1. POSTGRES SCHEMA ──
A4: evidence_taxonomy (reference table) | B4: CREATE TABLE evidence_taxonomy ( id SERIAL PRIMARY KEY, type_num INT NOT NULL UNIQUE, tier VARCHAR(2) NOT NULL, -- T1, T2, T3, T4, T5, N evidence_type VARCHAR(100) NOT NULL, description TEXT, examples TEXT, db_tag VARCHAR(30) NOT NULL UNIQUE, tier_range VARCHAR(10), tier_weight DECIMAL(3,2) NOT NULL, -- T1=1.00, T2=0.80, T3=0.60, T4=0.35, T5=0.15, N=0.50 created_at TIMESTAMPTZ DEFAULT NOW() ); -- Seed from EVIDENCE_TAXONOMY sheet (38 rows) INSERT INTO evidence_taxonomy (type_num, tier, evidence_type, db_tag, tier_range, tier_weight) VALUES (1, 'T1', 'Declassified Government Documents', 'declass_gov', 'T1-T2', 1.00), (2, 'T1', 'Congressional/Parliamentary Records', 'congress_record', 'T1-T2', 1.00), (3, 'T1', 'Court Records', 'court_record', 'T1', 1.00), -- ... (38 rows from your EVIDENCE_TAXONOMY sheet) (38, 'N', 'Classification/Redaction Patterns', 'redaction_pattern', 'ALL', 0.50); | C4: Reference table. Seed once from the EVIDENCE_TAXONOMY sheet. tier_weight drives the quality score calculation server-side. db_tag is the foreign key that evidence_entries references.
A6: evidence_entries (main data table) | B6: CREATE TABLE evidence_entries ( id UUID PRIMARY KEY DEFAULT gen_random_uuid(), claim_id VARCHAR(20) NOT NULL, -- CLAIM-001 format claim_text TEXT NOT NULL, -- schema: claimReviewed case_ref VARCHAR(50), -- FK to cases table / CASE_TYPES source TEXT NOT NULL, -- schema: author db_tag VARCHAR(30) NOT NULL -- FK to evidence_taxonomy REFERENCES evidence_taxonomy(db_tag), tier VARCHAR(2) NOT NULL -- T1, T2, T3, T4, T5, N CHECK (tier IN ('T1','T2','T3','T4','T5','N')), url TEXT NOT NULL, -- schema: url date_accessed DATE, -- when source was accessed verification VARCHAR(15) NOT NULL -- schema: creativeWorkStatus CHECK (verification IN ('verified','pending','disputed','unverifiable')), corroboration INT DEFAULT 0, -- schema: aggregateRating.ratingCount notes TEXT, -- schema: reviewBody -- Schema.org convergence fields author_name TEXT, -- schema: author.name (Person) author_org TEXT, -- schema: author.affiliation item_reviewed TEXT, -- schema: itemReviewed review_rating VARCHAR(20) -- schema: reviewRating.alternateName CHECK (review_rating IN ('True','Mostly True','Mixed','Mostly False','False','Unproven')), date_published DATE, -- schema: datePublished date_reviewed DATE, -- schema: dateModified positive_notes TEXT, -- schema: positiveNotes negative_notes TEXT, -- schema: negativeNotes -- Computed scores (set by trigger / worker) score_completeness INT, -- 0-100 score_quality INT, -- 0-100 score_consistency INT, -- 0-100 score_composite INT, -- 0-100 promo_gate VARCHAR(10) DEFAULT 'BLOCKED' -- 'READY' or 'BLOCKED' CHECK (promo_gate IN ('READY','BLOCKED')), -- Staging status VARCHAR(15) DEFAULT 'draft' -- draft -> staged -> promoted -> archived CHECK (status IN ('draft','staged','promoted','archived')), submitted_by TEXT, -- contributor identifier submitted_at TIMESTAMPTZ DEFAULT NOW(), promoted_at TIMESTAMPTZ, -- when entry went live created_at TIMESTAMPTZ DEFAULT NOW(), updated_at TIMESTAMPTZ DEFAULT NOW() ); CREATE INDEX idx_entries_db_tag ON evidence_entries(db_tag); CREATE INDEX idx_entries_tier ON evidence_entries(tier); CREATE INDEX idx_entries_promo ON evidence_entries(promo_gate); CREATE INDEX idx_entries_status ON evidence_entries(status); CREATE INDEX idx_entries_case ON evidence_entries(case_ref); | C6: Main table. Maps 1:1 to EVIDENCE_ENTRY sheet columns. All 19 user fields + 5 computed scores + staging fields. db_tag FK enforces taxonomy validity (same as the Excel COUNTIF check). CHECK constraints replicate the dropdown validations from the sheet. promo_gate is computed server-side (see scoring trigger below). status flow: draft → staged → promoted → archived draft: just saved, not scored yet staged: scored, waiting for review promoted: passed gate, live on site, gets JSON-LD archived: taken down / superseded UUID primary key for API-friendly IDs. Timestamps for audit trail.
A8: scoring trigger (auto-compute on insert/update) | B8: CREATE OR REPLACE FUNCTION compute_evidence_scores() RETURNS TRIGGER AS $$ DECLARE v_total_fields INT := 18; v_filled INT := 0; v_quality INT := 0; v_consistency INT := 0; v_tag_valid BOOLEAN; v_tier_weight DECIMAL; BEGIN -- 1. COMPLETENESS: count non-null, non-empty fields / 18 v_filled := ( (CASE WHEN COALESCE(NEW.claim_text,'') != '' THEN 1 ELSE 0 END) + (CASE WHEN COALESCE(NEW.case_ref,'') != '' THEN 1 ELSE 0 END) + (CASE WHEN COALESCE(NEW.source,'') != '' THEN 1 ELSE 0 END) + (CASE WHEN COALESCE(NEW.db_tag,'') != '' THEN 1 ELSE 0 END) + (CASE WHEN COALESCE(NEW.tier,'') != '' THEN 1 ELSE 0 END) + (CASE WHEN COALESCE(NEW.url,'') != '' THEN 1 ELSE 0 END) + (CASE WHEN NEW.date_accessed IS NOT NULL THEN 1 ELSE 0 END) + (CASE WHEN COALESCE(NEW.verification,'') != '' THEN 1 ELSE 0 END) + (CASE WHEN COALESCE(NEW.corroboration, 0) > 0 THEN 1 ELSE 0 END) + (CASE WHEN COALESCE(NEW.notes,'') != '' THEN 1 ELSE 0 END) + (CASE WHEN COALESCE(NEW.author_name,'') != '' THEN 1 ELSE 0 END) + (CASE WHEN COALESCE(NEW.author_org,'') != '' THEN 1 ELSE 0 END) + (CASE WHEN COALESCE(NEW.item_reviewed,'') != '' THEN 1 ELSE 0 END) + (CASE WHEN COALESCE(NEW.review_rating,'') != '' THEN 1 ELSE 0 END) + (CASE WHEN NEW.date_published IS NOT NULL THEN 1 ELSE 0 END) + (CASE WHEN NEW.date_reviewed IS NOT NULL THEN 1 ELSE 0 END) + (CASE WHEN COALESCE(NEW.positive_notes,'') != '' THEN 1 ELSE 0 END) + (CASE WHEN COALESCE(NEW.negative_notes,'') != '' THEN 1 ELSE 0 END) ); NEW.score_completeness := ROUND((v_filled::DECIMAL / v_total_fields) * 100); -- 2. QUALITY: tier weight lookup SELECT tier_weight INTO v_tier_weight FROM evidence_taxonomy WHERE db_tag = NEW.db_tag; NEW.score_quality := COALESCE(ROUND(v_tier_weight * 100), 0); -- 3. CONSISTENCY: tag valid + tier filled + status valid + corroboration check SELECT EXISTS(SELECT 1 FROM evidence_taxonomy WHERE db_tag = NEW.db_tag) INTO v_tag_valid; v_consistency := ( (CASE WHEN v_tag_valid THEN 1 ELSE 0 END) + (CASE WHEN NEW.tier IS NOT NULL THEN 1 ELSE 0 END) + (CASE WHEN NEW.verification IN ('verified','pending','disputed','unverifiable') THEN 1 ELSE 0 END) + (CASE WHEN NEW.tier IN ('T4','T5') AND COALESCE(NEW.corroboration,0) < 1 THEN 0 ELSE 1 END) ); NEW.score_consistency := ROUND((v_consistency::DECIMAL / 4) * 100); -- 4. COMPOSITE: completeness*0.3 + quality*0.4 + consistency*0.3 NEW.score_composite := ROUND( NEW.score_completeness * 0.3 + NEW.score_quality * 0.4 + NEW.score_consistency * 0.3 ); -- 5. PROMOTION GATE IF ( COALESCE(NEW.claim_text,'') != '' AND COALESCE(NEW.db_tag,'') != '' AND COALESCE(NEW.tier,'') != '' AND COALESCE(NEW.url,'') != '' AND COALESCE(NEW.verification,'') != '' AND (COALESCE(NEW.author_name,'') != '' OR COALESCE(NEW.author_org,'') != '') AND COALESCE(NEW.review_rating,'') != '' AND (NEW.tier NOT IN ('T4','T5') OR COALESCE(NEW.corroboration,0) >= 2) AND NEW.score_quality >= 60 AND NEW.score_composite >= 65 ) THEN NEW.promo_gate := 'READY'; -- Auto-stage if draft IF NEW.status = 'draft' THEN NEW.status := 'staged'; END IF; ELSE NEW.promo_gate := 'BLOCKED'; END IF; NEW.updated_at := NOW(); RETURN NEW; END; $$ LANGUAGE plpgsql; CREATE TRIGGER trg_evidence_scores BEFORE INSERT OR UPDATE ON evidence_entries FOR EACH ROW EXECUTE FUNCTION compute_evidence_scores(); | C8: This trigger replicates EXACTLY the same scoring logic from your Excel formulas: Excel col U (COMPLETENESS) = v_filled / 18 * 100 Excel col V (QUALITY) = tier weight lookup Excel col W (CONSISTENCY) = 4-check validation Excel col X (COMPOSITE) = weighted average Excel col Y (PROMO GATE) = 7-rule check Fires on every INSERT and UPDATE. Key behavior: • If an entry passes the promo gate and is still 'draft', it auto-advances to 'staged' • Promotion from 'staged' → 'promoted' is a separate manual/API action (see Worker endpoint) • Scores are always recomputed, so editing a promoted entry can un-promote it The gate rules are identical to the SCHEMA_MAP promotion gate: 1. Core fields filled 2. Author attribution 3. Review rating present 4. Corroboration for T4/T5 ≥ 2 5. Quality ≥ 60% 6. Composite ≥ 65%
A10: ── 2. CLOUDFLARE WORKERS API ──
A11: POST /api/evidence (submit new entry) | B11: // Cloudflare Worker: POST /api/evidence // Accepts form submission, validates, inserts into Postgres via Hyperdrive export async function onRequestPost({ request, env }) { const body = await request.json(); // 1. Server-side validation (mirrors Excel dropdowns) const VALID_TIERS = ['T1','T2','T3','T4','T5','N']; const VALID_VERIF = ['verified','pending','disputed','unverifiable']; const VALID_RATING = ['True','Mostly True','Mixed','Mostly False','False','Unproven']; const errors = []; if (!body.claim_text?.trim()) errors.push('claim_text is required'); if (!body.db_tag?.trim()) errors.push('db_tag is required'); if (!VALID_TIERS.includes(body.tier)) errors.push('tier must be T1-T5 or N'); if (!body.url?.trim()) errors.push('url is required'); if (!VALID_VERIF.includes(body.verification)) errors.push('invalid verification status'); if (body.review_rating && !VALID_RATING.includes(body.review_rating)) errors.push('invalid review_rating'); if (errors.length > 0) { return Response.json({ ok: false, errors }, { status: 400 }); } // 2. Insert via Hyperdrive (Postgres trigger auto-computes scores) const db = env.HYPERDRIVE.connect(); const result = await db.query( `INSERT INTO evidence_entries ( claim_id, claim_text, case_ref, source, db_tag, tier, url, date_accessed, verification, corroboration, notes, author_name, author_org, item_reviewed, review_rating, date_published, date_reviewed, positive_notes, negative_notes, submitted_by ) VALUES ($1,$2,$3,$4,$5,$6,$7,$8,$9,$10,$11,$12,$13,$14,$15,$16,$17,$18,$19,$20) RETURNING id, promo_gate, status, score_composite`, [ body.claim_id || `CLAIM-${Date.now()}`, body.claim_text, body.case_ref, body.source, body.db_tag, body.tier, body.url, body.date_accessed, body.verification, body.corroboration || 0, body.notes, body.author_name, body.author_org, body.item_reviewed, body.review_rating, body.date_published, body.date_reviewed, body.positive_notes, body.negative_notes, body.submitted_by || 'anonymous' ] ); const entry = result.rows[0]; // 3. Return result with scoring feedback return Response.json({ ok: true, id: entry.id, promo_gate: entry.promo_gate, status: entry.status, score: entry.score_composite, message: entry.promo_gate === 'READY' ? 'Entry scored and staged for promotion.' : 'Entry saved as draft. Fill required fields to qualify for promotion.' }, { status: 201 }); } | C11: SUBMIT ENDPOINT Flow: 1. Form posts JSON to Worker 2. Server-side validation (same rules as Excel dropdowns) 3. Insert into Postgres via Hyperdrive 4. Trigger auto-computes all 5 scores 5. Returns promo_gate status immediately The user sees instant feedback: • 'Entry scored and staged for promotion' if it passes • 'Fill required fields to qualify' if it doesn't They never see the scores directly — just the gate result. Same stealth scoring as the Excel sheet. Claim IDs auto-generate if not provided. Env bindings needed: • HYPERDRIVE: Cloudflare Hyperdrive binding to your Postgres
A13: GET /api/evidence (list + filter) | B13: // GET /api/evidence?tier=T1&status=promoted&limit=50 export async function onRequestGet({ request, env }) { const url = new URL(request.url); const tier = url.searchParams.get('tier'); const status = url.searchParams.get('status') || 'promoted'; const db_tag = url.searchParams.get('db_tag'); const limit = Math.min(parseInt(url.searchParams.get('limit') || '50'), 200); const offset = parseInt(url.searchParams.get('offset') || '0'); let query = 'SELECT * FROM evidence_entries WHERE 1=1'; const params = []; let i = 1; if (tier) { query += ` AND tier = $${i++}`; params.push(tier); } if (status) { query += ` AND status = $${i++}`; params.push(status); } if (db_tag) { query += ` AND db_tag = $${i++}`; params.push(db_tag); } query += ` ORDER BY score_composite DESC, created_at DESC LIMIT $${i++} OFFSET $${i++}`; params.push(limit, offset); const db = env.HYPERDRIVE.connect(); const result = await db.query(query, params); // Add JSON-LD for promoted entries const entries = result.rows.map(row => ({ ...row, // Strip score columns from public response score_completeness: undefined, score_quality: undefined, score_consistency: undefined, score_composite: undefined, jsonld: row.promo_gate === 'READY' ? buildClaimReviewLD(row) : null })); return Response.json({ ok: true, entries, count: entries.length }); } | C13: LIST ENDPOINT Default: returns only promoted entries Filters: tier, status, db_tag Sort: composite score DESC Score columns are STRIPPED from public response. Users see the data + the promo_gate flag but never the numeric scores. The jsonld field contains pre-built ClaimReview JSON-LD for each promoted entry. Your SPA can inject this directly — no client-side serialization needed. For the YAML export endpoint, add: GET /api/evidence.yaml (same query, serialize as YAML)
A15: POST /api/evidence/:id/promote (manual promotion) | B15: // POST /api/evidence/:id/promote // Moves a staged entry to promoted (live on site) export async function onRequestPost({ params, env }) { const db = env.HYPERDRIVE.connect(); // Only promote if gate is READY and status is staged const result = await db.query( `UPDATE evidence_entries SET status = 'promoted', promoted_at = NOW(), updated_at = NOW() WHERE id = $1 AND promo_gate = 'READY' AND status = 'staged' RETURNING id, claim_id, promo_gate, status`, [params.id] ); if (result.rows.length === 0) { return Response.json({ ok: false, error: 'Entry not found, not staged, or promo gate is BLOCKED' }, { status: 400 }); } // Purge Cloudflare cache for this case page // (so JSON-LD updates immediately) await env.CACHE.purge({ tags: [`case-${result.rows[0].case_ref}`] }); return Response.json({ ok: true, entry: result.rows[0], message: 'Entry promoted to live site. JSON-LD will be injected on next page load.' }); } | C15: PROMOTE ENDPOINT The gate between 'staged' and 'promoted' (live on site). Double-checks: • promo_gate must be 'READY' • status must be 'staged' Both must be true. Even if someone calls this endpoint directly, a BLOCKED entry can't be promoted. Optional: purge Cloudflare cache so the JSON-LD shows up immediately on the case page. This is the manual step. You could also set up a cron Worker to auto-promote all 'staged' + 'READY' entries on a schedule.
A17: ── 3. HTML FORM TEMPLATE ──
A18: Evidence Entry Form (Schema.org microdata baked in) | B18: <form id="evidence-form" itemscope itemtype="https://schema.org/ClaimReview" method="POST" action="/api/evidence"> <input type="hidden" name="@context" value="https://schema.org" /> <input type="hidden" name="@type" value="ClaimReview" /> <!-- CORE FIELDS --> <fieldset> <legend>Evidence Details</legend> <label for="claim_text">Claim Being Evaluated *</label> <textarea id="claim_text" name="claim_text" required itemprop="claimReviewed" rows="3" placeholder="The specific claim you are evaluating..."></textarea> <label for="source">Source *</label> <input type="text" id="source" name="source" required placeholder="Where does this evidence come from?" /> <label for="db_tag">Evidence Type *</label> <select id="db_tag" name="db_tag" required itemprop="additionalType"> <option value="">Select evidence type...</option> <optgroup label="T1 — Primary Sources (Strongest)"> <option value="declass_gov">Declassified Government Documents</option> <option value="congress_record">Congressional/Parliamentary Records</option> <option value="court_record">Court Records</option> <option value="official_admit">Official Admissions/Apologies</option> <option value="leaked_doc">Leaked Documents</option> <option value="peer_reviewed">Scientific/Peer-Reviewed Studies</option> <option value="financial_record">Financial Records</option> <option value="forensic">Physical/Forensic Evidence</option> </optgroup> <optgroup label="T2 — Secondary Sources (Supporting)"> <option value="invest_journalism">Investigative Journalism</option> <option value="witness_named">Witness Testimony (Named)</option> <option value="whistleblower">Whistleblower Disclosures</option> <option value="academic_research">Academic Research/Analysis</option> <option value="verified_media">Photographic/Video Evidence (Verified)</option> <option value="foia_response">FOIA Request Responses</option> <option value="audit_report">Audit Reports</option> </optgroup> <optgroup label="T3 — Tertiary Sources (Contextual)"> <option value="stat_pattern">Statistical/Pattern Analysis</option> <option value="circumstantial">Circumstantial Evidence Chains</option> <option value="historical_prec">Historical Precedent</option> <option value="expert_opinion">Expert Opinion (Named)</option> <option value="contemp_news">Contemporaneous News Reports</option> <option value="correspondence">Correspondence/Communications</option> </optgroup> <optgroup label="T4 — Weak Sources (Requires Corroboration)"> <option value="anon_source">Anonymous Sources</option> <option value="hearsay">Secondhand/Hearsay Accounts</option> <option value="unverified_doc">Unverified Documents</option> <option value="confession">Confession/Deathbed Statement</option> <option value="uncontrolled_pattern">Pattern Recognition Without Controls</option> <option value="archived_content">Archived/Deleted Content</option> <option value="documentary_claim">Documentary Film Claims</option> </optgroup> <optgroup label="T5 — Weakest Sources (Flag but Don't Dismiss)"> <option value="single_source">Single-Source Claims</option> <option value="anon_post">Anonymous Internet Posts</option> <option value="channeled">Channeled/Psychic/Revelatory Material</option> <option value="unverifiable">Unverifiable by Design</option> <option value="circular_ref">Circular/Self-Referencing</option> <option value="ai_generated">AI-Generated/Manipulated Content</option> </optgroup> <optgroup label="N — Negative Evidence (Absence as Data)"> <option value="conspic_absence">Conspicuous Absence</option> <option value="suppression">Suppression Evidence</option> <option value="non_denial">Non-Denial Denials</option> <option value="redaction_pattern">Classification/Redaction Patterns</option> </optgroup> </select> <label for="tier">Evidence Tier *</label> <select id="tier" name="tier" required> <option value="">Select tier...</option> <option value="T1">T1 — Primary (Strongest)</option> <option value="T2">T2 — Secondary (Supporting)</option> <option value="T3">T3 — Tertiary (Contextual)</option> <option value="T4">T4 — Weak (Requires Corroboration)</option> <option value="T5">T5 — Weakest (Flag but Don't Dismiss)</option> <option value="N">N — Negative Evidence (Absence as Data)</option> </select> <label for="url">Source URL *</label> <input type="url" id="url" name="url" required itemprop="url" placeholder="https://..." /> <label for="verification">Verification Status *</label> <select id="verification" name="verification" required> <option value="">Select status...</option> <option value="verified">Verified</option> <option value="pending">Pending</option> <option value="disputed">Disputed</option> <option value="unverifiable">Unverifiable</option> </select> <label for="corroboration">Independent Corroboration Count</label> <input type="number" id="corroboration" name="corroboration" min="0" value="0" /> <label for="notes">Notes</label> <textarea id="notes" name="notes" rows="2" itemprop="reviewBody" placeholder="Additional context or annotations..."></textarea> </fieldset> <!-- SCHEMA.ORG FIELDS (for promotion) --> <fieldset> <legend>Author &amp; Review Details (needed for web publication)</legend> <label for="author_name">Author Name</label> <input type="text" id="author_name" name="author_name" itemprop="author" placeholder="Named person who authored this evidence" /> <label for="author_org">Author Organization</label> <input type="text" id="author_org" name="author_org" placeholder="Organization (e.g. Washington Post, MIT, CIA)" /> <label for="item_reviewed">Item Reviewed</label> <input type="text" id="item_reviewed" name="item_reviewed" itemprop="itemReviewed" placeholder="What specific thing is being fact-checked?" /> <label for="review_rating">Review Rating</label> <select id="review_rating" name="review_rating"> <option value="">Select verdict...</option> <option value="True">True</option> <option value="Mostly True">Mostly True</option> <option value="Mixed">Mixed</option> <option value="Mostly False">Mostly False</option> <option value="False">False</option> <option value="Unproven">Unproven</option> </select> <label for="date_published">Date Published</label> <input type="date" id="date_published" name="date_published" /> <label for="positive_notes">Strengths of Evidence</label> <textarea id="positive_notes" name="positive_notes" rows="2" placeholder="What makes this evidence strong?"></textarea> <label for="negative_notes">Weaknesses of Evidence</label> <textarea id="negative_notes" name="negative_notes" rows="2" placeholder="Caveats, limitations, concerns?"></textarea> </fieldset> <button type="submit">Submit Evidence</button> </form> | C18: FORM STRUCTURE Two fieldsets: 1. Core Evidence Details (required) 2. Author & Review (needed for promotion) The form DOES NOT show scoring fields. Users fill in evidence naturally. The server-side trigger scores it and they get back a simple pass/fail. Schema.org microdata is baked into the HTML: • itemscope itemtype="ClaimReview" on <form> • itemprop on key fields • This means even the FORM PAGE itself is structured data The <select> for db_tag uses <optgroup> to mirror your 6-tier taxonomy structure. Users see the hierarchy. All required fields marked with * match the promo gate hard requirements. The form posts JSON to /api/evidence (Worker endpoint above). For SPA: replace form action with fetch() call and handle the response JSON (promo_gate status).
A20: ── 4. STAGING PIPELINE ──
A21: Status flow diagram | B21: EVIDENCE ENTRY LIFECYCLE: ┌─────────┐ ┌─────────┐ ┌───────────┐ ┌──────────┐ │ DRAFT │ ───▶ │ STAGED │ ───▶ │ PROMOTED │ ───▶ │ ARCHIVED │ └─────────┘ └─────────┘ └───────────┘ └──────────┘ │ │ │ │ Form submit Auto if POST /promote Manual or POST /evidence gate=READY (manual review) superseded │ │ │ Trigger scores ┌───┴───┐ JSON-LD injected all 5 metrics │ BLOCKED│ on case page └───────┘ Stays draft, user sees 'needs more info' TRANSITION RULES: draft → staged : AUTOMATIC when promo_gate = 'READY' (trigger) draft → draft : If gate = 'BLOCKED', stays draft with feedback staged → promoted : MANUAL via POST /api/evidence/:id/promote staged → draft : If edited and gate becomes 'BLOCKED' promoted → archived: MANUAL or via expiry rule ANY → rescored : Every UPDATE re-triggers scoring | C21: KEY DESIGN DECISIONS: 1. draft → staged is AUTO User doesn't need to know about staging. They fill in the form, and if it's good enough, it advances silently. 2. staged → promoted is MANUAL This is your editorial gate. Even if the scores are perfect, a human decides when it goes live. You can also add a cron Worker to auto-promote staged entries older than N days. 3. Editing can UN-PROMOTE If someone edits a promoted entry and it drops below thresholds, the trigger resets promo_gate to BLOCKED. The status stays 'promoted' but JSON-LD won't render (filtered by promo_gate in the GET endpoint). 4. Scores are NEVER shown to the user They see: • 'Entry saved' (draft) • 'Entry qualified for publication' (staged) • Live on site (promoted) • 'Needs more information' (blocked) They never see 73% completeness or 85 quality.
A23: ── 5. CLOUDFLARE DEPLOYMENT ──
A24: wrangler.toml | B24: name = "openintel-api" main = "src/index.ts" compatibility_date = "2025-01-01" # Hyperdrive binding to your Postgres [[hyperdrive]] binding = "HYPERDRIVE" id = "<your-hyperdrive-config-id>" # Routes [[routes]] pattern = "/api/evidence*" zone_name = "openintel.org" # Optional: D1 for caching / analytics [[d1_databases]] binding = "ANALYTICS" database_name = "openintel-analytics" database_id = "<d1-database-id>" # KV for rate limiting [[kv_namespaces]] binding = "RATE_LIMIT" id = "<kv-namespace-id>" | C24: DEPLOYMENT CONFIG Hyperdrive connects your Cloudflare Worker to Postgres. Setup: 1. npx wrangler hyperdrive create openintel-db \ --connection-string="postgres://user:pass@host:5432/openintel" 2. npx wrangler deploy 3. Point DNS: openintel.org → Cloudflare Optional D1: You could mirror promoted entries to D1 for edge-cached reads. Writes go to Postgres, reads from D1. But Hyperdrive alone is fine for your scale. Rate limiting via KV: Prevent form spam. Track submissions per IP per hour.
A26: ── 6. PROJECT FILE STRUCTURE ──
A27: Directory layout | B27: openintel/ ├── wrangler.toml # Cloudflare config (Section 5) ├── migrations/ │ ├── 001_create_taxonomy.sql # evidence_taxonomy table + seed data │ ├── 002_create_entries.sql # evidence_entries table + indexes │ └── 003_create_scoring_trigger.sql # compute_evidence_scores() trigger ├── src/ │ ├── index.ts # Worker entry point + router │ ├── routes/ │ │ ├── evidence.post.ts # POST /api/evidence (Section 2) │ │ ├── evidence.get.ts # GET /api/evidence (Section 2) │ │ └── evidence.promote.ts # POST /api/evidence/:id/promote │ ├── lib/ │ │ ├── validation.ts # Server-side validation rules │ │ ├── jsonld.ts # buildClaimReviewLD() + buildDatasetLD() │ │ └── taxonomy.ts # DB_TAG enum, tier weights, type map │ └── types.ts # TypeScript interfaces ├── public/ │ ├── evidence-form.html # Form template (Section 3) │ └── form.js # SPA form handler + fetch logic └── package.json | C27: Every section of this spec maps to a file. Migrations run in order on Postgres: psql -d openintel -f migrations/001_create_taxonomy.sql psql -d openintel -f migrations/002_create_entries.sql psql -d openintel -f migrations/003_create_scoring_trigger.sql The lib/taxonomy.ts should be auto-generated from your EVIDENCE_TAXONOMY Excel sheet so the 38 types stay in sync. The jsonld.ts is the same code from your JSONLD_TEMPLATES sheet.

Sheet EVIDENCE_TAXONOMY
A1: OPENINTEL EVIDENCE TAXONOMY | D1: 38 Evidence Types · 6 Tiers · Every claim gets tagged
A2: TYPE # | B2: TIER | C2: EVIDENCE TYPE | D2: DESCRIPTION | E2: EXAMPLES | F2: DB TAG | G2: T-RANGE
B3: T1 — PRIMARY SOURCES (Strongest)
A4: 1 | B4: T1 | C4: Declassified Government Documents | D4: FOIA releases, presidential libraries, national archives. Official records released through declassification processes. | E4: MKUltra, COINTELPRO, Operation Northwoods | F4: declass_gov | G4: T1–T2
A5: 2 | B5: T1 | C5: Congressional/Parliamentary Records | D5: Hearing transcripts, committee reports, testimony under oath. Official legislative investigation records. | E5: Church Committee, Pike Committee, 9/11 Commission | F5: congress_record | G5: T1–T2
A6: 3 | B6: T1 | C6: Court Records | D6: Indictments, trial transcripts, depositions, settlements, judgments. Legally produced under rules of evidence. | E6: Orlikow v. United States, Alex Jones defamation trial | F6: court_record | G6: T1
A7: 4 | B7: T1 | C7: Official Admissions/Apologies | D7: Government or institutional acknowledgments of past programs or wrongdoing. | E7: Tuskegee apology, Lavon Affair admission, CIA torture acknowledgment | F7: official_admit | G7: T1
A8: 5 | B8: T1 | C8: Leaked Documents | D8: Unauthorized disclosures verified by publication in major outlets with editorial oversight. | E8: Wikileaks cables, Snowden docs, Pentagon Papers, Panama Papers | F8: leaked_doc | G8: T1–T2
A9: 6 | B9: T1 | C9: Scientific/Peer-Reviewed Studies | D9: Published research with methodology, replication, and peer review in recognized journals. | E9: NTP fluoride study, VAERS data analysis | F9: peer_reviewed | G9: T1
A10: 7 | B10: T1 | C10: Financial Records | D10: SEC filings, tax records, campaign finance disclosures, foundation grants. Auditable money trails. | E10: SEC filings, FEC disclosures, foundation 990s | F10: financial_record | G10: T1–T2
A11: 8 | B11: T1 | C11: Physical/Forensic Evidence | D11: Lab results, autopsy reports, engineering analysis, DNA, materials testing. Physical evidence with chain of custody. | E11: Building 7 structural analysis, JFK bullet forensics, DNA evidence | F11: forensic | G11: T1
B12: T2 — SECONDARY SOURCES (Supporting)
A13: 9 | B13: T2 | C13: Investigative Journalism | D13: Long-form reporting by named journalists at identifiable outlets with editorial oversight. | E13: Gary Webb (Dark Alliance), Seymour Hersh, Carl Bernstein | F13: invest_journalism | G13: T2–T3
A14: 10 | B14: T2 | C14: Witness Testimony (Named) | D14: Identified individuals making statements on the record, under real name, often under oath. | E14: David Grusch UAP testimony, Frank Serpico | F14: witness_named | G14: T2–T3
A15: 11 | B15: T2 | C15: Whistleblower Disclosures | D15: Named insiders with verifiable employment history. Identity known, unlike anonymous sources. | E15: Edward Snowden, Daniel Ellsberg, Chelsea Manning | F15: whistleblower | G15: T1–T2
A16: 12 | B16: T2 | C16: Academic Research/Analysis | D16: University-affiliated researchers publishing analysis. Scholarly work with citations, not peer-reviewed primary science. | E16: University policy papers, historical analysis, meta-studies | F16: academic_research | G16: T2–T3
A17: 13 | B17: T2 | C17: Photographic/Video Evidence (Verified) | D17: Authenticated imagery with chain of custody or metadata verification. | E17: Bohemian Grove footage, Abu Ghraib photos | F17: verified_media | G17: T1–T2
A18: 14 | B18: T2 | C18: FOIA Request Responses | D18: Specific responses to targeted FOIA requests, not just declassified dumps. Targeted information retrieval. | E18: Black Vault archives, specific FOIA releases | F18: foia_response | G18: T1–T2
A19: 15 | B19: T2 | C19: Audit Reports | D19: GAO, inspector general, independent auditor findings. Official watchdog assessments. | E19: Pentagon audit failures, TARP oversight, IG reports | F19: audit_report | G19: T1–T2
B20: T3 — TERTIARY SOURCES (Contextual)
A21: 16 | B21: T3 | C21: Statistical/Pattern Analysis | D21: Data showing anomalies, correlations, or patterns that require explanation. Quantitative evidence. | E21: Excess death data, financial market anomalies, voting pattern analysis | F21: stat_pattern | G21: T2–T4
A22: 17 | B22: T3 | C22: Circumstantial Evidence Chains | D22: Individual facts each confirmed but whose connection is inferred. Timing coincidences, personnel overlaps, funding trails. | E22: Personnel overlap patterns, funding trail connections, timing coincidences | F22: circumstantial | G22: T3–T4
A23: 18 | B23: T3 | C23: Historical Precedent | D23: "This has happened before, therefore plausible now." Confirmed precedents make future claims more plausible, not proven. | E23: Confirmed false flags making future false flag claims plausible | F23: historical_prec | G23: T3
A24: 19 | B24: T3 | C24: Expert Opinion (Named) | D24: Credentialed experts making assessments outside formal publications. Professional opinion, not peer-reviewed. | E24: Architects & Engineers for 9/11 Truth, retired intelligence officers | F24: expert_opinion | G24: T2–T3
A25: 20 | B25: T3 | C25: Contemporaneous News Reports | D25: News coverage from the time of the event. Shows what was known when, and what changed over time. | E25: Day-of news broadcasts, initial wire reports, early coverage | F25: contemp_news | G25: T3
A26: 21 | B26: T3 | C26: Correspondence/Communications | D26: Emails, letters, memos not officially declassified but obtained through leaks or litigation. | E26: Podesta emails, Climategate emails, corporate memos | F26: correspondence | G26: T2–T4
B27: T4 — WEAK SOURCES (Requires Corroboration)
A28: 22 | B28: T4 | C28: Anonymous Sources | D28: Unnamed insiders, anonymous tips, "sources say" reporting. May be accurate but unverifiable. | E28: "Sources familiar with the matter," anonymous tips to journalists | F28: anon_source | G28: T3–T5
A29: 23 | B29: T4 | C29: Secondhand/Hearsay Accounts | D29: Someone reporting what someone else told them. No direct witness access. | E29: "My uncle worked at Area 51 and said..." | F29: hearsay | G29: T4–T5
A30: 24 | B30: T4 | C30: Unverified Documents | D30: Documents of unknown provenance. Cannot confirm authenticity or chain of custody. | E30: Majestic 12 papers, some UFO documents | F30: unverified_doc | G30: T4–T5
A31: 25 | B31: T4 | C31: Confession/Deathbed Statement | D31: Individuals claiming involvement or knowledge, often without corroboration. Uncorroborated personal claims. | E31: E. Howard Hunt JFK claims, deathbed confessions | F31: confession | G31: T3–T5
A32: 26 | B32: T4 | C32: Pattern Recognition Without Controls | D32: Seeing connections without base-rate comparison. Pattern matching without statistical rigor. | E32: Predictive programming claims, numerology connections | F32: uncontrolled_pattern | G32: T4–T5
A33: 27 | B33: T4 | C33: Archived/Deleted Content | D33: Wayback Machine captures, screenshots of deleted posts. Authentic capture but context may be missing. | E33: Archived tweets, deleted articles, Wayback captures | F33: archived_content | G33: T3–T5
A34: 28 | B34: T4 | C34: Documentary Film Claims | D34: Documentaries mix evidence types. Individual claims within them need separate rating. | E34: Claims within Zeitgeist, Loose Change, etc. (rate each claim separately) | F34: documentary_claim | G34: T3–T5
B35: T5 — WEAKEST SOURCES (Flag but Don’t Dismiss)
A36: 29 | B36: T5 | C36: Single-Source Claims | D36: Entire theory rests on one person's testimony with no corroboration whatsoever. | E36: Project Monarch, Dulce Base | F36: single_source | G36: T5
A37: 30 | B37: T5 | C37: Anonymous Internet Posts | D37: Chan boards, anonymous forums, unsigned blog posts. No identity, no accountability. | E37: QAnon drops, anonymous "insider" claims, 4chan posts | F37: anon_post | G37: T5
A38: 31 | B38: T5 | C38: Channeled/Psychic/Revelatory Material | D38: Claims based on spiritual revelation rather than physical evidence. Prophecy claims without scriptural basis. | E38: Psychic claims, channeled messages, non-scriptural prophecy | F38: channeled | G38: T5
A39: 32 | B39: T5 | C39: Unverifiable by Design | D39: Claims structured so they cannot be tested. "They destroyed all the evidence," "it's too classified." | E39: Self-sealing claims, unfalsifiable assertions | F39: unverifiable | G39: T5
A40: 33 | B40: T5 | C40: Circular/Self-Referencing | D40: Source A cites Source B, which cites Source A. Common in conspiracy echo chambers. | E40: Blog networks citing each other, circular Wikipedia references | F40: circular_ref | G40: T5
A41: 34 | B41: T5 | C41: AI-Generated/Manipulated Content | D41: Deepfakes, AI-written articles presented as reporting. Growing problem since 2023. | E41: Deepfake videos, AI-generated articles, synthetic media | F41: ai_generated | G41: T5
B42: N — NEGATIVE EVIDENCE (Absence as Data) | C42: Cuts across all tiers
A43: 35 | B43: N | C43: Conspicuous Absence | D43: Records that should exist but don't. Missing frames, redacted pages, destroyed files. The absence itself is data. | E43: Helms ordering MKUltra destruction, missing JFK files, destroyed tapes | F43: conspic_absence | G43: ALL
A44: 36 | B44: N | C44: Suppression Evidence | D44: Documented attempts to silence, deplatform, discredit, or punish. The suppression itself is a data point, not proof of claim. | E44: Deplatforming patterns, whistleblower retaliation, media blackouts | F44: suppression | G44: ALL
A45: 37 | B45: N | C45: Non-Denial Denials | D45: Official responses that don't actually deny the specific claim. "We don't comment on intelligence matters." | E45: "We neither confirm nor deny," evasive testimony, non-responsive answers | F45: non_denial | G45: ALL
A46: 38 | B46: N | C46: Classification/Redaction Patterns | D46: What's redacted can reveal what's sensitive. Bulk redactions in specific areas suggest something worth hiding. | E46: FOIA redaction patterns, selective classification, over-classification | F46: redaction_pattern | G46: ALL

Sheet CASE_TYPES
A1: OPENINTEL CASE TYPE CLASSIFICATION | D1: Structure-based, not source-based. What the thing IS, not who confirmed it.
A2: # | B2: CASE TYPE | C2: CORE QUESTION | D2: DESCRIPTION | E2: EXAMPLES | F2: DB TAG | G2: KEY MODULES LOADED
A3: 1 | B3: EVENT | C3: What really happened? | D3: A specific thing happened. The debate is about what, how, and why. Official explanation exists. Alternative theories exist. Focus on timelines, contradictions, forensics. | E3: JFK assassination, 9/11, January 6, Las Vegas shooting, MH370, TWA 800 | F3: EVENT | G3: Timeline (detailed), Contradictions, Evidence Cards, Witness Testimony, Open Questions, Media Gallery, Narrative Comparison
A4: 2 | B4: PROGRAM | C4: Does/did this operation exist? | D4: An ongoing or historical operation with organizational structure. Doesn't matter if government admitted it or not — the question is whether the program exists or existed. | E4: MKUltra, COINTELPRO, mass surveillance, geoengineering, vaccine programs, Project Stargate | F4: PROGRAM | G4: Evidence Cards (heavy), Document Cards, Timeline, Contradictions, Claims (rated), Scientific Studies, Open Questions
A5: 3 | B5: INSTITUTION | C5: What do they actually do vs. what's claimed? | D5: A real organization whose actual power and activities are debated. They exist. The question is what they actually do versus what's claimed. | E5: Federal Reserve, Bilderberg, WEF, BlackRock, CFR, Rothschild network, Trilateral Commission | F5: INSTITUTION | G5: Narrative Comparison (documented vs claimed), Key Entities, Financial Records, Evidence Cards, Methodology
A6: 4 | B6: PROPAGANDA | C6: Who is running this campaign and why? | D6: Coordinated information campaigns, manufactured consensus, suppression operations. Bot campaigns, paid influencers, media coordination, narrative manufacturing. THE BLUE OCEAN TEMPLATE. | E6: Operation Mockingbird, Twitter Files, COVID lab leak suppression, Iraq WMD campaign, Candace Owens hit campaign | F6: PROPAGANDA | G6: Propagation Map, Campaign Timeline, Bot/Coordination Analysis, Financial Trail, Suppression Log, Narrative Comparison
A7: 5 | B7: PROPHETIC | C7: What does scripture say and what's the fulfillment status? | D7: Biblical prophecy, prediction claims, fulfillment tracking. Source is scripture, not speculation. Your 1,554-prophecy database. | E7: End times, mark of the beast, third temple, Ezekiel 38, rapture, four horsemen | F7: PROPHETIC | G7: Scripture Card, Interpretation Comparison (4 traditions), Fulfillment Tracker, Timeline, Cross-Links
A8: 6 | B8: PHENOMENON | C8: What is being observed and what explains it? | D8: Something observable that lacks explanation. The thing is reported. The cause is debated. Focus on sighting data and physical evidence. | E8: UFOs/UAP, Bigfoot, cattle mutilation, Bermuda Triangle, Skinwalker Ranch, crop circles | F8: PHENOMENON | G8: Sighting Map, Physical Evidence Cards, Scientific Explanation, Witness Testimony, Media Gallery
A9: 7 | B9: PATTERN | C9: Do these data points indicate coordination? | D9: No single event, but convergent data points suggesting coordination. Financial anomalies, suspicious clusters, timing coincidences, personnel overlaps. Requires statistical analysis. | E9: Clinton body count, financial market anomalies, death clusters, personnel overlap patterns | F9: PATTERN | G9: Pattern Analysis, Statistical Data, Base Rate Comparison, Evidence Cards, Entity Map, Timeline
A10: 8 | B10: SYMBOL | C10: What does this actually mean vs. what's claimed? | D10: Symbol interpretation theories. Shows what the symbol actually is (historical origin, documented meaning) vs. conspiracy interpretation. Heavy on images and visual evidence. | E10: Dollar bill symbols, Denver Airport murals, Masonic architecture, Saturn worship, 666 | F10: SYMBOL | G10: Media Gallery (heavy), Symbol Origin Card, Interpretation Comparison, Historical Context, Cross-Links
A11: 9 | B11: CULTURAL | C11: Is this fake/staged/not what it seems? | D11: Pop culture or reality-questioning theories. Often T5 but massive search volume. Demonstrates the rating system works honestly on T5 content just as well as T1. | E11: Paul McCartney replaced, Stevie Wonder can see, moon landing hoax, Mandela Effect, Tartaria, Finland doesn't exist | F11: CULTURAL | G11: Claims, Evidence Cards (thin), Pattern Analysis, Contradictions, "What Would Need to Be True"

Sheet MODULE_TEMPLATES
A1: OPENINTEL MODULE TEMPLATES | D1: 24 modules · 10–15 per case page · Snap in/out by case type
A2: # | B2: MODULE NAME | C2: CATEGORY | D2: WHAT IT CAPTURES | E2: FIELD SCHEMA (DB COLUMNS) | F2: USED IN
B3: BASE MODULES (Every case page)
A4: 1 | B4: 5W Card | C4: BASE | D4: Who/What/When/Where/Why quick reference. The entry point for every case page. | E4: case_id, who, what, when_start, when_end, where, why, summary, last_updated | F4: ALL
A5: 2 | B5: Verdict | C5: BASE | D5: One-sentence assessment with T-rating. The bottom line. | E5: case_id, verdict_text, t_rating, confidence, evidence_count, last_reviewed, reviewer | F5: ALL
A6: 3 | B6: Timeline | C6: BASE | D6: Chronological events with dates, sources, and verification status. | E6: event_id, case_id, date, time, event_desc, source_id, source_type, verified, disputed, notes | F6: ALL
A7: 4 | B7: Entity Card | C7: BASE | D7: Person/Org — name, role, connections, first appearance, current status. | E7: entity_id, entity_type, name, aliases, role, affiliations, first_appearance, status, connections[], bio | F7: ALL
A8: 5 | B8: Evidence Card | C8: BASE | D8: Single piece of evidence — type (1–38), source, tier, verification. The atomic unit of the platform. | E8: evidence_id, case_id, evidence_type_id, tier, source_url, source_name, description, verification_status, date_added, notes | F8: ALL
A9: 6 | B9: Related Cases | C9: BASE | D9: Cross-links to cases sharing entities, patterns, or methods. | E9: link_id, case_id_from, case_id_to, relationship_type, shared_entities[], shared_evidence[], strength | F9: ALL
A10: 7 | B10: "What Would Change This" | C10: BASE | D10: Single piece of evidence that would upgrade or downgrade the rating. The intellectual honesty anchor. | E10: case_id, upgrade_condition, downgrade_condition, current_gap, last_assessed | F10: ALL
A11: 8 | B11: 10 Things Card | C11: BASE | D11: Surprising verified facts most people don't know. The viral section — drives social sharing. | E11: case_id, fact_number, fact_text, source_id, surprise_score, verified | F11: ALL
A12: 9 | B12: Video/Image Card | C12: BASE | D12: Authenticated media with metadata, chain of custody. | E12: media_id, case_id, media_type, url, title, source, date_captured, metadata, chain_of_custody, authenticated | F12: ALL
A13: 10 | B13: Wikipedia Card | C13: BASE | D13: What Wikipedia says vs what the primary sources say. Comparison tool for editorial bias detection. | E13: case_id, wiki_url, wiki_summary, wiki_last_edited, primary_source_summary, divergence_score, edit_war_flag | F13: ALL
B14: SPECIALIZED MODULES (Loaded by case type)
A15: 11 | B15: Narrative Comparison | C15: SPECIALIZED | D15: Official vs Alternative side-by-side. Two-column analysis of competing accounts. | E15: comparison_id, case_id, official_claim, alternative_claim, evidence_for_official[], evidence_for_alt[], assessment | F15: EVENT, PROGRAM, INST
A16: 12 | B16: Contradictions | C16: SPECIALIZED | D16: Where accounts conflict with each other. Direct comparison of conflicting statements/evidence. | E16: contradiction_id, case_id, source_a, claim_a, source_b, claim_b, resolution_status, significance | F16: EVENT, PROGRAM
A17: 13 | B17: Document Card | C17: SPECIALIZED | D17: Specific document — title, classification, source, key content. For primary source document archives. | E17: doc_id, case_id, title, classification_level, source_archive, date_created, date_released, key_content, url, pages | F17: PROGRAM, EVENT
A18: 14 | B18: Witness Card | C18: SPECIALIZED | D18: Named testimony — who, when, under what conditions, corroboration status. | E18: witness_id, case_id, name, date_testimony, conditions, under_oath, corroborated_by[], credibility_notes | F18: EVENT, PHENOMENON
A19: 15 | B19: Financial Trail | C19: SPECIALIZED | D19: Money flows, payments, funding sources. Follow the money — auditable financial connections. | E19: flow_id, case_id, from_entity, to_entity, amount, currency, date, source_doc, purpose, verified | F19: INST, PROP, PROG
A20: 16 | B20: Propagation Map | C20: PROPAGANDA | D20: How information/narrative spread. Bot detection, timing analysis, organic vs coordinated spread patterns. | E20: prop_id, case_id, platform, first_appearance, spread_timeline[], bot_indicators, organic_score, coordination_score | F20: PROPAGANDA
A21: 17 | B21: Suppression Log | C21: PROPAGANDA | D21: Documented censorship, deplatforming, institutional force applied. Gemini's P_s suppression pressure variable. | E21: suppression_id, case_id, date, action_type, actor, target, platform, evidence_url, severity, institutional_force_score | F21: PROPAGANDA, PROG
A22: 18 | B22: Bot/Coordination Analysis | C22: PROPAGANDA | D22: Account age distributions, message timing, uniformity metrics. Detecting inorganic amplification. | E22: analysis_id, case_id, platform, account_age_dist, timing_pattern, message_uniformity, hashtag_coordination, verdict | F22: PROPAGANDA
A23: 19 | B23: Scripture Card | C23: PROPHETIC | D23: Bible reference, original language text, 4 interpretive traditions comparison. | E23: scripture_id, book, chapter, verse_start, verse_end, hebrew_greek_text, english_text, tradition_1, tradition_2, tradition_3, tradition_4 | F23: PROPHETIC
A24: 20 | B24: Fulfillment Tracker | C24: PROPHETIC | D24: Prophecy status — unfulfilled/partially/fulfilled + supporting evidence for each status. | E24: prophecy_id, scripture_id, status, fulfillment_evidence[], partial_indicators[], date_assessed, confidence | F24: PROPHETIC
A25: 21 | B25: Interpretation Comparison | C25: MULTI-USE | D25: 4-tradition comparison for prophecy; multi-view comparison for symbols. How different schools read the same thing. | E25: interp_id, case_id, subject, interpretation_1, source_1, interpretation_2, source_2, interpretation_3, source_3, interpretation_4, source_4 | F25: PROPHETIC, SYMBOL
A26: 22 | B26: Sighting Map | C26: PHENOMENON | D26: Geographic locations of reported observations. Latitude/longitude, date, witness count, corroboration. | E26: sighting_id, case_id, lat, lon, location_name, date, time, witness_count, description, corroborated, evidence_ids[] | F26: PHENOMENON
... A28: 24 | B28: Pattern Analysis | C28: MULTI-USE | D28: Statistical data, base rates, anomaly detection. Quantitative pattern assessment with controls. | E28: pattern_id, case_id, data_points[], base_rate, observed_rate, sigma_deviation, p_value, methodology, controls_applied | F28: PATTERN, CULTURAL

Sheet CASE_MODULE_MAP
A1: CASE × MODULE MATRIX
A2: # | B2: MODULE | C2: EVENT | D2: PROGRAM | E2: INSTIT. | F2: PROPAG. | G2: PROPH. | H2: PHENOM. | I2: PATTERN | J2: SYMBOL | K2: CULTURAL
B3: BASE MODULES
A4: 1 | B4: 5W Card | C4: ✓ | D4: ✓ | E4: ✓ | F4: ✓ | G4: ✓ | H4: ✓ | I4: ✓ | J4: ✓ | K4: ✓
A5: 2 | B5: Verdict | C5: ✓ | D5: ✓ | E5: ✓ | F5: ✓ | G5: ✓ | H5: ✓ | I5: ✓ | J5: ✓ | K5: ✓
A6: 3 | B6: Timeline | C6: ✓ | D6: ✓ | E6: ✓ | F6: ✓ | G6: ✓ | H6: ✓ | I6: ✓ | J6: ✓ | K6: ✓
A7: 4 | B7: Entity Card | C7: ✓ | D7: ✓ | E7: ✓ | F7: ✓ | G7: ✓ | H7: ✓ | I7: ✓ | J7: ✓ | K7: ✓
A8: 5 | B8: Evidence Card | C8: ✓ | D8: ✓ | E8: ✓ | F8: ✓ | G8: ✓ | H8: ✓ | I8: ✓ | J8: ✓ | K8: ✓
A9: 6 | B9: Related Cases | C9: ✓ | D9: ✓ | E9: ✓ | F9: ✓ | G9: ✓ | H9: ✓ | I9: ✓ | J9: ✓ | K9: ✓
A10: 7 | B10: "What Would Change This" | C10: ✓ | D10: ✓ | E10: ✓ | F10: ✓ | G10: ✓ | H10: ✓ | I10: ✓ | J10: ✓ | K10: ✓
A11: 8 | B11: 10 Things Card | C11: ✓ | D11: ✓ | E11: ✓ | F11: ✓ | G11: ✓ | H11: ✓ | I11: ✓ | J11: ✓ | K11: ✓
A12: 9 | B12: Video/Image Card | C12: ✓ | D12: ✓ | E12: ✓ | F12: ✓ | G12: ✓ | H12: ✓ | I12: ✓ | J12: ✓ | K12: ✓
A13: 10 | B13: Wikipedia Card | C13: ✓ | D13: ✓ | E13: ✓ | F13: ✓ | G13: ✓ | H13: ✓ | I13: ✓ | J13: ✓ | K13: ✓
B14: SPECIALIZED MODULES
A15: 11 | B15: Narrative Comparison | C15: ✓ | D15: ✓ | E15: ✓ | F15: ✓
A16: 12 | B16: Contradictions | C16: ✓ | D16: ✓ | K16: ✓
A17: 13 | B17: Document Card | C17: ✓ | D17: ✓
A18: 14 | B18: Witness Card | C18: ✓ | H18: ✓
A19: 15 | B19: Financial Trail | D19: ✓ | E19: ✓ | F19: ✓
A20: 16 | B20: Propagation Map | F20: ✓
A21: 17 | B21: Suppression Log | D21: ✓ | F21: ✓
A22: 18 | B22: Bot/Coordination Analysis | F22: ✓
A23: 19 | B23: Scripture Card | G23: ✓
A24: 20 | B24: Fulfillment Tracker | G24: ✓
A25: 21 | B25: Interpretation Comparison | G25: ✓ | J25: ✓
A26: 22 | B26: Sighting Map | H26: ✓
A27: 23 | B27: Symbol Origin Card | J27: ✓
A28: 24 | B28: Pattern Analysis | I28: ✓ | K28: ✓
B30: MODULES PER CASE TYPE | C30: =COUNTA(C4:C28) -> 14 | D30: =COUNTA(D4:D28) -> 15 | E30: =COUNTA(E4:E28) -> 12 | F30: =COUNTA(F4:F28) -> 15 | G30: =COUNTA(G4:G28) -> 13 | H30: =COUNTA(H4:H28) -> 12 | I30: =COUNTA(I4:I28) -> 11 | J30: =COUNTA(J4:J28) -> 12 | K30: =COUNTA(K4:K28) -> 12

Sheet TEMPLATE_THEOPHYSICS_FACTS (1)
A1: RESEARCH INTAKE ENGINE
A2: Answer 6 questions. The system configures itself. Every run is saved and repeatable.
A4: §1 — INTAKE FORM (6 CONTROL QUESTIONS)
A5: FIELD | B5: QUESTION | C5: YOUR ANSWER ▼ + notes below ↓ | D5: WHAT THIS CONTROLS | E5: SYSTEM CODE
A6: Q1 | B6: What is the target type? | D6: Determines how the case row is created and what metadata schema applies | E6: → cases.target_type → sets metadata columns → determines link discovery method
A7: ↳ notes | D7: Add context, aliases, notes, or scope clarification | E7: =IF(C6="","",INDEX(DROPDOWNS!$CT$2:$CT$7,MATCH(C6,DROPDOWNS!$BR$2:$BR$7,0)))
A8: Q2 | B8: What is the research intent? | D8: Determines what the pipeline DOES — define, collect, rip, map, timeline, etc. | E8: → case_runs.intent → selects which workers fire → determines output tables populated
A9: ↳ notes | D9: Describe specific intent, keywords, what you're looking for | E9: =IF(C8="","",INDEX(DROPDOWNS!$CU$2:$CU$8,MATCH(C8,DROPDOWNS!$BS$2:$BS$8,0)))
A10: Q3 | B10: What source scope? | D10: Determines WHERE to search — Wikipedia only, trusted hubs, web-wide, archives, etc. | E10: → case_runs.source_scope → filters link discovery → sets source_type on links table
A11: ↳ notes | D11: Specify domains, include/exclude sources, trusted exceptions | E11: =IF(C10="","",INDEX(DROPDOWNS!$CV$2:$CV$7,MATCH(C10,DROPDOWNS!$BT$2:$BT$7,0)))
A12: Q4 | B12: What depth? | D12: Determines HOW MANY links to collect and how many hops deep | E12: → case_runs.depth → sets max_links, max_hops → controls rip queue size
A13: ↳ notes | D13: Note any hard limits, priority sources to rip first | E13: =IF(C12="","",INDEX(DROPDOWNS!$CW$2:$CW$7,MATCH(C12,DROPDOWNS!$BU$2:$BU$7,0)))
A14: Q5 | B14: What output do you want? | D14: Determines what the system PRODUCES — link list, entities, timeline, workbook, JSON, etc. | E14: → case_runs.output_type → selects export workers → determines final artifact format
A15: ↳ notes | D15: Describe what the output should contain, who will use it | E15: =IF(C14="","",INDEX(DROPDOWNS!$CX$2:$CX$11,MATCH(C14,DROPDOWNS!$BV$2:$BV$11,0)))
A16: Q6 | B16: How should it organize results? | D16: Determines the PRIMARY KEY / GROUP BY for how output is sorted and sectioned | E16: → case_runs.org_mode → sets ORDER BY / GROUP BY → controls workbook tab structure
A17: ↳ notes | D17: Describe how you want results grouped, primary audience | E17: =IF(C16="","",INDEX(DROPDOWNS!$CY$2:$CY$8,MATCH(C16,DROPDOWNS!$BW$2:$BW$8,0)))
A18: MEDIA / API INTAKE (optional — Q7–Q9) | B18: Skip Q7–Q9 if you are only harvesting links. Fill them in to activate the YouTube / media pipeline.
A19: Q7 | B19: Include media / video sources? | D19: Activates P4b media harvest — YouTube, podcast, or other platform sources | E19: =IF(C19="Yes — Include Media","include_media",IF(C19="No — Links Only","links_only",IF(C19="Later / Decide Per Run","defer","")))
A20: ↳ notes | D20: Paste YouTube URLs, channel names, playlists, or search terms
A21: Q8 | B21: What media asset types do you want? | D21: Determines what gets harvested per video — metadata only is fast/free, transcripts cost more | E21: =IF(C21="Metadata Only","metadata_only",IF(C21="Metadata + Transcripts","transcript",IF(C21="Metadata + Transcripts + Comments","transcript_comments",IF(C21="Full Research Harvest","research_harvest",IF(C21="Deep Media Harvest","deep_media_harvest","")))))
A22: ↳ notes | D22: e.g. 'transcripts only, no comments' or 'full research harvest on top 20 videos'
A23: Q9 | B23: Media harvest mode? | D23: Sets depth + volume cap. Deep Media Harvest can explode — defaults keep it disciplined | E23: =IF(C23="Channel Inventory (metadata only)","channel_inventory",IF(C23="Transcript Harvest (up to 500 videos)","transcript_harvest",IF(C23="Research Harvest (up to 200 videos)","research_harvest",IF(C23="Deep Media Harvest (up to 50 videos)","deep_media_harvest",""))))
A24: ↳ notes | D24: Note any specific channels to exclude, max video count, or date range constraints
A26: §2 — PROCESS MAP (WHAT EACH ANSWER TRIGGERS)
A27: Q1 OPTIONS — Target Type | B27: What It Creates | C27: Metadata Schema | D27: Link Discovery Method | E27: Example
A28: single_case | B28: 1 case row, focused link harvest | C28: case_name, canonical_title, aliases, category | D28: Wikipedia page → outlinks → See Also → References | E28: MKUltra
A29: category | B29: 1 parent case + N child cases | C29: category_name, member_count, taxonomy_path | D29: Wikipedia category page → all member articles → subcategories | E29: Government surveillance programs
A30: person | B30: 1 case row + entity record | C30: person_name, birth, death, roles, affiliations | D30: Wikipedia bio → career sections → related people → references | E30: Sidney Gottlieb
A31: organization | B31: 1 case row + entity record | C31: org_name, type, jurisdiction, parent_org, dates | D31: Wikipedia org page → history → controversies → subsidiaries | E31: CIA Office of Scientific Intelligence
A32: topic | B32: 1 case row + keyword cluster | C32: topic_name, related_terms, domain, era | D32: Wikipedia topic → related articles → cross-references | E32: Mass surveillance
A33: keyword_cluster | B33: N search runs → merged link set | C33: keywords[], cluster_name, search_strategy | D33: Multiple keyword searches → dedupe → rank by overlap | E33: mind control + LSD + CIA + experiments
A35: Q2 OPTIONS — Research Intent | B35: Pipeline Action | C35: Workers That Fire | D35: Output Tables Populated
A36: define_it | B36: Collect and synthesize what this IS | C36: search → rip → extract_claims → summarize | D36: cases, links, raw_pages, extracted_claims
A37: aggregate_sources | B37: Build a source inventory | C37: search → collect_links → classify → score | D37: cases, links, source_scores
A38: rip_site | B38: Download and store specific page(s) | C38: rip → store_raw → extract_metadata | D38: cases, links, raw_pages
A39: find_outgoing_links | B39: Map where a page POINTS TO | C39: rip → parse_links → classify_targets | D39: cases, links (with direction=outgoing)
A40: find_best_evidence | B40: Rank and tier evidence quality | C40: search → rip → extract → score → tier | D40: cases, links, raw_pages, extracted_claims, source_scores
A41: build_timeline | B41: Extract and order dated events | C41: rip → extract_dates → extract_events → order | D41: cases, links, raw_pages, timeline_events
A42: build_entity_map | B42: Extract people/orgs/places and their relationships | C42: rip → NER → relation_extract → graph_write | D42: cases, links, raw_pages, extracted_entities, entity_edges
A44: Q3 OPTIONS — Source Scope | B44: Where It Searches | C44: Domains Allowed | D44: Trust Level
A45: wikipedia_only | B45: en.wikipedia.org only | C45: en.wikipedia.org | D45: High — encyclopedic, cited, structured
A46: trusted_hubs | B46: Wikipedia + curated source list | C46: wikipedia, archive.org, .gov, .edu, selected .org | D46: High — vetted domains only
A47: web_wide | B47: Any domain, scored after collection | C47: Any (scored post-collection) | D47: Variable — requires scoring pass
... A50: mixed | B50: All of the above, layered by trust tier | C50: All (tagged by source_class) | D50: Tiered — T1/T2/T3 scoring applied
A52: Q4 OPTIONS — Depth | B52: Max Links | C52: Max Hops | D52: Rip Queue | E52: Cost Estimate
A53: top_10 | B53: 10 | C53: 0 (seed page only) | D53: Top 2-4 pages | E53: $— minimal
A54: top_25 | B54: 25 | C54: 0 | D54: Top 5-8 pages | E54: $ low
A55: top_50 | B55: 50 | C55: 0-1 | D55: Top 10-15 pages | E55: $$ moderate
A56: one_hop | B56: 100+ | C56: 1 | D56: Seed + all outlinks ripped | E56: $$$ significant
A57: two_hops | B57: 500+ | C57: 2 | D57: Seed + outlinks + their outlinks | E57: $$$$ heavy
A58: deep_crawl | B58: 1000+ | C58: 3+ | D58: Exhaustive — everything reachable | E58: $$$$$ max
A60: Q5 OPTIONS — Output Type | B60: What Gets Produced | C60: Format | D60: Where It Goes
A61: link_list | B61: Flat list of URLs with metadata | C61: CSV / JSON | D61: links table → export
A62: source_inventory | B62: Scored, classified source list | C62: CSV / Workbook | D62: links + source_scores → export
A63: ripped_pages | B63: Full page content stored | C63: Markdown / HTML in Postgres | D63: raw_pages table
A64: entities | B64: People, orgs, places extracted | C64: JSON / CSV | D64: extracted_entities + entity_edges → export
A65: timeline_events | B65: Dated events in order | C65: JSON / CSV / Workbook | D65: timeline_events → export
A66: workbook | B66: Multi-tab Excel with all outputs | C66: .xlsx | D66: All relevant tables → tabs
A67: notebook | B67: Narrative research document | C67: Markdown / HTML | D67: All tables → rendered narrative
A68: package_json | B68: Full structured export for downstream | C68: JSON bundle | D68: All tables → nested JSON
A69: knowledge_graph | B69: Full knowledge graph: all nodes, edges, clusters for the case | C69: D3 JSON / GraphML / Gephi / Cytoscape | D69: kg_nodes + kg_edges + kg_clusters → snapshot
A70: graph_snapshot | B70: Frozen graph state at this run — comparable across runs over time | C70: JSON bundle | D70: kg_graph_snapshots table
A73: Q6 OPTIONS — Organization Mode | B73: Primary Grouping | C73: SQL Equivalent | D73: Workbook Tab Structure
... A80: by_graph | B80: Graph-first: nodes as primary grouping, edges as navigation | C80: Serialize kg_graph_snapshots by cluster | D80: Tabs or sections per kg_cluster; visual graph as primary output
A82: §3 — POSTGRES SCHEMA (10 CORE TABLES)
A83: Layer 1 — CASE MANAGEMENT
A84: TABLE | B84: COLUMNS | C84: PRIMARY KEY | D84: FOREIGN KEYS | E84: FED BY Q#
A85: cases | B85: case_id, canonical_title, target_type, category, aliases[], priority, status, created_at, notes | C85: case_id (UUID) | D85: — | E85: Q1
A86: case_runs | B86: run_id, case_id, intent, source_scope, depth, output_type, org_mode, config_json, started_at, completed_at, status | C86: run_id (UUID) | D86: case_id → cases | E86: Q1–Q6 (ALL)
A88: Layer 2 — LINK INVENTORY
A89: links | B89: link_id, case_id, run_id, url, canonical_url, source_domain, source_type, direction, hop_depth, priority, label, notes, seed_type, discovery_mode, link_role, independence_class, capture_method, snapshot_status, triage_status, keep_reason, title_confidence, date_confidence, source_type_confidence, entity_confidence | C89: link_id (UUID) UNIQUE(canonical_url, case_id) | D89: case_id → cases run_id → case_runs | E89: Q3, Q4 + §9 ingestion fields
A90: source_scores | B90: score_id, link_id, trust_tier (T1/T2/T3), relevance_score, authority_score, freshness_score, composite_score, scored_at | C90: score_id (UUID) | D90: link_id → links | E90: Q2 (score intents)
A92: Layer 3 — RIPPED CONTENT
A93: raw_pages | B93: page_id, link_id, case_id, url, title, raw_html_path, markdown_text, word_count, ripped_at, source_domain, http_status | C93: page_id (UUID) | D93: link_id → links case_id → cases | E93: Q2 (rip intents), Q4
A95: Layer 4 — EXTRACTED STRUCTURE
A96: extracted_claims | B96: claim_id, page_id, case_id, claim_text, claim_type, confidence, evidence_tier, source_sentence, extracted_at | C96: claim_id (UUID) | D96: page_id → raw_pages case_id → cases | E96: Q2 (define/evidence)
A97: extracted_entities | B97: entity_id, case_id, entity_name, entity_type (person/org/place/event), aliases[], first_seen_page, mention_count, extracted_at | C97: entity_id (UUID) | D97: case_id → cases | E97: Q2 (entity_map)
A98: entity_edges | B98: edge_id, source_entity_id, target_entity_id, relationship_type, evidence_page_id, confidence, extracted_at | C98: edge_id (UUID) | D98: source/target → extracted_entities evidence → raw_pages | E98: Q2 (entity_map)
A99: timeline_events | B99: event_id, case_id, event_date, date_precision (day/month/year/decade), event_description, source_page_id, entities_involved[], extracted_at | C99: event_id (UUID) | D99: case_id → cases source → raw_pages | E99: Q2 (timeline)
A100: Layer 4b — KNOWLEDGE GRAPH
A101: kg_nodes | B101: node_id, case_id, node_label, node_type (person/org/place/event/concept/document/claim/date), canonical_name, aliases[], description, source_page_id, confidence, created_at | C101: node_id (UUID) | D101: case_id → cases source → raw_pages | E101: Q2 (entity_map build_timeline define_it)
A102: kg_edges | B102: edge_id, source_node_id, target_node_id, relationship_type, relationship_label, direction (directed/undirected), weight (0.0–1.0), evidence_page_id[], confidence, temporal_start, temporal_end, created_at | C102: edge_id (UUID) | D102: source_node_id → kg_nodes target_node_id → kg_nodes evidence → raw_pages | E102: Q2 (entity_map)
A103: kg_clusters | B103: cluster_id, case_id, cluster_name, cluster_type (community/topic/timeline/org_hierarchy), node_ids[], description, algorithm_used, created_at | C103: cluster_id (UUID) | D103: case_id → cases | E103: P7 (AI clustering)
A104: kg_graph_snapshots | B104: snapshot_id, case_id, run_id, graph_json (full nodes+edges export), node_count, edge_count, density, diameter, format (D3/Gephi/Cytoscape/GraphML), created_at | C104: snapshot_id (UUID) | D104: case_id → cases run_id → case_runs | E104: P9 (export)
A111: Layer 4c — TESTIMONY
A112: testimony_records | B112: testimony_id, case_id, source_designation, source_type, collection_method, collection_setting, event_date_claimed, event_date_precision, statement_date, recall_delay_days (GENERATED ALWAYS), statement_text, statement_hash (SHA-256, UNIQUE), statement_vector_embedding, credibility_tier (DEFAULT 'UNASSESSED'), spontaneity_score, emotional_valence, sensory_specificity, temporal_specificity, self_doubt_markers, field_protocol_version (DEFAULT 'FIP-1.0'), page_id, run_id, created_at | C112: testimony_id (UUID) UNIQUE(statement_hash) | D112: case_id → cases page_id → raw_pages run_id → case_runs | E112: P5b (testimony extraction)
A113: testimony_credibility_assessment | B113: assessment_id, testimony_id, internal_consistency, external_corroboration, contextual_plausibility, source_competence, source_character_bias (all REAL 0-1), reliability_score, confidence_in_assessment, prior_statement_id, drift_detected (BOOLEAN), drift_type CHECK(AMPLIFICATION|ATTENUATION|REVERSAL|MIGRATION|ATTRIBUTION), critical_failure_mode, assessed_by, assessed_at | C113: assessment_id (UUID) | D113: testimony_id → testimony_records prior_statement_id → testimony_records | E113: Human review (credibility_tier cannot auto-assign)
A127: Layer 4d — MEDIA
A128: media_sources | B128: media_id, case_id, run_id, platform, platform_id, canonical_url, target_type, title, channel_id, channel_name, published_at, duration_seconds, view_count, like_count, comment_count, triage_status, independence_class, transcript_status, asset_types_collected[], keep_reason, kg_node_id, harvested_at | C128: media_id (UUID) UNIQUE(canonical_url, case_id) | D128: case_id → cases run_id → case_runs kg_node_id → kg_nodes | E128: P4b (harvest)
A129: media_transcripts | B129: transcript_id, media_id, transcript_source (auto_captions|manual|whisper), full_text, word_count, language, confidence_score, segments_json (timestamped array), extracted_at | C129: transcript_id (UUID) | D129: media_id → media_sources | E129: P4b
A130: media_comments | B130: comment_id, media_id, platform_comment_id, author_id, comment_text, comment_hash (UNIQUE), published_at, like_count, reply_count, parent_comment_id, harvested_at | C130: comment_id (UUID) UNIQUE(comment_hash) | D130: media_id → media_sources parent_comment_id → media_comments | E130: P4b (Deep only)
A132: Layer 5 — CONFIG & AI
A133: run_configs | B133: config_id, run_id, q1_target_type, q2_intent, q3_scope, q4_depth, q5_output, q6_org_mode, custom_params_json, created_at | C133: config_id (UUID) | D133: run_id → case_runs | E133: Q1–Q6 (saved)
A134: ai_jobs | B134: job_id, run_id, page_id, job_type (summarize/extract/classify/embed), model_used, input_tokens, output_tokens, cost_usd, result_json, started_at, completed_at | C134: job_id (UUID) | D134: run_id → case_runs page_id → raw_pages | E134: Pipeline (auto)
A136: §4 — PIPELINE STAGES (Intake → Postgres → AI → Output)
A137: STAGE | B137: ACTION | C137: POSTGRES TABLES TOUCHED | D137: AI REQUIRED? | E137: COST TIER
A138: P1 — CONFIGURE | B138: User fills 6 questions → run_config created | C138: cases, case_runs, run_configs | D138: No | E138: Free
A139: P2 — SEARCH | B139: Discover links based on Q1 target + Q3 scope | C139: links | D139: No (scraper/parser) | E139: $
A140: P3 — COLLECT | B140: Harvest top N links based on Q4 depth | C140: links (expanded) | D140: No | E140: $
A141: P4 — RIP | B141: Download and store page content (top 2-4 per case first) | C141: raw_pages | D141: No | E141: $$
...

Sheet FACTS_PAPER
A1: THEOPHYSICS — LOWE FACTS FORMAT
A2: Navigate cell by cell. Click any yellow cell — dropdown menus appear. Fill what you can. Skip what you can't.
A4: 📋 PAPER METADATA
A5: Paper ID | B5: [e.g., NUC-THESIS-001]
A6: Title | B6: [Your papthe bank first alarm company called back is that right now getting zones S stairwell er title]
A7: Paper Type | B7: [Select ▼]
A8: Series | B8: [Select ▼]
A9: Classification | B9: [Select ▼]
A10: Author | B10: David Lowe
A11: Co-Author | B11: [e.g., Claude (Opus)]
A12: Date | B12: [YYYY-MM-DD]
A13: Version | B13: 1.0
A14: Status | B14: [Draft / Review / Final]
A16: §0 AXIOM DECLARATION
A17: Foundational Axiom | B17: [One sentence. If this is false, the entire paper fails.]
A19: [F] FIND — THE ANOMALY
A20: What was observed? What pattern demands explanation?
A21: Observation | B21: [What did you notice?]
A22: Expected | B22: [What should have been true?]
A23: Actual | B23: [What IS true instead?]
A24: Prior Explanations | B24: [What others have said — and why it's insufficient]
A25: What's New Here | B25: [Your contribution]
A26: The Anomaly (2-3 paragraphs) | B26: [Write the core finding. No throat-clearing.]
A28: [A] ADMIT — THE BIAS
A29: Compressed Biaxiosum — who is writing this and what are their priors?
A30: Worldview | B30: [Select ▼] | C30: Details | D30: [Expand on selection if needed]
A31: Core Belief | B31: [Select ▼] | C31: Details | D31: [Expand on selection if needed]
A32: Epistemology | B32: [Select ▼] | C32: Details | D32: [Expand on selection if needed]
A33: Off-Ramp | B33: [Select ▼] | C33: Details | D33: [Expand on selection if needed]
A34: Priors | B34: [e.g., Master Equation χ, Ten Laws, 188 axioms]
A35: Mea Culpa | B35: [Honest limitations — what you might be wrong about]
A37: [C] CLAIM — THE THESIS
A38: Primary Question | B38: [One question this paper answers]
A39: THESIS (one sentence) | B39: [One sentence. The claim. No hedging.]
A40: Support 1 | B40: [Supporting argument 1]
A41: Support 2 | B41: [Supporting argument 2]
A42: Support 3 | B42: [Supporting argument 3]
A43: Predictions
A44: If True → 1 | B44: [Observable consequence 1]
A45: If True → 2 | B45: [Observable consequence 2]
A46: If True → 3 | B46: [Observable consequence 3]
A47: If False → 1 | B47: [What would be true instead 1]
A48: If False → 2 | B48: [What would be true instead 2]
A49: If False → 3 | B49: [What would be true instead 3]
A51: [T] TEST — THE PROOF
A52: Method Summary | B52: [How was this investigated?]
A53: Tools Used (select all that apply)
A54: Tool 1 | B54: [Select ▼] | C54: Source/Detail | D54: [Specify dataset or source]
A55: Tool 2 | B55: [Select ▼] | C55: Source/Detail | D55: [Specify dataset or source]
A56: Tool 3 | B56: [Select ▼] | C56: Source/Detail | D56: [Specify dataset or source]
A57: Tool 4 | B57: [Select ▼] | C57: Source/Detail | D57: [Specify dataset or source]
A59: Evidence Table
A60: # | B60: Domain / Variable | C60: Finding | D60: Metric | E60: Source
A61: 1 | B61: [Select ▼]
A62: 2 | B62: [Select ▼]
A63: 3 | B63: [Select ▼]
A64: 4 | B64: [Select ▼]
A65: 5 | B65: [Select ▼]
A66: 6 | B66: [Select ▼]
A67: 7 | B67: [Select ▼]
A69: Primary Finding | B69: [Main result in plain language]
A70: Unexpected | B70: [What you didn't expect to find]
A71: Null (no effect) | B71: [What returned nothing — intellectual honesty]
A72: Confidence | B72: [Select ▼]
A74: [S] SNAP — THE KILL CONDITIONS
A75: # | B75: Kill Condition | D75: Threshold | E75: Status
A76: 1 | B76: [How to destroy this claim] | D76: [What would count as evidence] | E76: [Select ▼]
A77: 2 | B77: [How to destroy this claim] | D77: [What would count as evidence] | E77: [Select ▼]
A78: 3 | B78: [How to destroy this claim] | D78: [What would count as evidence] | E78: [Select ▼]
A79: 4 | B79: [How to destroy this claim] | D79: [What would count as evidence] | E79: [Select ▼]
A80: 5 | B80: [How to destroy this claim] | D80: [What would count as evidence] | E80: [Select ▼]
A81: 6 | B81: [How to destroy this claim] | D81: [What would count as evidence] | E81: [Select ▼]
A83: 📐 FRAMEWORK POSITIONING
A84: χ Variables Addressed | B84: [Select ▼] | C84: [Select ▼] | D84: [Select ▼]
A85: Laws Invoked | B85: [Select ▼] | C85: [Select ▼] | D85: [Select ▼]
A86: Connection 1 | B86: [Link to other paper/axiom — how it connects]
A87: Connection 2 | B87: [Link to other paper/axiom — how it connects]
A89: 🔋 THE LOWE BATTERY
A90: LCT (Coherence Test) | B90: Does the domain show coherence decay when the principle is violated? | E90: [Select ▼]
A91: LFT (Fruits Test) | B91: Does constraint removal correlate with negative outcomes? | E91: [Select ▼]
A92: LMT (Mastery Test) | B92: Can the model predict future states? | E92: [Select ▼]
A94: ✅ AUDIT BLOCK
A95: Format: Lowe FACTS Format v1.0
A96: Thesis Unit: [auto from Paper ID]
A97: Author: David Lowe
A98: Date: [auto from metadata]
A99: Kill Conditions Met: [ ] Yes [ ] No

Sheet DROPDOWNS
A1: Worldview | B1: Core Belief | C1: Epistemology | D1: Off-Ramp | E1: χ Variables | F1: Laws | G1: Test Methods | H1: Evidence Domains | I1: Kill Status | J1: Lowe Battery | K1: Paper Type | L1: Series | M1: Classification | N1: Severity | O1: Defense Outcome | P1: Overall Verdict | Q1: Fixable? | R1: Confidence | S1: Who Wins | T1: Survival | U1: Entity Type | V1: Precision | W1: Evidence Type | X1: Terminus | Y1: ISO Status | Z1: 7Q Paper Type | AA1: Ontological Status | AB1: Epistemological Mode | AC1: Inquiry Type | AD1: Cross-Domain Status | AE1: Evidence Strength | AF1: Connection Type | AG1: Uniqueness | AH1: Vulnerability Flags | AI1: Repro Status | AJ1: Effect Magnitude | AK1: Mechanism Type | AL1: Entity Epistemic | AM1: Entity Observational | AN1: Entity Formal | AO1: Object Status | AP1: Source Class | AQ1: Math Object Type | AR1: Formalism | AS1: Domain | AT1: Scale | AU1: Regime | AV1: Claim Type | AW1: Question Type | AX1: Coherence Prediction | AY1: Entropy Relation | AZ1: Grace Dependence | BA1: Consciousness Role | BB1: Evidence Tier | BC1: Proof Method | BD1: Proof Completeness | BE1: Derivation Method | BF1: Prediction Type | BG1: Prediction Status | BH1: Death Condition | BI1: Branch Status | BJ1: Collapse Scope | BK1: Framework Damage | BL1: Proof Status | BM1: Debate Resolution | BN1: Pipeline Status | BO1: Gate Decision | BP1: Pipeline Domain | BQ1: Current Step | BR1: Q1 — Target Type | BS1: Q2 — Research Intent | BT1: Q3 — Source Scope | BU1: Q4 — Depth | BV1: Q5 — Output Format | BW1: Q6 — Organization Mode | BX1: Seed Type | BY1: Discovery Mode | BZ1: Link Role | CA1: Independence Class | CB1: Capture Method | CC1: Snapshot Status | CD1: Triage Status | CE1: Keep Reason | CF1: Source Type (Testimony) | CG1: Collection Method | CH1: Collection Setting | CI1: Date Precision | CJ1: Credibility Tier | CK1: Drift Type | CL1: YT Target Type | CM1: YT Asset Types | CN1: YT Scope | CO1: YT Depth | CP1: YT Output Format | CQ1: YT Org Mode | CR1: Harvest Mode | CS1: Platform | CT1: Q1 codes (lookup) | CU1: Q2 codes (lookup) | CV1: Q3 codes (lookup) | CW1: Q4 codes (lookup) | CX1: Q5 codes (lookup) | CY1: Q6 codes (lookup) | CZ1: Case Type | DA1: Evidence Tier | DB1: Evidence Type (T1) | DC1: Evidence Type (T2) | DD1: Evidence Type (T3) | DE1: Evidence Type (T4) | DF1: Evidence Type (T5) | DG1: Evidence Type (Negative) | DH1: Module Category
A2: Christian Theist | B2: Physics and theology are dual projections of single substrate | C2: Empirical + Revelational | D2: About God — nothing | E2: G (Gravity/Grace) | F2: Law I — Gravity ↔ Grace | G2: Historical analysis | H2: Physics | I2: Not yet tested | J2: Pass | K2: Paper I — Foundational Claim | L2: Logos Papers | M2: Core | N2: Critical — framework fails | O2: Held | P2: Passed | Q2: Yes — minor revision | R2: 0.95+ (near-certain) | S2: Paper I | T2: Yes | U2: theorem | V2: precise | W2: experimental | X2: axiom | Y2: ISO-CONFIRMED 3+ | Z2: foundational | AA2: foundational | AB2: deductive | AC2: causal | AD2: ISO-CONFIRMED | AE2: conclusive | AF2: direct_test | AG2: exclusive | AH2: WHY-PENALTY | AI2: replicated | AJ2: negligible | AK2: physical | AL2: axiom | AM2: observation | AN2: definition | AO2: draft | AP2: theophysics_original | AQ2: equation | AR2: equation | AS2: physics | AT2: quantum | AU2: linear | AV2: descriptive | AW2: Type 1: Does X hold? | AX2: increases | AY2: opposes | AZ2: required | BA2: fundamental | BB2: tier_1 | BC2: direct | BD2: complete | BE2: deductive | BF2: retrodictive | BG2: untested | BH2: self_refutation | BI2: dead | BJ2: local | BK2: minimal | BL2: open | BM2: unresolved | BN2: Not Started | BO2: PASS | BP2: physics | BQ2: S01 — CONCEPT | BR2: Single Case Investigation | BS2: Define & Describe It | BT2: Wikipedia Only | BU2: Top 10 Links | BV2: Link List Only | BW2: By Case | BX2: case_name | BY2: wiki_page_links | BZ2: seed | CA2: primary_source | CB2: html_scrape | CC2: not_archived | CD2: new | CE2: foundational_overview | CF2: FIRST_HAND | CG2: in_person_interview | CH2: VOLUNTARY | CI2: EXACT (+3) | CJ2: UNASSESSED (default — blocked) | CK2: AMPLIFICATION | CL2: single_video | CM2: metadata_only | CN2: newest_only | CO2: video_only | CP2: csv_index | CQ2: by_channel | CR2: channel_inventory | CS2: youtube | CT2: single_case | CU2: define_it | CV2: wikipedia_only | CW2: top_10 | CX2: link_list | CY2: by_case | CZ2: EVENT | DA2: T1 — Primary Sources | DB2: 1 — Declassified Government Documents | DC2: 9 — Investigative Journalism | DD2: 16 — Statistical/Pattern Analysis | DE2: 22 — Anonymous Sources | DF2: 29 — Single-Source Claims | DG2: 35 — Conspicuous Absence | DH2: BASE
A3: Deist | B3: Reality has a Logos structure discoverable through physics | C3: Empirical only | D3: Would change mind if kill conditions met | E3: M (Mass-Energy/Meaning) | F3: Law II — Mass-Energy ↔ Meaning | G3: Cross-domain synthesis | H3: Theology | I3: Not yet falsified | J3: Fail | K3: Paper II — Adversarial | L3: Theophysics Applied | M3: Bridge | N3: Major — paper fails | O3: Partially held | P3: Conditional Pass | Q3: Yes — major revision | R3: 0.90 (high) | S3: The Objection | T3: Partially | U3: law | V3: mathematical | W3: mathematical | X3: empirical | Y3: ISO-CONFIRMED 2 | Z3: bridge | AA3: derived | AB3: inductive | AC3: descriptive | AD3: ISO-PARALLEL | AE3: strong | AF3: indirect_test | AG3: discriminating | AH3: NO_LIVED_VALIDITY | AI3: partial | AJ3: small | AK3: mathematical | AL3: hypothesis | AM3: evidence | AN3: equation | AO3: candidate | AP3: scripture | AQ3: theorem | AR3: inequality | AS3: biology | AT3: microscopic | AU3: nonlinear | AV3: causal | AW3: Type 2: What is X? | AX3: decreases | AY3: generates | AZ3: enhancing | BA3: emergent | BB3: tier_2 | BC3: contradiction | BD3: partial | BE3: inductive | BF3: predictive | BG3: confirmed | BH3: infinite_regress | BI3: survives | BJ3: domain | BK3: moderate | BL3: argued | BM3: resolved_in_favor | BN3: In Progress | BO3: FAIL | BP3: theology | BQ3: S02 — WRITING | BR3: Category / Program Family | BS3: Aggregate Sources | BT3: Trusted Hubs (Wikipedia + .gov + .edu + archives) | BU3: Top 25 Links | BV3: Source Inventory | BW3: By Source Type | BX3: single_url | BY3: wiki_references | BZ3: reference | CA3: independent_reporting | CB3: api_result | CC3: wayback_saved | CD3: queued | CE3: primary_evidence | CF3: SECOND_HAND | CG3: written_statement | CH3: REQUESTED | CI3: DATE_RANGE (+2) | CJ3: CORROBORATED (T1–T2 eligible) | CK3: ATTENUATION | CL3: channel | CM3: transcript | CN3: top_N | CO3: video_plus_channel | CP3: excel_workbook | CQ3: by_video | CR3: transcript_harvest | CS3: tiktok | CT3: category | CU3: aggregate_sources | CV3: trusted_hubs | CW3: top_25 | CX3: source_inventory | CY3: by_source_type | CZ3: PROGRAM | DA3: T2 — Secondary Sources | DB3: 2 — Congressional/Parliamentary Records | DC3: 10 — Witness Testimony (Named) | DD3: 17 — Circumstantial Evidence Chains | DE3: 23 — Secondhand/Hearsay | DF3: 30 — Anonymous Internet Posts | DG3: 36 — Suppression Evidence | DH3: SPECIALIZED
A4: Agnostic | B4: Consciousness is fundamental, not emergent | C4: Rationalist | D4: Would change mind given sufficient counter-evidence | E4: E (Electromagnetism/Truth) | F4: Law III — Electromagnetism ↔ Truth | G4: External data (specify sources) | H4: Consciousness | I4: Tested — survived | J4: Pending | K4: Paper III — Application | L4: Convergence (Substack) | M4: Experimental | N4: Minor — claim weakened | O4: Broke | P4: Failed | Q4: No — fundamental problem | R4: 0.85 (strong) | S4: Draw | T4: No | U4: equation | V4: detailed | W4: computational | X4: brute_fact | Y4: ISO-PARALLEL 3+ | Z4: adversarial | AA4: structural | AB4: abductive | AC4: predictive | AD4: ISO-ANALOGY | AE4: moderate | AF4: analogy | AG4: ambiguous | AH4: UNFALSIFIABLE | AI4: unreplicated | AJ4: medium | AK4: logical | AL4: theory | AM4: evidence_bundle | AN4: law | AO4: provisional | AP4: peer_review | AQ4: axiom | AR4: operator | AS4: chemistry | AT4: cellular | AU4: perturbative | AV4: ontological | AW4: Type 3: What grounds X? | AX4: maintains | AY4: neutral | AZ4: independent | BA4: participatory | BB4: tier_3 | BC4: induction | BD4: sketch | BE4: abductive | BF4: structural | BG4: disconfirmed | BH4: empirical_contradiction | BI4: problematic | BJ4: framework | BK4: severe | BL4: derived | BM4: resolved_against | BN4: Done | BO4: BORDERLINE | BP4: consciousness | BQ4: S03 — COLLECTION | BR4: Person / Individual | BS4: Rip a Site | BT4: Web-Wide | BU4: Top 50 Links | BV4: Ripped Pages | BW4: By Date / Chronological | BX4: domain | BY4: site_search | BZ4: outlink | CA4: quoting_primary | CB4: pdf_extraction | CC4: local_copy | CD4: ripped | CE4: timeline_anchor | CF4: INSTITUTIONAL | CG4: recorded_audio | CH4: CUSTODIAL | CI4: MONTH_YEAR (+1) | CJ4: CREDIBLE (T2–T3 eligible) | CK4: REVERSAL | CL4: playlist | CM4: captions_timestamped | CN4: entire_channel | CO4: video_plus_related | CP4: transcript_files | CQ4: by_date | CR4: research_harvest | CS4: spotify | CT4: person | CU4: rip_site | CV4: web_wide | CW4: top_50 | CX4: ripped_pages | CY4: by_date | CZ4: INSTITUTION | DA4: T3 — Tertiary Sources | DB4: 3 — Court Records | DC4: 11 — Whistleblower Disclosures | DD4: 18 — Historical Precedent | DE4: 24 — Unverified Documents | DF4: 31 — Channeled/Psychic/Revelatory | DG4: 37 — Non-Denial Denials | DH4: PROPAGANDA
A5: Atheist / Materialist | B5: Universe has discoverable moral architecture | C5: Pragmatist | D5: Framework survives or dies on the math | E5: S (Strong Force/Love) | F5: Law IV — Strong Force ↔ Love | G5: Mathematical derivation | H5: Quantum | I5: Tested — partially held | J5: N/A | L5: Genesis to Quantum | M5: Speculative | N5: Cosmetic — presentation issue | O5: Deferred | Q5: Unknown — needs more work | R5: 0.80 (good) | S5: Inconclusive | U5: theory | V5: basic | W5: observational | X5: consensus | Y5: ISO-PARALLEL 2 | Z5: application | AA5: processual | AB5: transcendental | AC5: normative | AD5: DOMAIN-BOUND | AE5: suggestive | AF5: necessary | AG5: generic | AH5: UNGROUNDED | AI5: not_applicable | AJ5: large | AK5: biological | AL5: claim | AN5: mechanism | AO5: stable | AP5: historical | AQ5: identity | AR5: field_equation | AS5: consciousness | AT5: organism | AU5: non_perturbative | AV5: predictive | AW5: Type 4: What must X be? | AX5: oscillates | AY5: coupled | AZ5: none | BA5: observer | BC5: construction | BD5: conjectured | BE5: constructive | BF5: explanatory | BG5: ambiguous | BH5: logical_incoherence | BI5: terminal | BK5: catastrophic | BL5: tested | BM5: ongoing | BN5: Blocked | BO5: CONDITIONAL | BP5: moral | BQ5: S04 — YAML + AXIOM TRACE | BR5: Organization / Institution | BS5: Find Outgoing Links | BT5: Specific Domain(s) | BU5: One Hop Out | BV5: Entities & Relationships | BW5: By Entity (Person / Org / Place) | BX5: category_page | BY5: web_search | BZ5: citation | CA5: syndicated_copy | CB5: wayback_archive | CC5: markdown_ripped | CD5: classified | CE5: entity_source | CF5: ANONYMOUS | CG5: recorded_video | CH5: PUBLIC_RECORD | CI5: YEAR_ONLY (0) | CJ5: QUESTIONABLE (T3 cap) | CK5: MIGRATION | CL5: search_query | CM5: comments | CN5: date_range | CO5: video_plus_comments | CP5: json_package | CQ5: by_topic | CR5: deep_media_harvest | CS5: rumble | CT5: organization | CU5: find_outgoing_links | CV5: domain_specific | CW5: one_hop | CX5: entities | CY5: by_entity | CZ5: PROPAGANDA | DA5: T4 — Weak Sources | DB5: 4 — Official Admissions/Apologies | DC5: 12 — Academic Research/Analysis | DD5: 19 — Expert Opinion (Named) | DE5: 25 — Confession/Deathbed Statement | DF5: 32 — Unverifiable by Design | DG5: 38 — Classification/Redaction Patterns | DH5: PROPHETIC
A6: Pantheist | B6: Mathematics is the language of both physics and theology | C6: Cross-domain coherence as truth criterion | D6: Other (specify) | E6: T (Thermodynamics/Judgment) | F6: Law V — Thermodynamics ↔ Judgment | G6: Axiomatic derivation from Theophysics framework | H6: Scripture | I6: Tested — FAILED | L6: Dr. Thesis Unit | M6: Boundary | O6: Inconclusive | R6: 0.75 (moderate) | U6: mechanism | V6: vague | W6: meta_analytic | X6: authority | Y6: ISO-ANALOGY | Z6: destruction_manual | AA6: relational | AB6: empirical | AC6: mechanistic | AD6: BRIDGE | AE6: weak | AF6: sufficient | AH6: UNDEFINED | AI6: in_principle | AJ6: overwhelming | AK6: social | AL6: postulate | AN6: operator | AO6: canonical | AP6: commentary | AQ6: operator | AR6: lagrangian | AS6: theology | AT6: human | AU6: equilibrium | AV6: mathematical | AX6: none | BA6: none | BC6: existence | BE6: by_contradiction | BH6: unsupported | BL6: survived_adversary | BN6: N/A | BO6: KILL | BP6: meta | BQ6: S05 — SCORING ⛔ | BR6: Topic / Subject Area | BS6: Find Best Evidence | BT6: Archives & Legal Sources Only | BU6: Two Hops Out | BV6: Timeline of Events | BW6: By Confidence Level | BX6: search_query | BY6: sitemap | BZ6: related_article | CA6: same_domain_dup | CB6: manual_add | CC6: pdf_saved | CD6: scored | CE6: contradiction_source | CG6: sworn_testimony | CH6: ANONYMOUS_TIP | CI6: APPROXIMATE (-1) | CJ6: COMPROMISED (EC only) | CK6: ATTRIBUTION | CL6: topic | CM6: thumbnails | CN6: keyword_match | CO6: channel_all_videos | CP6: cleaned_text_nlp | CQ6: by_keyword_cluster | CS6: odysee | CT6: topic | CU6: find_best_evidence | CV6: archives_gov_legal | CW6: two_hops | CX6: timeline_events | CY6: by_confidence | CZ6: PROPHETIC | DA6: T5 — Weakest Sources | DB6: 5 — Leaked Documents | DC6: 13 — Photo/Video Evidence (Verified) | DD6: 20 — Contemporaneous News Reports | DE6: 26 — Pattern Recognition Without Controls | DF6: 33 — Circular/Self-Referencing | DH6: PHENOMENON
A7: Panentheist | B7: Other (specify) | C7: Bayesian + Falsificationist | E7: K (Information/Logos) | F7: Law VI — Information ↔ Logos | G7: Experimental correlation (specify dataset) | H7: Evidence/Data | I7: Deferred | L7: Standalone | R7: 0.70 (suggestive) | U7: observation | W7: clinical | X7: revelation* | Y7: DOMAIN-BOUND | AA7: dispositional | AB7: testimonial | AC7: constitutive | AE7: contested | AF7: corroborating | AH7: SELECTION_BIAS | AK7: theological | AN7: conservation_law | AO7: deprecated | AP7: speculative | AQ7: tensor | AR7: hamiltonian | AS7: moral | AT7: planetary | AU7: non_equilibrium | AV7: mechanistic | BC7: uniqueness | BH7: circular | BQ7: S06 — ADVERSARIAL ⛔ | BR7: Keyword Cluster | BS7: Build a Timeline | BT7: Mixed / Let System Decide | BU7: Deep Crawl | BV7: Full Workbook | BW7: By Domain / Subject | BX7: csv_list | BY7: page_outlinks | BZ7: archive_mirror | CA7: commentary | CB7: imported_csv | CC7: failed | CD7: reviewed | CE7: background_only | CG7: imported_existing | CI7: DECADE (-2) | CJ7: REJECTED (excluded) | CL7: person_show | CM7: chapter_markers | CN7: playlist_only | CO7: channel_all_with_transcripts | CP7: citation_clips | CQ7: by_speaker | CS7: twitter_x | CT7: keyword_cluster | CU7: build_timeline | CV7: mixed | CW7: deep_crawl | CX7: workbook | CY7: by_domain | CZ7: PHENOMENON | DA7: N — Negative Evidence | DB7: 6 — Scientific/Peer-Reviewed Studies | DC7: 14 — FOIA Request Responses | DD7: 21 — Correspondence/Communications | DE7: 27 — Archived/Deleted Content | DF7: 34 — AI-Generated/Manipulated | DH7: SYMBOL
A8: Process Theology | C8: Other (specify) | E8: R (Relativity/Relationship) | F8: Law VII — Relativity ↔ Relationship | G8: Biblical calibration | H8: Information Theory | R8: 0.60 (weak) | U8: hypothesis | W8: statistical | X8: circular | AB8: revelatory | AC8: correlational | AH8: SURVIVORSHIP_BIAS | AK8: computational | AN8: theorem | AP8: anonymous | AQ8: function | AR8: lindblad | AS8: mathematics | AT8: cosmological | AV8: normative | BQ8: S07 — DATA ANALYTICS | BS8: Map Entities & Relationships | BV8: Research Notebook | BW8: By Graph Structure | BX8: workbook_tab | BY8: manual_seed | BZ8: duplicate_candidate | CA8: unknown | CD8: promoted | CE8: weak_but_notable | CI8: UNKNOWN (-2) | CM8: audio_file | CS8: reddit | CU8: build_entity_map | CX8: notebook | CY8: by_graph | CZ8: PATTERN | DB8: 7 — Financial Records | DC8: 15 — Audit Reports | DE8: 28 — Documentary Film Claims | DH8: MULTI-USE
A9: Buddhist | E9: Q (Quantum/Faith) | F9: Law VIII — Quantum ↔ Faith | G9: Cross-civilizational validation | H9: History | R9: 0.50 (coin flip) | U9: conjecture | W9: historical | X9: infinite | AB9: computational | AC9: existential | AH9: CONFIRMATION_BIAS | AN9: identity | AQ9: inequality | AR9: conservation | AS9: information | AT9: metaphysical | AV9: conservation | BQ9: S08 — INTEGRATION | BV9: JSON Data Package | BY9: imported_csv | BZ9: unknown | CD9: discarded | CE9: unknown | CM9: video_file | CS9: vimeo | CX9: package_json | CZ9: SYMBOL | DB9: 8 — Physical/Forensic Evidence
A10: Islamic Monotheist | E10: F (Weak Force/Sin) | F10: Law IX — Weak Force ↔ Sin | G10: Statistical analysis | H10: Psychology | R10: Below 0.50 (dubious) | U10: claim | W10: case_study | AB10: phenomenological | AH10: P-HACKING | AN10: inequality | AQ10: lagrangian | AT10: multi_scale | AV10: symmetry_claim | BQ10: S09 — ARTIFACT HYGIENE | BV10: Knowledge Graph | CM10: related_videos | CX10: knowledge_graph | CZ10: CULTURAL
A11: Hindu Non-Dualist | E11: C (Coherence/Christ) | F11: Law X — Coherence ↔ Christ | G11: Computational verification (JAX/SymPy) | H11: Sociology | W11: testimonial | AH11: SMALL_N | AQ11: hamiltonian | AV11: boundary_condition | BQ11: S10 — TTS PIPELINE | BV11: Graph Snapshot | CX11: graph_snapshot
A12: Secular Humanist | G12: Other (specify) | H12: Economics | W12: phenomenological | AH12: SINGLE_SOURCE | BQ12: S11 — MEDIA GENERATION
A13: Other (specify) | H13: Linguistics | W13: scriptural* | AH13: UNREPLICATED | BQ13: S12 — PUBLISH PREP
W14: analogical | AH14: CIRCULAR | BQ14: S13 — QUARTZ DEPLOY
AH15: COMPETING_MODEL | BQ15: S14 — PUBLISHED
BQ16: S15 — DISTRIBUTED

Sheet DEFENSE_RECORD
A1: DEFENSE RECORD — Live Adversarial Session
A2: "The current defense is theater. Replace it with a real adversarial session."
A4: 📋 SESSION METADATA
A5: Date | B5: [YYYY-MM-DD]
A6: Thesis Unit | B6: [DT-XXX]
A7: Candidate | B7: David Lowe
A8: Designated Attacker | B8: [Name / AI system / Role]
A9: Attacker's Field | B9: [Must be OUTSIDE thesis domain]
A10: Duration | B10: [e.g., 2 hours]
A11: Format | B11: [Live / Async / Multi-session]
A13: ⚔️ PRE-DEFENSE: ATTACKER'S OPENING POSITION
A14: Attacker's Worldview | B14: [Biaxiosum for the attacker — what are THEIR priors?]
A15: Primary Line of Attack | B15: [What did they come to break?]
A16: Strongest Pre-Submitted Objection | B16: [Written before the session — their best shot with full prep time]
A18: 🥊 THE EXCHANGE
A19: Round 1
A20: Topic | B20: [What was argued about]
A21: Attack | B21: [The objection]
A22: Defense | B22: [How it was answered]
A23: Outcome | B23: [Select ▼]
A24: Round 2
A25: Topic | B25: [What was argued about]
A26: Attack | B26: [The objection]
A27: Defense | B27: [How it was answered]
A28: Outcome | B28: [Select ▼]
A29: Round 3
A30: Topic | B30: [What was argued about]
A31: Attack | B31: [The objection]
A32: Defense | B32: [How it was answered]
A33: Outcome | B33: [Select ▼]
A34: Round 4
A35: Topic | B35: [What was argued about]
A36: Attack | B36: [The objection]
A37: Defense | B37: [How it was answered]
A38: Outcome | B38: [Select ▼]
A39: Round 5
A40: Topic | B40: [What was argued about]
A41: Attack | B41: [The objection]
A42: Defense | B42: [How it was answered]
A43: Outcome | B43: [Select ▼]
A45: 💀 WHAT BROKE
A46: # | B46: What Broke | C46: How It Broke | D46: Severity | E46: Fixable?
A47: 1 | D47: [Select ▼] | E47: [Select ▼]
A48: 2 | D48: [Select ▼] | E48: [Select ▼]
A49: 3 | D49: [Select ▼] | E49: [Select ▼]
A50: 4 | D50: [Select ▼] | E50: [Select ▼]
A52: 🛡️ WHAT SURVIVED
A53: # | B53: What Survived | C53: Attack It Withstood | D53: Why It Held
A54: 1
A55: 2
A56: 3
A57: 4
A59: ⚖️ VERDICT
A60: Overall | B60: [Select ▼]
A61: Strongest Moment | B61: [The exchange where the thesis was most convincingly defended]
A62: Weakest Moment | B62: [The exchange where the thesis was most vulnerable]
A63: Attacker's Assessment | B63: [Did the attacker concede any ground?]
A64: New Kill Conditions | B64: [Add these to the Destruction Manual]

Sheet PAPER_II_ADVERSARIAL
A1: PAPER II: THE ADVERSARIAL RESPONSE
A2: The candidate steelmans the strongest objection, then lets the idea respond. If it survives, it earned survival. If it breaks, we learn where.
A4: §0 AXIOM DECLARATION
A5: Objector's Foundational Axiom | B5: [The bedrock assumption of the STRONGEST critic. Not a strawman.]
A6: My Foundational Axiom (from Paper I) | B6: [Restate for contrast]
A8: [F] FIND — THE STRONGEST OBJECTION
A9: What is the most damaging attack on Paper I's claim? Not a nitpick. The one that breaks the core argument.
A10: Objector's Position | B10: [2-3 paragraphs. Write AS the objector. Inhabit the worldview. Make the case as well as its best advocates would.]
A11: Why This Objection Is Serious | B11: [What specifically does it threaten? Which step does it attack? What breaks downstream?]
A13: Objector's Worldview Table
A14: Element | B14: Their Position
A15: Worldview | B15: [Select ▼]
A16: Core Assumption | B16: [e.g., Math is abstract, necessary, mind-independent, but not personal]
A17: What They Accept | B17: [Which of your premises they grant]
A18: Where They Break | B18: [The exact step where they diverge]
A20: [A] ADMIT — WHERE THEY'RE RIGHT
A21: Intellectual honesty requires acknowledging the objection's genuine force before responding.
A22: Concession 1 | B22: [Something genuinely true in their critique]
A23: Concession 2 | B23: [Something genuinely true in their critique]
A24: Concession 3 | B24: [Something genuinely true in their critique]
A26: What I Cannot Currently Answer | B26: [Residual gap. Name it. This is strength, not weakness.]
A28: [C] CLAIM — THE RESPONSE
A29: The objection fails because (one sentence):
A30: Core Rebuttal | B30: [One sentence. The core reason the objection doesn't hold.]
A32: Response 1 | B32: [Full argument. Show the logical chain. Identify where the objection's reasoning breaks.]
A33: Response 2 | B33: [Second independent argument. Different angle.]
A34: Response 3 | B34: [Third argument. Ideally flips the objection into evidence FOR your position.]
A36: [T] TEST — THE COLLISION
A37: Direct comparison:
A38: Criterion | B38: Paper I's Claim | C38: The Objection | D38: Who Wins?
A39: Explanatory scope | B39: [How well does it explain?] | C39: [How well does it explain?] | D39: [Select ▼]
A40: Internal consistency | B40: [Self-contradictions?] | C40: [Self-contradictions?] | D40: [Select ▼]
A41: Falsifiability | B41: [Can it be killed?] | C41: [Can it be killed?] | D41: [Select ▼]
A42: Cross-domain coherence | B42: [Does it hold across domains?] | C42: [Does it hold across domains?] | D42: [Select ▼]
A43: Predictive power | B43: [Does it predict new observations?] | C43: [Does it predict new observations?] | D43: [Select ▼]
A45: The Decisive Test | B45: [What single piece of evidence or logical step settles this?]
A47: [S] SNAP — KILL CONDITIONS (for both sides)
A48: What would kill MY response:
A49: # | B49: Kill Condition | C49: Threshold | D49: Status
A50: 1 | B50: [How to destroy this response] | C50: [What would count as evidence] | D50: [Select ▼]
A51: 2 | B51: [How to destroy this response] | C51: [What would count as evidence] | D51: [Select ▼]
A53: What would kill THE OBJECTION:
A54: # | B54: Kill Condition | C54: Threshold | D54: Status
A55: 1 | B55: [How to destroy the objection] | C55: [What would count as evidence] | D55: [Select ▼]
A56: 2 | B56: [How to destroy the objection] | C56: [What would count as evidence] | D56: [Select ▼]
A58: ⚖️ VERDICT
A59: Did the idea survive? | B59: [Select ▼]
A60: What was learned? | B60: [What's stronger now? What boundary was clarified?]
A61: What remains open? | B61: [Unresolved tensions that need future work]
A63: ✅ AUDIT BLOCK
A64: Format: Lowe FACTS Format v1.0 (Adversarial Variant)
A65: Thesis Unit: [auto from Paper I]
A66: Paper: II (Adversarial Response)
A67: Objector Worldview: [Named]
A68: Author: David Lowe
A69: Date: YYYY-MM-DD
A70: Survival Status: [Survived / Partially / Failed]
A71: Kill Conditions Met: [ ] Yes [ ] No

Sheet WORD_CLUSTERS
A1: PROFESSION WORD CLUSTERS — Semantic Trigger Engine
A2: Select a role → clusters auto-populate tags, search terms, and cognitive framing for analysis sections.
A4: 🧠 ROLE → CLUSTER MAPPING
A5: Role | B5: Cognitive Operator | C5: Term 1 | D5: Wt | E5: Term 2 | F5: Wt | G5: Term 3 | H5: Wt | I5: Term 4 | J5: Wt | K5: Term 5 | L5: Wt | M5: Term 6 | N5: Wt | O5: Term 7 | P5: Wt | Q5: Term 8 | R5: Wt | S5: Term 9 | T5: Wt | U5: Term 10 | V5: Wt | W5: Negative Tags (NOT these)
A6: Physicist | B6: Look for invariants | C6: field | D6: 0.9 | E6: energy | F6: 0.9 | G6: symmetry | H6: 0.9 | I6: conservation | J6: 0.9 | K6: interaction | L6: 0.8 | M6: force | N6: 0.8 | O6: entropy | P6: 0.8 | Q6: quantum | R6: 0.7 | S6: spacetime | T6: 0.7 | U6: tensor | V6: 0.7 | W6: precedent, liability, jurisdiction, statute, compliance
A7: Lawyer | B7: Look for rule violations | C7: precedent | D7: 0.9 | E7: statute | F7: 0.9 | G7: liability | H7: 0.9 | I7: jurisdiction | J7: 0.8 | K7: contract | L7: 0.8 | M7: evidence | N7: 0.8 | O7: argument | P7: 0.8 | Q7: interpretation | R7: 0.7 | S7: rights | T7: 0.7 | U7: compliance | V7: 0.7 | W7: entropy, tensor, spacetime, quantum, field
A8: Doctor | B8: Map symptoms → cause | C8: diagnosis | D8: 0.9 | E8: pathology | F8: 0.9 | G8: symptoms | H8: 0.9 | I8: treatment | J8: 0.8 | K8: prognosis | L8: 0.8 | M8: etiology | N8: 0.8 | O8: risk | P8: 0.8 | Q8: intervention | R8: 0.7 | S8: patient | T8: 0.7 | U8: clinical | V8: 0.7 | W8: tensor, recursion, equilibrium, spacetime, algorithm
A9: Engineer | B9: Build under constraints | C9: system | D9: 0.9 | E9: design | F9: 0.9 | G9: constraints | H9: 0.9 | I9: optimization | J9: 0.9 | K9: efficiency | L9: 0.8 | M9: failure | N9: 0.8 | O9: load | P9: 0.7 | Q9: architecture | R9: 0.7 | S9: process | T9: 0.7 | U9: implementation | V9: 0.7 | W9: precedent, statute, pathology, prognosis, conditioning
A10: Economist | B10: Model behavior under constraints | C10: supply | D10: 0.9 | E10: demand | F10: 0.9 | G10: equilibrium | H10: 0.9 | I10: incentive | J10: 0.9 | K10: utility | L10: 0.8 | M10: market | N10: 0.8 | O10: elasticity | P10: 0.7 | Q10: growth | R10: 0.7 | S10: scarcity | T10: 0.7 | U10: tradeoff | V10: 0.7 | W10: tensor, spacetime, pathology, diagnosis, recursion
A11: Psychologist | B11: Model internal systems | C11: cognition | D11: 0.9 | E11: behavior | F11: 0.9 | G11: bias | H11: 0.9 | I11: perception | J11: 0.8 | K11: memory | L11: 0.8 | M11: emotion | N11: 0.8 | O11: learning | P11: 0.7 | Q11: motivation | R11: 0.7 | S11: conditioning | T11: 0.7 | U11: identity | V11: 0.7 | W11: tensor, field, jurisdiction, statute, spacetime
A12: Computer Scientist | B12: Formalize process + transformation | C12: algorithm | D12: 0.9 | E12: complexity | F12: 0.9 | G12: data | H12: 0.8 | I12: structure | J12: 0.8 | K12: abstraction | L12: 0.8 | M12: computation | N12: 0.8 | O12: logic | P12: 0.8 | Q12: optimization | R12: 0.7 | S12: recursion | T12: 0.7 | U12: state | V12: 0.7 | W12: precedent, pathology, prognosis, jurisdiction, etiology
A13: Statistician | B13: Quantify uncertainty | C13: distribution | D13: 0.9 | E13: variance | F13: 0.9 | G13: correlation | H13: 0.9 | I13: inference | J13: 0.9 | K13: probability | L13: 0.8 | M13: regression | N13: 0.8 | O13: sampling | P13: 0.7 | Q13: noise | R13: 0.7 | S13: signal | T13: 0.7 | U13: model | V13: 0.7 | W13: precedent, statute, liability, pathology, jurisdiction
A15: 🔄 CROSS-DOMAIN INTERPRETATION ENGINE
A16: Same question → different interpretation engines. When a role is selected, THIS is how they read the claim.
A17: Role | B17: "Is this system fair?" | C17: "Is this claim true?" | D17: "Does this model work?" | E17: "What breaks first?" | F17: "What's missing?"
A18: Physicist | B18: symmetry / invariance | C18: conservation / measurement | D18: boundary conditions / stability | E18: entropy increase / phase transition | F18: force / field not accounted for
A19: Lawyer | B19: rights / liability / precedent | C19: evidence / burden of proof | D19: compliance / jurisdiction | E19: contract breach / statute conflict | F19: unaddressed counterargument
A20: Doctor | B20: harm / benefit balance | C20: differential diagnosis / etiology | D20: treatment efficacy / outcomes | E20: contraindication / side effect | F20: undiagnosed comorbidity
A21: Engineer | B21: load distribution / tolerance | C21: specification / test results | D21: efficiency / constraint satisfaction | E21: single point of failure / fatigue | F21: untested edge case
A22: Economist | B22: incentives / distribution | C22: equilibrium / market signal | D22: supply-demand match / elasticity | E22: perverse incentive / market failure | F22: externality not priced
A23: Psychologist | B23: perception / bias | C23: cognitive load / framing effect | D23: behavior change / conditioning | E23: cognitive dissonance / blind spot | F23: unconscious motivation
A24: Computer Scientist | B24: state access / permissions | C24: logical consistency / halting | D24: runtime / space complexity | E24: infinite loop / stack overflow | F24: unhandled edge case / null state
A25: Statistician | B25: distribution shape / selection bias | C25: p-value / confidence interval | D25: fit / residuals / prediction error | E25: overfitting / confound / noise | F25: unmeasured variable / power

Sheet 7Q_RIGOR_CARD
A1: 7Q RIGOR CARD
A2: 7Q LLM Maximum Rigor — Autonomous Analysis Engine
A4: 🏆 DISPLAY CARD
A5: Paper Title | B5: [Paper title]
A6: Confidence Label | B6: =IFERROR(IF(C88="","",C88),"")
A7: T Score (Final) | B7: =IFERROR(IF(C87="","",C87),"") | C7: CKG Score | D7: =IFERROR(IF(C85="","",C85),"")
A9: Core Claim
A10: Claim (short) | B10: [One sentence core claim]
A12: Strongest Q | B12: =IFERROR(IF(COUNTA(C36:C43)<8,"","Q"&MATCH(MAX(C36:C43),C36:C43,0)-1&" — "&INDEX(B36:B43,MATCH(MAX(C36:C43),C36:C43,0))&" ("&TEXT(MAX(C36:C43),"0.00")&")"),"")
A13: Weakest Q | B13: =IFERROR(IF(COUNTA(C36:C43)<8,"","Q"&MATCH(MIN(C36:C43),C36:C43,0)-1&" — "&INDEX(B36:B43,MATCH(MIN(C36:C43),C36:C43,0))&" ("&TEXT(MIN(C36:C43),"0.00")&")"),"")
A15: Kill Threat | B15: [kill count] kill conditions | Most dangerous:
A16: ISO Status | B16: [Select ▼] | C16: Domain Count | D16: [#]
A17: Bundled Claims | B17: [#] independently killable claims
A19: At A Glance
A20: Paper Type | B20: [Select ▼] | C20: Effective n | D20: [#]
A21: Decisive Test | B21: [One-line decisive test] | C21: Theory Mappings | D21: [#]
A22: 🔬 PHILOSOPHICAL CLASSIFICATION
A23: Before scoring — classify the claim. This determines which evidence types apply.
A24: Dimension | B24: Selection | C24: Description
A25: Ontological Status | C25: What kind of thing is being claimed?
A26: Epistemological Mode | C26: How do we know this? What justification type?
A27: Inquiry Type | C27: What is the claim doing?
A28: Scope | C28: How far does this apply?
A29: Cross-Domain Status | C29: Same structure appear in other domains?
A33: 📊 SCORING ENGINE
A34: Per-Question Scores (0.00 – 1.00)
A35: Q# | B35: Question | C35: Score | D35: Explanation
A36: Q0 | B36: Posture | D36: [Brief rationale]
A37: Q1 | B37: Identity | D37: [Brief rationale]
A38: Q2 | B38: Domain | D38: [Brief rationale]
A39: Q3 | B39: Assertion | D39: [Brief rationale]
A40: Q4 | B40: Evidence | D40: [Brief rationale]
A41: Q5 | B41: Dependencies | D41: [Brief rationale]
A42: Q6 | B42: Consequences | D42: [Brief rationale]
A43: Q7 | B43: Falsification | D43: [Brief rationale]
A45: 📝 THREE-CHANNEL EVIDENCE CALCULATOR
A46: Channel 1: Phenomenon Strength (PS)
A47: Component | B47: Score (0-1) | C47: Weight | D47: Weighted
A48: Reproducibility | C48: 0.4 | D48: =IF(B48="","",B48*C48)
A49: Effect Size | C49: 0.3 | D49: =IF(B49="","",B49*C49)
A50: Measurement Quality | C50: 0.3 | D50: =IF(B50="","",B50*C50)
A51: PS = | B51: =IF(COUNTA(B48:B50)=3,D48+D49+D50,"")
A53: Channel 2: Explanatory Depth (ED)
A54: Component | B54: Score (0-1) | C54: Weight | D54: Weighted
A55: Mechanism | C55: 0.4 | D55: =IF(B55="","",B55*C55)
A56: Constraints | C56: 0.3 | D56: =IF(B56="","",B56*C56)
A57: Scope | C57: 0.3 | D57: =IF(B57="","",B57*C57)
A58: ED = | B58: =IF(COUNTA(B55:B57)=3,D55+D56+D57,"")
A60: Channel 3: Experiential Coherence (EC)
A61: Component | B61: Score (0-1) | C61: Weight | D61: Weighted
A62: Consistency | C62: 0.25 | D62: =IF(B62="","",B62*C62)
A63: Stability | C63: 0.25 | D63: =IF(B63="","",B63*C63)
A64: Transformation | C64: 0.25 | D64: =IF(B64="","",B64*C64)
A65: Pattern | C65: 0.25 | D65: =IF(B65="","",B65*C65)
A66: EC = | B66: =IF(COUNTA(B62:B65)=4,D62+D63+D64+D65,"")
A68: ⚙️ CATEGORY WEIGHTS (dropdown → auto-weight)
A69: Category | B69: Selection | C69: Weight
A70: Entity Type | B70: [Select ▼] | C70: =IFERROR(VLOOKUP(B70,A98:B106,2,FALSE),"")
A71: Precision Level | B71: [Select ▼] | C71: =IFERROR(VLOOKUP(B71,C98:D102,2,FALSE),"")
A72: Evidence Type | B72: [Select ▼] | C72: =IFERROR(VLOOKUP(B72,E98:F110,2,FALSE),"")
A73: Terminus Type | B73: [Select ▼] | C73: =IFERROR(VLOOKUP(B73,G98:H105,2,FALSE),"")
A74: ISO Status | B74: [Select ▼] | C74: =IFERROR(VLOOKUP(B74,A113:B118,2,FALSE),"")
A76: 🎯 TRUTH SCORE CALCULATION
A77: Component | B77: Source | C77: Value
A78: S (Survivability) | B78: ← Q7 | C78: =IF(C43="","",C43)
A79: E (Evidence) | B79: ← Q4 | C79: =IF(C40="","",C40)
A80: L (Logic) | B80: ← Q3 × ED | C80: =IF(OR(C39="",B58=""),"",C39*B58)
A81: D (Dependencies) | B81: ← Q5 | C81: =IF(C41="","",C41)
A82: P (Predictions) | B82: ← Q6 | C82: =IF(C42="","",C42)
A83: C (Coherence) | B83: ← Q2 | C83: =IF(C38="","",C38)
A85: T_RAW | B85: (S+E+L+D+P+C) / 6 | C85: =IFERROR(IF(COUNTA(C78:C83)<6,"",(C78+C79+C80+C81+C82+C83)/6),"")
A86: Cross-Domain Multiplier | B86: ← from ISO Status | C86: =IF(C74="","",C74)
A87: T_FINAL | B87: T_RAW × Multiplier | C87: =IFERROR(IF(OR(C85="",C86=""),"",_xlfn.LET(_xlpm.raw,C85*C86,_xlpm.capped1,IF(AND(C43<>"",C43<0.3),MIN(_xlpm.raw,0.6),_xlpm.raw),_xlpm.capped2,IF(AND(C42<>"",C42<0.3),MIN(_xlpm.capped1,0.7),_xlpm.capped1),MIN(_xlpm.capped2,1))),"")
A88: Confidence Class | C88: =IFERROR(IF(C87="","",IF(C87>=0.85,"ESTABLISHED",IF(C87>=0.65,"WELL_SUPPORTED",IF(C87>=0.4,"TENTATIVE",IF(C87>=0.15,"SPECULATIVE","UNSUPPORTED"))))),"")
A89: ⚠️ CAPS & PENALTIES (auto-applied)
A90: Condition | B90: Trigger | C90: Effect | D90: Status
A91: WHY-PENALTY | B91: ED < 0.30 | C91: E_final capped at 0.50 | D91: =IF(B58="","",IF(B58<0.3,"⚠️ ACTIVE","✅ Clear"))
A92: NO_LIVED_VALIDITY | B92: EC < 0.10 | C92: FLAG — evidence untested in lived reality | D92: =IF(B66="","",IF(B66<0.1,"⚠️ ACTIVE","✅ Clear"))
A93: FALSIFICATION CAP | B93: Q7 < 0.30 | C93: T capped at 0.60 | D93: =IF(C43="","",IF(C43<0.3,"⚠️ ACTIVE","✅ Clear"))
A94: PREDICTION CAP | B94: Q6 < 0.30 | C94: T capped at 0.70 | D94: =IF(C42="","",IF(C42<0.3,"⚠️ ACTIVE","✅ Clear"))
A96: 📚 WEIGHT REFERENCE TABLES
A97: Entity Type | B97: Wt | C97: Precision | D97: Wt | E97: Evidence Type | F97: Wt | G97: Terminus Type | H97: Wt
A98: theorem | B98: 1 | C98: precise | D98: 1 | E98: experimental | F98: 1 | G98: axiom | H98: 1
A99: law | B99: 0.95 | C99: mathematical | D99: 0.85 | E99: mathematical | F99: 1 | G99: empirical | H99: 0.85
A100: equation | B100: 0.85 | C100: detailed | D100: 0.65 | E100: computational | F100: 0.85 | G100: brute_fact | H100: 0.7
A101: theory | B101: 0.75 | C101: basic | D101: 0.4 | E101: observational | F101: 0.8 | G101: consensus | H101: 0.4
A102: mechanism | B102: 0.7 | C102: vague | D102: 0 | E102: meta_analytic | F102: 0.8 | G102: authority | H102: 0.2
A103: observation | B103: 0.6 | E103: clinical | F103: 0.75 | G103: revelation* | H103: 0.15
A104: hypothesis | B104: 0.4 | E104: statistical | F104: 0.7 | G104: circular | H104: 0
A105: conjecture | B105: 0.3 | E105: historical | F105: 0.55 | G105: infinite | H105: 0
A106: claim | B106: 0.2 | E106: case_study | F106: 0.4
E107: testimonial | F107: 0.3
E108: phenomenological | F108: 0.25
E109: scriptural* | F109: 0.2
E110: analogical | F110: 0.15
A112: ISO Status | B112: Multiplier
A113: ISO-CONFIRMED 3+ | B113: 1.5
A114: ISO-CONFIRMED 2 | B114: 1.3
A115: ISO-PARALLEL 3+ | B115: 1.15
A116: ISO-PARALLEL 2 | B116: 1.05
...

Sheet 7Q_EVIDENCE_PROTOCOL
A1: 7Q EVIDENCE PROTOCOL — Per-Item Deep Analysis
A2: Evidence without explanation is incomplete. Explanation without evidence is speculation.
A4: Evidence Item ID | B4: [e.g. EV-001] | C4: Linked Sub-Claim | D4: [e.g. SC-001]
A5: Evidence Description | B5: [Brief description of this evidence item]
A7: §1 — PHILOSOPHICAL CLASSIFICATION
A8: Dimension | B8: Selection | C8: Description
A9: Ontological Status | C9: What kind of thing is claimed?
A10: Epistemological Mode | C10: How do we know this?
A11: Inquiry Type | C11: What is the claim doing?
A12: Scope | C12: How far does it apply?
A13: Cross-Domain Status | C13: Same structure in other domains?
A15: §2 — THREE-CHANNEL EVIDENCE SCORING
A16: CHANNEL 1: Phenomenon Strength (PS)
A17: Component | B17: Score | C17: Weight | D17: Detail | E17: Status
A18: Reproducibility | C18: 0.4 | D18: [# independent replications]
A19: Effect Size | C19: 0.3 | D19: [sigma / p-value / CI]
A20: Measurement Quality | C20: 0.3 | D20: [instrument / blinding / bias risk]
A21: PS = | B21: =IFERROR(IF(COUNTA(B18:B20)=3,B18*C18+B19*C19+B20*C20,""),"")
A23: CHANNEL 2: Explanatory Depth (ED)
A24: Component | B24: Score | C24: Weight | D24: Detail
A25: Mechanism | C25: 0.4 | D25: [described? formalized? type?]
A26: Constraints | C26: 0.3 | D26: [conservation / symmetry / boundary]
A27: Scope | C27: 0.3 | D27: [domains / novel predictions]
A28: ED = | B28: =IFERROR(IF(COUNTA(B25:B27)=3,B25*C25+B26*C26+B27*C27,""),"")
A30: CHANNEL 3: Experiential Coherence (EC)
A31: Component | B31: Score | C31: Weight | D31: Detail
A32: Consistency | C32: 0.25 | D32: [self-contradictions found?]
A33: Stability | C33: 0.25 | D33: [time tested / trend]
A34: Transformation | C34: 0.25 | D34: [measurable behavior change?]
A35: Pattern | C35: 0.25 | D35: [independent discoverers / cross-cultural?]
A36: EC = | B36: =IFERROR(IF(COUNTA(B32:B35)=4,B32*C32+B33*C33+B34*C34+B35*C35,""),"")
A38: §3 — COMPLETENESS & FINAL SCORE
A39: CF = (0.5 + 0.5×ED) × (0.5 + 0.5×EC) | B39: =IFERROR(IF(OR(B28="",B36=""),"",(0.5+0.5*B28)*(0.5+0.5*B36)),"") | C39: CF
A40: E_final = PS × CF | B40: =IFERROR(IF(OR(B21="",B39=""),"",_xlfn.LET(_xlpm.raw,B21*B39,_xlpm.capped,IF(AND(B28<>"",B28<0.3),MIN(_xlpm.raw,0.5),_xlpm.raw),_xlpm.capped)),"") | C40: E_final
A41: WHY-PENALTY active? | B41: ED < 0.3 → E_final capped at 0.50 | C41: =IF(AND(B28<>"",B28<0.3),"⚠️ WHY-PENALTY ACTIVE","")
A42: NO_LIVED_VALIDITY? | B42: EC < 0.1 → flag — evidence untested in reality | C42: =IF(AND(B36<>"",B36<0.1),"⚠️ NO LIVED VALIDITY","")
A44: §4 — FIVE EVIDENCE GATES
A45: Gate | B45: Question | C45: Response | D45: Detail / Notes
A46: E1: Identity | B46: What format is this evidence in? | C46: [format] | D46: [publication status / DOI / access]
A47: E2: Type | B47: What epistemic class? | D47: [weight in chain: primary/supporting/corroborating]
A48: E3: Strength | B48: How strong by its own standards? | D48: [key metric / methodological concerns]
A49: E4: Linkage | B49: How does it connect to the claim? | D49: [alt explanations / exclusion of alternatives]
A50: E5: Vulnerabilities | B50: What's wrong or missing? | C50: [flags] | D50: [critical gap / recommended action]
A52: §5 — COMPETING MODELS
A53: Exclusive to this claim? | B53: [Yes/No] | C53: Uniqueness
A54: Competing Theory | B54: Explains Same Evidence? | C54: What It Misses | D54: Decisive Test
A55: [Theory 1]
A56: [Theory 2]
A57: [Theory 3]
A59: §6 — EVIDENCE CHAIN AUDIT
A60: Channel | B60: Summary
A61: PS | B61: [What PS found]
A62: ED | B62: [What ED found]
A63: EC | B63: [What EC found]
A65: Independence Check
A66: Sources truly independent? | B66: [Yes/No] | C66: Independence Score
A67: Shared confounders | B67: [List shared upstream DNA]
A68: Shared methodology | B68: [Same dataset / instrument / lens?]
A69: Same author? | B69: [Yes/No]
A71: §7 — TRUTH SCORE CONTRIBUTION
A72: Component | B72: Source | C72: Value
A73: S (Survivability) | B73: Q7 falsifiability
A74: E (Evidence) | B74: Q4 E_final = PS × CF
A75: L (Logic) | B75: mean(Q3 assertion, Q4 ED)
A76: D (Dependencies) | B76: Q5 dependency chain depth
A77: P (Predictions) | B77: Q6 predictions generated
A78: C (Coherence) | B78: Q2 cross-domain coherence
A80: Overall Narrative
A81: [2-3 sentence plain language assessment of this evidence item]
A83: §8 — QUICK REFERENCE
A84: Dimension | B84: What It Asks | C84: Range | D84: Key Metric
A85: PS | B85: What do we observe? | C85: 0-1 | D85: Repro × Effect × Quality
A86: ED | B86: Why does it happen? | C86: 0-1 | D86: Mechanism × Constraints × Scope
A87: EC | B87: Does it hold in life? | C87: 0-1 | D87: Consistency × Stability × Trans × Pattern
A88: CF | B88: How complete? | C88: 0.25-1.0 | D88: (0.5+0.5×ED)(0.5+0.5×EC)
A89: E_final | B89: Total evidence | C89: 0-1 | D89: PS × CF
A91: ✅ AUDIT BLOCK
A92: Protocol Version | B92: 7Q Evidence Protocol v1.0
A93: Author | B93: David Lowe · POF 2828 · Theophysics
A94: Date | B94: 46102
A95: Principle | B95: "The method does not guarantee truth. It guarantees transparency."

Sheet 7Q_CLASSIFIER
A1: 7Q UNIVERSAL CLASSIFIER v2.0
A2: For anything in the system — ask these seven in order. Every object carries its own death warrant.
A4: Q1: WHAT IS IT? (Identity)
A5: Core Identity
A6: ID | B6: [PREFIX-DOMAIN-SEQ] | C6: e.g. TP-LAW-007, TP-AX-004
A7: Title
A8: Summary | B8: [One-sentence description]
A10: Entity Type
A11: Epistemic | C11: axiom | hypothesis | theory | claim | postulate
A12: Observational | C12: observation | evidence | evidence_bundle
A13: Formal | C13: definition | equation | law | mechanism | operator | ...
A14: Axiom Class
A16: Stability & Status
A17: Status | C17: draft → candidate → provisional → stable → canonical
A18: Last Reviewed
A20: Source Authority
A21: Author | B21: David Lowe
A22: Institution | B22: Theophysics Research Initiative
A23: Source Class
A24: Reliability (0-5) | C24: 5=highest (scripture=5, speculative=1)
A26: Mathematical Object
A27: Type
A28: Symbols | B28: [e.g. χ, Λ, Ω, G, C]
A29: Notation (LaTeX)
A30: Formalism
A32: Graph & Navigation
A33: Graph Node ID | B33: [e.g. TP_NODE_00214]
A34: Importance (1-5)
A35: Hub Note?
A37: AI Permissions
A38: Edit Metadata | B38: TRUE
A39: Edit Body | B39: FALSE
A40: Suggest Changes | B40: TRUE
A41: Auto-Classify | B41: TRUE
A43: Q2: WHAT DOMAIN IS IT IN? (Location)
A44: Domain
A45: Domain
A46: Subdomain | B46: [e.g. quantum_mechanics, christology]
A47: Scale
A48: Regime
A50: Cross-Domain Mapping
A51: Physics | B51: [e.g. entropy as sin decay]
A52: Theology | B52: [e.g. grace as negentropy]
A53: Consciousness | B53: [e.g. observer collapse]
A54: Biology | B54: [e.g. coherence in neural systems]
A55: Moral | B55: [e.g. entropy as sin]
A56: Information | B56: [e.g. Shannon limit correspondence]
A57: Mathematics | B57: [e.g. group symmetry breaking]
A59: Isomorphism
A60: Isomorphism Status
A61: Isomorphism Target | B61: [What it maps to in other domain]
A63: Temporal Scope
A64: Period | B64: [e.g. Second Temple Era, Modern Physics]
A65: Start
A66: End
A68: Q3: WHAT IS IT CLAIMING? (Assertion)
A69: Claim Classification
A70: Claim Type
A71: Question Type
A72: Precision Level
A73: Certainty Type
A74: Scope
A76: Mathematical Form
A77: Equation (LaTeX)
A78: Units
... A91: Symmetry Pair
A92: Ten Laws Mapping | B92: [e.g. 1, 5, 8]
A94: Q4: WHAT SUPPORTS IT? (Evidence)
A95: Evidence Classification
A96: Evidence Type | C96: empirical | experimental | observational | mathematical | logical | scriptural | historical | inferential
A97: Evidence Tier
A98: Sources | B98: [comma-separated source list]
A99: Replication Status
A100: Independent Lines | C100: 3 independent > 1 strong
A102: Evidence Types Present
A103: Mathematical
A104: Scriptural
A105: Historical
A106: Empirical
A107: Philosophical
A108: Computational
A110: Experimental Data
A111: Dataset | B111: [e.g. PEAR-LAB, GCP]
A112: n Trials
A113: Sigma (σ)
A114: p-value
A115: Effect Size
A117: Mathematical Proof
A118: Method
A119: Completeness
A120: Verified By
A122: Computational Tests
A123: Scripts | B123: [e.g. scripts/simulation_entropy.py]
A124: Datasets | B124: [e.g. datasets/gr_data.csv]
A125: Results | B125: [e.g. Mass matrix rank 8/10, drift < 1e-6]
A126: Platform | B126: [e.g. JAX/Colab, Wolfram, Python]
A128: Theophysics Correlations
A129: Experiment | B129: Trials/Replicas | C129: Sigma | D129: Relevant?
A130: PEAR_LAB
A131: GCP
...

Sheet 7Q_REVERSE_PROVE
A1: FIELD_ID | B1: TYPE | C1: LAYER | D1: DEPENDS_ON | E1: EXPORT_RULE | F1: 7Q REVERSE — PROVE
A2: _HEADER | B2: section | C2: PRESENT | D2: — | E2: skip | F2: Start with destruction. Let the thesis emerge from what's left standing.
A4: S1_HEADER | B4: section | C4: PRESENT | D4: — | E4: ## heading | F4: STEP 1 (Q7→): WHAT WOULD KILL IT? — DESTROY
A5: S1_PROMPT | B5: static | C5: PRESENT | D5: — | E5: > blockquote | F5: "Here is everything that could destroy this. Watch."
F7: Death Conditions Tested
F8: Death Type | G8: Test Description | H8: Result
A9: S1.SELF_REF | B9: select+text | C9: SCHEMA | D9: — | E9: yaml + body | F9: Self-Refutation
A10: S1.INF_REG | B10: select+text | C10: SCHEMA | D10: — | E10: yaml + body | F10: Infinite Regress
A11: S1.EMP_CON | B11: select+text | C11: SCHEMA | D11: — | E11: yaml + body | F11: Empirical Contradiction
A12: S1.LOG_INC | B12: select+text | C12: SCHEMA | D12: — | E12: yaml + body | F12: Logical Incoherence
A13: S1.UNSUP | B13: select+text | C13: SCHEMA | D13: — | E13: yaml + body | F13: Unsupported
F15: Exhaustive Branch Analysis
F16: # | G16: Branch | H16: Kill Method | I16: Status
A17: S1.BR1 | B17: text+select | C17: SCHEMA | D17: — | E17: yaml + body | F17: 1
A18: S1.BR2 | B18: text+select | C18: SCHEMA | D18: — | E18: yaml + body | F18: 2
F19: 3
F20: 4
F21: 5
F23: Falsification Summary
A24: S1.TOTAL_BR | B24: number | C24: LOGIC | D24: S1.BR1-5 | E24: yaml (computed) | F24: Total Branches Tested
A25: S1.KILLED | B25: computed | C25: LOGIC | D25: S1.BR*.status | E25: yaml (computed) | F25: Branches Killed
A26: S1.SURVIVING | B26: computed | C26: LOGIC | D26: S1.BR*.status | E26: yaml (computed) | F26: Branches Surviving
A28: S2_HEADER | B28: section | C28: PRESENT | D28: S1 complete | E28: ## heading | F28: STEP 2 (Q6→): WHAT DOES THE SURVIVOR FORCE? — FORCE
A29: S2_PROMPT | B29: static | C29: PRESENT | D29: — | E29: > blockquote | F29: "If this survives, these things must be true. Are they?"
F31: Forced Consequences
F32: # | G32: Consequence | H32: Verified?
A33: S2.CON1 | B33: text+select | C33: SCHEMA | D33: S1.* | E33: yaml + body | F33: 1
A34: S2.CON2 | B34: text+select | C34: SCHEMA | D34: S1.* | E34: yaml + body | F34: 2
F35: 3
F36: 4
F37: 5
A39: S2.NECESS | B39: free_text | C39: SCHEMA | D39: S1.SURVIVING | E39: body | F39: Necessary Implications | G39: [what logically follows with no escape]
A40: S2.PREDICT | B40: free_text | C40: SCHEMA | D40: S1.SURVIVING | E40: body | F40: Predictions Generated | G40: [testable downstream predictions]
A41: S2.DOWNSTRM | B41: free_text | C41: SCHEMA | D41: S1.SURVIVING | E41: body | F41: Downstream Objects Required | G41: [things that must exist if this is true]
A42: S2.CANT_AVOID | B42: free_text | C42: SCHEMA | D42: S1.SURVIVING | E42: body | F42: Cannot Avoid | G42: [inescapable outcomes]
A44: S3_HEADER | B44: section | C44: PRESENT | D44: S2 complete | E44: ## heading | F44: STEP 3 (Q5→): WHAT DOES IT DEPEND ON? — GROUND
F45: "These are the load-bearing walls. Test them."
F47: Required Foundations
A48: S3.AXIOM_DEP | B48: free_text | C48: SCHEMA | D48: — | E48: yaml | F48: Axiom Dependencies | G48: [by axiom ID]
A49: S3.LAW_DEP | B49: free_text | C49: SCHEMA | D49: — | E49: yaml | F49: Law Dependencies | G49: [by law number]
A50: S3.ASSUMPT | B50: free_text | C50: SCHEMA | D50: — | E50: body | F50: Assumptions Exposed | G50: [every hidden assumption, named]
F51: Boundary Conditions | G51: [BCs required]
A52: S3.WEAKEST | B52: free_text | C52: SCHEMA | D52: S3.AXIOM+LAW | E52: yaml (critical) | F52: Weakest Dependency | G52: [the one most likely to fail]
A54: S4_HEADER | B54: section | C54: PRESENT | D54: S3 complete | E54: ## heading | F54: STEP 4 (Q4→): WHAT SUPPORTS IT? — SUPPORT
F55: "You already know it survived destruction. Here is why it survived."
F57: Evidence Presented
F58: # | G58: Evidence | H58: Type | I58: Tier
A59: S4.EV1 | B59: text+2sel | C59: SCHEMA | D59: S1.SURVIVING | E59: yaml + body | F59: 1
F60: 2
F61: 3
F62: 4
F63: 5
F65: Evidence Summary
A66: S4.REPL_STAT | B66: select | C66: SCHEMA | D66: S4.EV* | E66: yaml | F66: Replication Status
A67: S4.STRONGEST | B67: free_text | C67: SCHEMA | D67: S4.EV* | E67: yaml (critical) | F67: Strongest Evidence | G67: [single most compelling line]
A69: S5_HEADER | B69: section | C69: PRESENT | D69: S4 complete | E69: ## heading | F69: STEP 5 (Q3→): WHAT IS IT CLAIMING? — STATE
F70: "This is not a hypothesis. This is what's left."
F72: The Conclusion
A73: S5.CLAIM | B73: free_text | C73: SCHEMA | D73: S1-S4 all | E73: yaml (critical) | F73: Claim Statement | G73: [the conclusion that survived]
A74: S5.TYPE | B74: select | C74: SCHEMA | D74: — | E74: yaml | F74: Claim Type
A75: S5.PRECISION | B75: select | C75: SCHEMA | D75: — | E75: yaml | F75: Precision Level
A76: S5.CERTAINTY | B76: select | C76: SCHEMA | D76: — | E76: yaml | F76: Certainty Type
A77: S5.SCOPE | B77: select | C77: SCHEMA | D77: — | E77: yaml | F77: Scope
A79: S6_HEADER | B79: section | C79: PRESENT | D79: S5 complete | E79: ## heading | F79: STEP 6 (Q2→): WHAT DOMAIN IS IT IN? — GENERALIZE
F80: "This isn't local. It survives across domains."
F82: Domain Validation
A83: S6.PRI_DOM | B83: select | C83: SCHEMA | D83: — | E83: yaml | F83: Primary Domain
F84: Additional Domains | G84: [comma-separated domains where it also holds]
F85: Scale Range | G85: [e.g. quantum → cosmological]
A86: S6.ISO_STAT | B86: select | C86: SCHEMA | D86: S6.CROSS_* | E86: yaml | F86: Isomorphism Status
F88: Cross-Domain Validation
F89: Domain | G89: How It Holds | H89: Validated?
A95: S7_HEADER | B95: section | C95: PRESENT | D95: S6 complete | E95: ## heading | F95: STEP 7 (Q1→): WHAT IS IT? — NAME
F96: "Now you know what it is. Because you watched everything else fail."
F98: Identity Earned
A99: S7.ID | B99: free_text | C99: SCHEMA | D99: S1-S6 all | E99: yaml (critical) | F99: ID | G99: [earned through survival]
A100: S7.TITLE | B100: free_text | C100: SCHEMA | D100: — | E100: yaml (critical) | F100: Title
A101: S7.FINAL_CLS | B101: select | C101: SCHEMA | D101: S1-S6 all | E101: yaml (critical) | F101: Final Classification
F102: Entity Type
A103: S7.CANONICAL | B103: free_text | C103: SCHEMA | D103: S7.FINAL_CLS | E103: yaml (critical) | F103: Canonical Statement | G103: [the thing that couldn't be killed is the thing that's true]
A105: COMPARE | B105: static | C105: PRESENT | D105: — | E105: table (optional) | F105: WHY THIS IS DIFFERENT
F107: Dimension | G107: Traditional Scientific Method | H107: 7Q Reverse (New Method)
F108: Starting point | G108: Start with hypothesis | H108: Start with destruction
F109: Method | G109: Try to confirm | H109: Try to kill
F110: Evidence role | G110: Evidence leads | H110: Evidence confirms
F111: Identity | G111: Identity assumed first | H111: Identity earned last
F112: Testing | G112: Survives one test | H112: Survives exhaustive elimination
F113: Validation | G113: Replication validates | H113: Survival validates
F114: Conclusion | G114: Conclusion at end | H114: Conclusion is what's left standing
F116: THE CORE PRINCIPLE
F117: Seven questions forward: classify anything.
F118: Seven questions reversed: prove anything.
F119: Same engine. Two directions. Nothing escapes.
A121: AUDIT | B121: static | C121: PRESENT | D121: — | E121: footer | F121: ✅ AUDIT BLOCK
F122: Template | G122: 7Q Reverse — Prove v2.0
F123: Direction | G123: REVERSE: death → consequence → dependency → evidence → assertion → location → identity
F124: Complement | G124: 7Q_CLASSIFIER (Forward — Classify)
F125: Authors | G125: David Lowe + Opus · POF 2828 · Theophysics

Sheet 7Q_REVERSE_PROVE_CLEAN
A1: 7Q REVERSE — PROVE
A2: Start with destruction. Let the thesis emerge from what's left standing.
A4: STEP 1 (Q7→): WHAT WOULD KILL IT? — DESTROY
A5: "Here is everything that could destroy this. Watch."
A7: Death Conditions Tested
A8: Death Type | B8: Test Description | C8: Result
A9: Self-Refutation
A10: Infinite Regress
A11: Empirical Contradiction
A12: Logical Incoherence
A13: Unsupported
A15: Exhaustive Branch Analysis
A16: # | B16: Branch | C16: Kill Method | D16: Status
A17: 1
A18: 2
A19: 3
A20: 4
A21: 5
A23: Falsification Summary
A24: Total Branches Tested
A25: Branches Killed
A26: Branches Surviving
A28: STEP 2 (Q6→): WHAT DOES THE SURVIVOR FORCE? — FORCE
A29: "If this survives, these things must be true. Are they?"
A31: Forced Consequences
A32: # | B32: Consequence | C32: Verified?
A33: 1
A34: 2
A35: 3
A36: 4
A37: 5
A39: Necessary Implications | B39: [what logically follows with no escape]
A40: Predictions Generated | B40: [testable downstream predictions]
A41: Downstream Objects Required | B41: [things that must exist if this is true]
A42: Cannot Avoid | B42: [inescapable outcomes]
A44: STEP 3 (Q5→): WHAT DOES IT DEPEND ON? — GROUND
A45: "These are the load-bearing walls. Test them."
A47: Required Foundations
A48: Axiom Dependencies | B48: [by axiom ID]
A49: Law Dependencies | B49: [by law number]
A50: Assumptions Exposed | B50: [every hidden assumption, named]
A51: Boundary Conditions | B51: [BCs required]
A52: Weakest Dependency | B52: [the one most likely to fail]
A54: STEP 4 (Q4→): WHAT SUPPORTS IT? — SUPPORT
A55: "You already know it survived destruction. Here is why it survived."
A57: Evidence Presented
A58: # | B58: Evidence | C58: Type | D58: Tier
A59: 1
A60: 2
A61: 3
A62: 4
A63: 5
A65: Evidence Summary
A66: Replication Status
A67: Strongest Evidence | B67: [single most compelling line]
A69: STEP 5 (Q3→): WHAT IS IT CLAIMING? — STATE
A70: "This is not a hypothesis. This is what's left."
A72: The Conclusion
A73: Claim Statement | B73: [the conclusion that survived]
A74: Claim Type
A75: Precision Level
A76: Certainty Type
A77: Scope
A79: STEP 6 (Q2→): WHAT DOMAIN IS IT IN? — GENERALIZE
A80: "This isn't local. It survives across domains."
A82: Domain Validation
A83: Primary Domain
A84: Additional Domains | B84: [comma-separated domains where it also holds]
A85: Scale Range | B85: [e.g. quantum → cosmological]
A86: Isomorphism Status
A88: Cross-Domain Validation
A89: Domain | B89: How It Holds | C89: Validated?
A95: STEP 7 (Q1→): WHAT IS IT? — NAME
A96: "Now you know what it is. Because you watched everything else fail."
A98: Identity Earned
A99: ID | B99: [earned through survival]
A100: Title
A101: Final Classification
A102: Entity Type
A103: Canonical Statement | B103: [the thing that couldn't be killed is the thing that's true]
A105: WHY THIS IS DIFFERENT
A107: Dimension | B107: Traditional Scientific Method | C107: 7Q Reverse (New Method)
A108: Starting point | B108: Start with hypothesis | C108: Start with destruction
A109: Method | B109: Try to confirm | C109: Try to kill
A110: Evidence role | B110: Evidence leads | C110: Evidence confirms
A111: Identity | B111: Identity assumed first | C111: Identity earned last
A112: Testing | B112: Survives one test | C112: Survives exhaustive elimination
A113: Validation | B113: Replication validates | C113: Survival validates
A114: Conclusion | B114: Conclusion at end | C114: Conclusion is what's left standing
A116: THE CORE PRINCIPLE
A117: Seven questions forward: classify anything.
A118: Seven questions reversed: prove anything.
A119: Same engine. Two directions. Nothing escapes.
A121: ✅ AUDIT BLOCK
A122: Template | B122: 7Q Reverse — Prove v2.0
A123: Direction | B123: REVERSE: death → consequence → dependency → evidence → assertion → location → identity
A124: Complement | B124: 7Q_CLASSIFIER (Forward — Classify)
A125: Authors | B125: David Lowe + Opus · POF 2828 · Theophysics

Sheet LOWE_FACTS_FORMAT
A1: THE LOWE FACTS FORMAT
A2: Transparent Academic Papers Through Explicit Axioms
A3: The method does not guarantee truth. It guarantees transparency.
A5: FACTS SUMMARY
A6: Letter | B6: Phase | C6: Purpose
A7: F | B7: FIND — State the anomaly | C7: What demands explanation?
A8: A | B8: ADMIT — Disclose bias | C8: Who is asking and why?
A9: C | B9: CLAIM — Make thesis explicit | C9: What exactly is being asserted?
A10: T | B10: TEST — Show your work | C10: How can this be checked?
A11: S | B11: SNAP — Provide kill conditions | C11: How can this be destroyed?
A13: CORE INNOVATION
A14: Forces Biaxiosum (explicit axiom declaration) rather than claimed objectivity with hidden assumptions.
A16: 📋 PAPER METADATA
A17: Paper ID
A18: Title
A19: Series
A20: Position | B20: [e.g., 3 of 7]
A21: Paper Type
A22: Author | B22: David Lowe
A23: Co-Author
A24: Version | B24: 1
A25: Date
A26: Status
A28: §0 AXIOM DECLARATION
A29: This is the bedrock assumption. If this is false, the entire paper fails.
A30: Foundational Axiom
A32: [F] FIND — THE ANOMALY
A33: What was observed? What pattern demands explanation?
A35: Observation
A36: Expected
A37: Actual
A38: Prior Explanations | B38: [What others have said — and why it's insufficient]
A39: What's New Here
A40: The Anomaly (2-3 paragraphs) | B40: [Write the core finding. No throat-clearing.]
A42: [A] ADMIT — THE BIAS
A43: Who is asking? What are their priors? Full worldview disclosure.
A45: Author Posture (Biaxiosum Declaration)
A46: Element | B46: Declaration
A47: Worldview
A48: Core Belief
A49: Epistemology
A50: Priors
A51: Off-Ramp
A52: Mea Culpa | B52: [Honest limitations — what you might be wrong about]
A54: [C] CLAIM — THE THESIS
A55: What is being asserted? What would follow if true/false?
A57: Primary Question | B57: [One question this paper answers]
A58: THESIS (one sentence) | B58: [The claim. No hedging.]
A59: Support 1
A60: Support 2
A61: Support 3
A63: Predictions
A64: If True → 1
A65: If True → 2
A66: If True → 3
A67: If False → 1
A68: If False → 2
A69: If False → 3
A71: [T] TEST — THE PROOF
A72: Show your work. Method is public. Data is accessible.
A74: Method | B74: [How was this investigated?]
A76: Tools Used
A77: Tool 1
A78: Tool 2
A79: Tool 3
A80: Tool 4
A82: Evidence Table
A83: # | B83: Domain / Variable | C83: Finding | D83: Metric | E83: Source
A84: 1
A85: 2
A86: 3
A87: 4
A88: 5
A89: 6
A90: 7
A92: Primary Finding | B92: [Main result in plain language]
A93: Unexpected | B93: [What you didn't expect to find]
A94: Null (no effect) | B94: [What returned nothing — intellectual honesty]
A95: Confidence
A97: [S] SNAP — THE KILL CONDITIONS
A98: How to destroy the argument. Explicit falsification criteria.
A100: # | B100: Kill Condition | C100: Threshold | D100: Status
A101: 1
A102: 2
A103: 3
A105: Explicit Invitation | B105: If you can satisfy any kill condition, this paper is falsified. I will publicly acknowledge the refutation.
A107: §XI REPLICATION
A108: How to Repeat This | B108: [Step-by-step replication instructions]
A110: The Lowe Battery
A111: Test | B111: Question | C111: Pass Condition | D111: Result
A112: LCT | B112: Does the domain show coherence decay over time?
A113: LFT | B113: Does constraint removal correlate with negative outcomes?
A114: LMT | B114: Can the model predict future states?
A116: §XII REFERENCES + APPENDICES
A117: Primary Sources
A118: Appendix A
A119: Appendix B
A121: ✅ AUDIT BLOCK
A122: Format | B122: Lowe FACTS Format v1.0
A123: Author | B123: David Lowe
...

Sheet AXIOM_DIAGRAMS
A1: AXIOM DIAGRAM TEMPLATES — 10 Canonical Shapes
A2: Each shape corresponds to a content type in the Canonical Tag Taxonomy.
A3: These templates can be used to auto-generate proof diagrams from axiom data.
A5: MASTER REFERENCE TABLE
A6: Shape | B6: Tag | C6: Callout | D6: Key Question
A7: Axiom (A) | B7: axiom | C7: [!axiom]- | D7: Can this be defeated? What does it open?
A8: Definition (D) | B8: definition | C8: — | D8: What does this mean and where does it go?
A9: Equation (E) | B9: equation | C9: [!equation]- | D9: What does each symbol represent?
A10: Proposition (P) | B10: hypothesis | C10: [!hypothesis]- | D10: How does this follow? What does it license?
A11: Theorem (T) | B11: hypothesis+verified | C11: [!hypothesis]- | D11: How is this proven? What does the proof open?
A12: Corollary (C) | B12: hypothesis+dependency | C12: [!hypothesis]- | D12: What does this add beyond its parent?
A13: Boundary Condition (BC) | B13: falsification | C13: [!falsification]- | D13: What satisfies this? What fails it?
A14: Law Note (LN) | B14: isomorphism | C14: [!isomorphism]- | D14: Where does established science say this?
A15: Protocol (PROT) | B15: prediction | C15: [!prediction]- | D15: What would actually break this?
A16: Evidence (EV) | B16: evidence | C16: [!evidence]- | D16: How strong is the support, honestly?
A18: SHAPE 1 — AXIOM (A)
A19: Claim under pressure — what attacks it, what it withstands, what it opens.
A20: Structure | B20: UPSTREAM → CLAIM → ATTACKS → HOLDS → ENABLES
A21: Upstream Dependency | B21: [None for primitives, or parent axiom]
A22: Claim Statement
A23: Attack Vector 1 | B23: [Steelmanned objection] | C23: Result
A24: Attack Vector 2 | C24: Result
A25: Attack Vector 3 | C25: Result
A26: Self-Refutation Trap | B26: [Does denying this axiom require using it?]
A27: Holds Because
A28: Enables 1
A29: Enables 2
A30: Enables 3
A32: SHAPE 2 — DEFINITION (D)
A33: Term at center, components radiating, downstream uses anchoring.
A34: Structure | B34: PARENT → TERM → COMPONENTS → USED_IN
A35: Parent Concept
A36: Term
A37: Component 1
A38: Component 2
A39: Component 3
A40: Used In 1
A41: Used In 2
A43: SHAPE 3 — EQUATION (E)
A44: Each variable gets its own node — domain, meaning, physical analogue.
A45: Structure | B45: EQUATION → VARIABLES (each with domain) → MEANING → ENABLES
A46: Equation
A47: Variable | B47: Domain | C47: Meaning | D47: Physical Analogue
A52: Enables
A54: SHAPE 4 — PROPOSITION (P)
A55: Inference path — what it follows from, what license it grants.
A56: Structure | B56: FROM_AXIOMS → INFERENCE_STEP → PROPOSITION → GRANTS
A57: From Axiom 1
A58: From Axiom 2
A59: Inference Step | B59: [How do these axioms combine?]
A60: Proposition
A61: Grants / Licenses | B61: [What can you now do or claim?]
A63: SHAPE 5 — THEOREM (T)
A64: Premises stack into conclusion, conclusion fans into corollaries.
A65: Structure | B65: PREMISES → PROOF_STEP → THEOREM → COROLLARIES + IMPLICATIONS
A66: Premise 1
A67: Premise 2
A68: Proof Step
A69: Theorem Statement
A70: Corollary 1
A71: Corollary 2
A72: Implication
A74: SHAPE 6 — COROLLARY (C)
A75: Parent → logical step → consequence → what it opens.
A76: Structure | B76: PARENT_THEOREM → STEP → COROLLARY → NEXT + OBJECTION
A77: Parent Theorem
A78: Logical Step
A79: Corollary Statement
A80: Opens / Next
A81: Objection | B81: [What could challenge this corollary specifically?]
A83: SHAPE 7 — BOUNDARY CONDITION (BC)
A84: What's constrained → requirement → what passes → what fails.
A85: Structure | B85: SYSTEM → BC → WHY + PASS + FAIL → NEXT
A86: System / Context
A87: Boundary Condition
A88: Why This Boundary
A89: Pass Condition
A90: Fail Condition
A91: Next
A93: SHAPE 8 — LAW NOTE (LN)
A94: Known physics on one side, χ-framework on the other, mapping in middle.
A95: Structure | B95: KNOWN_PHYSICS → MAPPING_BRIDGE → CHI_FRAMEWORK → WEIGHT
A96: Known Physics | B96: [Established law or principle]
A97: Mapping Bridge | B97: [How does the known physics map to the χ framework?]
A98: χ Framework Equivalent
A99: Isomorphism Weight
A101: SHAPE 9 — PROTOCOL (PROT)
A102: Theoretical claim → experiment → expected result → kill condition.
A103: Structure | B103: CLAIM → EXPERIMENT → PREDICTED + KILL_CONDITION → HONEST_ASSESSMENT
A104: Claim Being Tested
A105: Experiment / Test
A106: Predicted Result
A107: Kill Condition
A108: Honest Assessment
A110: SHAPE 10 — EVIDENCE (EV)
A111: Claim → data → methodology → what it proves and what it doesn't.
A112: Structure | B112: CLAIM → EVIDENCE → DATA + STRONG + WEAK → NET_WEIGHT
A113: Claim Supported
A114: Evidence / Data
A115: Methodology
...

Sheet AXIOM_CONTAINER_MODEL
A1: It's a lot simpler than what you think but it's a lot harder
A2: The axiom is the atom. Everything else is subatomic. Axioms flow left→right. Internal types stack vertically. Gaps are the signal.
A4: CANONICAL TYPE | B4: ▼ | C4: A3.1 — Order Requirement | D4: Depth | E4: ↔ | F4: ▼ | G4: A3.2 — Coherence Measure | H4: Depth | I4: ↔ | J4: ▼ | K4: A4.1 — [Next Axiom] | L4: Depth
A5: THE SPINE → | B5: ✅ | C5: Information must be organized to be meaningful | D5: 7 sect | E5: ━━▶ | F5: ✅ | G5: The universe tends toward organization | H5: 5 sect | I5: ━━▶ | J5: ⬜ | K5: [pending] | L5: —
A7: 2. Definition (D) | B7: ✅ | C7: Information, Logos Field, Coherence Functional | D7: 3 | E7: ── | F7: ✅ | G7: Coherence, C-functional, Organization Density | H7: 3 | I7: ── | J7: ⬜ | L7: —
A8: 3. Equation (E) | B8: ✅ | C8: K(x), I(meaning)=ΔK, Shannon H(X), Φ=IIT | D8: 4 | E8: ── | F8: ✅ | G8: C(χ) functional, dS/dt, V(χ) potential | H8: 3 | I8: ── | J8: ⬜ | L8: —
A9: 4. Proposition (P) | B9: ✅ | C9: Meaning ≠ randomness; compressibility = meaning | D9: 2 | E9: ── | F9: ✅ | G9: Universe minimizes complexity; coherence increases | H9: 2 | I9: ── | J9: ⬜ | L9: —
A10: 5. Theorem (T) | B10: ✅ | C10: T4.1: Laws are low-K descriptions of reality | D10: 1 | E10: ╱ | F10: ✅ | G10: Coherence theorem (formalized) | H10: 2 | I10: ── | J10: ⬜ | L10: —
A11: 6. Corollary (C) | B11: ✅ | C11: If order=meaning, then disorder=meaninglessness | D11: 1 | E11: ── | F11: ✅ | G11: If coherence increases, entropy locally decreases | H11: 1 | I11: ── | J11: ⬜ | L11: —
A12: 7. Boundary Cond (BC) | B12: ✅ | C12: C≥0, K≥0, scope=universal | D12: 3 | E12: ╲ | F12: ⚠️ | G12: Partial — needs entropy coupling constraint | H12: 1 | I12: ── | J12: ⬜ | L12: —
A13: 8. Law Note (LN) | B13: ✅ | C13: 2nd Law, Shannon, Penrose Weyl, Schrödinger | D13: 4 | E13: ── | F13: ✅ | G13: Prigogine, Boltzmann, dissipative structures | H13: 3 | I13: ── | J13: ⬜ | L13: —
A14: 9. Protocol (PROT) | B14: ✅ | C14: gzip test, IIT Φ measurement, compression ratio | D14: 3 | E14: ── | F14: ✅ | G14: Entropy measurement, C-functional tracking | H14: 2 | I14: ── | J14: ⬜ | L14: —
A15: 10. Evidence (EV) | B15: ✅ | C15: Shannon '48, Kolmogorov '65, Penrose, Tononi, Schrödinger | D15: 6 | E15: ╲ | F15: ✅ | G15: Prigogine, Boltzmann, dissipative obs. | H15: 3 | I15: ── | J15: ⬜ | L15: —
A17: SYMMETRY CHECK | B17: 46305 | C17: All types present • Depth: 34 total | F17: 46275 | G17: BC partial (gap) • Depth: 21 total | J17: 0/10 | K17: Empty — needs all types
A19: CONNECTOR LEGEND
A20: ── Straight | B20: Perfect mirror. Both axioms have this type at equal or near-equal depth.
A21: ╱ Up-slope | B21: Next axiom ADDS complexity. More depth, more detail, more formalization than predecessor.
A22: ╲ Down-slope | B22: Next axiom DROPS depth. Less evidence, less formalization. Gap signal — needs work or justified absence.
A23: ✖ Missing | B23: Type exists in one axiom but not the other. Hard gap. Either fill it or document why it's absent.
A25: STATUS ICONS
A26: ✅ Present | B26: Type fully populated with content
A27: ⚠️ Partial | B27: Type exists but incomplete — needs fortification
A28: ⬜ Empty | B28: Type not yet created for this axiom
A30: THE 5 RULES
A31: 1. Axiom-to-Axiom Only | B31: The spine is A→A→A. Internal types never connect across axioms directly.
A32: 2. Types Are Internal | B32: Expand an axiom → see its 10 types. Collapse it → one node on the spine.
A33: 3. Type-to-Type Symmetry | B33: Adjacent axioms' internals should mirror. Where they don't = gap = most valuable signal.
A34: 4. Mind Map at Axiom Level | B34: Click axiom → branches radiate. Missing branches visible. Gap = information.
A35: 5. Internal Causal Chain | B35: D→E→P→T→C within each axiom. Same order as the 10 shapes.

Sheet PUBLICATION_PIPELINE
A1: PUBLICATION PIPELINE — S01→S15
A2: Concept → Writing → Scoring → Adversarial → Integration → TTS → Media → Publish → Distribute
A4: PROJECT NAME
A5: Series
A6: Domain
A7: Current Step
A9: TASK | B9: STATUS | C9: NOTES / DETAIL | D9: GATE / SCORE | E9: DATE
A10: S01 — CONCEPT
A11: Paper or idea exists (document created, even rough)
A12: Working title assigned
A13: Tagged with primary domain
A14: Series identified (if applicable)
A16: S02 — WRITING
A17: Paper drafted — raw thought on the page
A18: Core argument articulated (what is the claim?)
A19: Court papers written (prosecution/defense structure)
A20: Biaxiosum / Page 0 finalized
A21: Destruction manual written (what should kill this idea?)
A22: Defense record started (how does it survive its own destruction?)
... A35: Axiom dependencies identified (which of the 189 axioms?)
A37: ⛔ S05 — SCORING — GATE 1 | D37: GATE 1
A38: BAES evaluation run
A39: Score recorded
A40: Score meets minimum threshold
A41: GATE DECISION | C41: PASS → S06 | FAIL → S02 or KILL | BORDERLINE → flag for adversarial
A43: ⛔ S06 — ADVERSARIAL REVIEW — GATE 2 | D43: GATE 2
A44: Adversarial AI pass completed (dedicated session)
A45: Steelman of strongest objections articulated
A46: Evidence tiering applied (T1: confirmed / T2: contested / T3: speculative)
A47: Inference gaps identified (logic leap vs. derivation)
A48: ISO classifications applied (ISO-confirmed / ISO-parallel / ISO-analogy)
A49: Adversarial report saved
A50: Author response to adversarial findings documented
A51: GATE DECISION | C51: PASS → S07 | FAIL → S02 or KILL | CONDITIONAL → specific repairs
A53: S07 — DATA ANALYTICS + STRUCTURAL AUDIT
A54: Run unification_audit_extract.py on target scope
A55: Metrics: Notes scanned / Semantic tags / Resolved links / Broken links
A56: Metrics: Weak claims / Claims fully covered
A57: Artifacts verified (index.html, claim_graph.json, collapse/weak JSONs, BRUTAL_REPORT.md)
A58: Analytics pipeline + vault health triage + knowledge graph complete
A59: Escalation check (weak claims ↑? broken links ↑? collapse shifts?)
A61: S08 — FRAMEWORK INTEGRATION
A62: Cross-file edits applied (Markdown, Excel, JSON, Google Sheets)
A63: New axioms inserted if needed; axiom count updated everywhere
A64: Dependency chains updated (depends_on, enables)
A65: Master Equation mapping — χ = ∭(G·M·E·S·T·K·R·Q·F·C)
... A113: Blog cross-post (if applicable)
A115: LINKED PAPERS | B115: Location | C115: Status
A120: NOTES
